Workbook
Name Ccy: #REF!
Name Conv: #REF!
Name Discount_Rate: #REF!
Name IQ_CH: 110000
Name IQ_CQ: 5000
Name IQ_CY: 10000
Name IQ_DAILY: 500000
Name IQ_FH: 100000
Name IQ_FQ: 500
Name IQ_FY: 1000
Name IQ_LTM: 2000
Name IQ_MONTH: 15000
Name IQ_NTM: 6000
Name IQ_WEEK: 50000
Name IQ_YTD: 3000
Name QFour: #REF!
Name Scenario: #REF!
Name SharePrice: #REF!
Name Tax: #REF!
Name Tax_Rate: #REF!
Name WACC: #REF!

Sheet Cover
C3: European Call Option Valuation | AAPL
C11: Cross-Method Pricing Analysis
C12: Black-Scholes-Merton · Binomial Tree · Monte Carlo

Sheet Important Comments
C3: Editure Limited | Important Comments
C5: =Cover!C5 -> 0
A7: x | C7: Overview
B9: x | C9: Key Assumptions (Due to Lack of Information in CIM)
C11: Assumption | D11: Value | E11: Commentary
C12: Comparable Company Analysis | D12: n.a. | E12: This method was not relied upon. Please see "Comps" tab for detailed explanation.
C13: Model Date | D13: 40999 | E13: Given that the CIM incorporates financials for Q1 2012, the model date was assumed to be March 31, 2012.
C14: General Model Assumptions | D14: Various | E14: Please see comments in specific cells throughout the model for explanations of minor assumptions.
C15: "Assumptions" Tab | D15: Various | E15: Please see additional commentary on the right side of the "Assumptions" tab that explains the though process behind assumptions
C16: Q4 2012E Allocation | D16: =3000/6892 -> 0.43528729 | E16: Given the model date of March 31, the valuation needed to include Q4 of 2012. However, there was no quarterly information available in the CIM except for 2013P EBITDA projections on Pg. 63, which indicated most earnings are generated in quarters 3 and 4 due to seasonality. As a result, Q4 2013P's EBITDA as a % of the total year's EBITDA was used as a proxy to allocate 2012E's yearly figures to Q4 of 2012. This method was deemed to be the best and only option, as the alternative was to not include Q4 numbers in the valuation at all, which was we believed would have been more inaccurate.
C17: Depreciation | D17: Equal to CapEx | E17: Since no depreciation information was provided in the CIM, depreciation was set equal to CapEx so that 1) FCF was not understated because of not adding back depreciation, 2) the tax saving of depreciation could be accounted for, and 3) depreciation and CapEx could be equal in the terminal year.
C18: Exit Multiple | D18: n.a. | E18: This method was completed for illustration and completion purposes only as it was not relied upon. There is no way to accurately estimate Editure's exit multiple given that comps were not public in 2012 and there is no trading history.
C19: Debt / Equity Split | D19: 0 | E19: Debt weighting was set at 0% as there was no long-term debt on balance sheet (did not count "Other Creditors" as debt). Additionally, there is no accurate way to estimate cost of debt without the interest rates on debts and/or interest expense on the income statement (could have approximated a debt rating). Due to this lack of information in the financials, it was more accurate to assume "Other Creditors" was not included in debt instead of assuming an arbitrary cost of debt.
C20: Beta | D20: 1.25 | E20: Given that 2012 public comparable companies were unavailable and that Editure itself is a private company, there were no public options for calculating beta. As a result, the only option was to reasonably estimate beta according to our experience in the finance industry. We believed that for a technology company, specifically one in the growing education technology space, a beta of 1.25 was a reasonable estimate. This represents its relatively higher volatility compared to the overall market. Additionally, out of the three comparable companies, only one (Learning Technologies Group) has a beta today, which is 1.33. Given that the outlook and performance of the technology sector is not the same today as it was in 2012, we used this figure as a sense check and determined it was reasonable to use a slightly lower figure of 1.25 for this valuation.
A23: x | B23: x

Sheet Summary
C3: AAPL $250 Call Option Valuation | Summary
C6: Base Case Valuation (Implied Vol)
C8: Method | D8: Theoretical Value | E8: Volatility Used
C9: Black-Scholes-Merton Model | D9: 22.63 | E9: ='Option Monitor'!F7/100 -> 0.31072491
C10: Binomial Tree | D10: 22.64 | E10: ='Option Monitor'!F7/100 -> 0.31072491
C11: Monte Carlo | D11: ='Monte Carlo'!K25 -> 22.594179 | E11: ='Option Monitor'!F7/100 -> 0.31072491
C13: Alternative Case Cross-Check (Historical Vol)
C15: Method | D15: Theoretical Value | E15: Volatility Used
C16: Black-Scholes-Merton Model | D16: 16.74 | E16: ='Historical Prices'!F9 -> 0.22560599
C17: Binomial Tree | D17: 16.76 | E17: ='Historical Prices'!F9 -> 0.22560599
C18: Monte Carlo | D18: ='Monte Carlo'!K26 -> 16.711456 | E18: ='Historical Prices'!F9 -> 0.22560599
C20: Observed Bloomberg Market Price Midpoint (IV = 31.07%) | D20: =('Option Monitor'!C7+'Option Monitor'!D7)/2 -> 22.650001

Sheet Models>>

Sheet _CIQHiddenCacheSheet
A1: 80 | B1: BAABTAVMT0NBTAFI/////wFQcQEAACZDSVEuT006QVJKTyBCLklRX0JBU0lDX0VQU19FU1QuSVFfTlRNLgUAAAAAAAAACAAAABYoSW52YWxpZCBGb3JtdWxhIE5hbWUpnWqa/Qpl2gjnuQLoKWXaCCVDSVEuS0xTRTpMS0wuSVFfQkFTSUNfRVBTX0VTVC5JUV9OVE0uBQAAAAAAAAAIAAAAFihJbnZhbGlkIEZvcm11bGEgTmFtZSmdapr9CmXaCC0eAugpZdoIJUNJUS5UU0U6NzgxMy5JUV9CQVNJQ19FUFNfRVNULklRX05UTS4FAAAAAAAAAAgAAAAWKEludmFsaWQgRm9ybXVsYSBOYW1lKZ1qmv0KZdoIB2wC6Cll2ggkQ0lRLlRTWDpTSVMuSVFfQkFTSUNfRVBTX0VTVC5JUV9OVE0uBQAAAAAAAAAIAAAAFihJbnZhbGlkIEZvcm11bGEgTmFtZSmdapr9CmXaCIjmAOgpZdoIJUNJUS5UU0U6NzgxNy5JUV9CQVNJQ19FUFNfRVNULklRX05UTS4FAAAAAAAAAAgAAAAWKEludmFsaWQgRm9ybXVsYSBOYW1lKZ1qmv0KZdoI+ZIC6Cll2ggvQ0lRLlRTRTo3ODE3LklRX0JBU0lDX0VQU19FU1QuSVFfTlRNLjIwMjItMDctMTMFAAAAAAAAAAgAAAAWKEludmFsaWQgRm9ybXVsYSBOYW1lKaO4mecpZdoINqnp9yll2gguQ0lRLlRTWDpTSVMuSVFfQkFTSUNfRVBTX0VTVC5JUV9OVE0uMjAyMi0wNy0xMwUAAAAAAAAACAAAABYoSW52YWxpZCBGb3JtdWxhIE5hbWUpo7iZ5yll2gg7lOr3KWXaCC9DSVEuVFNFOjc4MTMuSVFf | C1: QkFTSUNfRVBTX0VTVC5JUV9OVE0uMjAyMi0wNy0xMwUAAAAAAAAACAAAABYoSW52YWxpZCBGb3JtdWxhIE5hbWUpo7iZ5yll2gjn0en3KWXaCC9DSVEuS0xTRTpMS0wuSVFfQkFTSUNfRVBTX0VTVC5JUV9OVE0uMjAyMi0wNy0xMwUAAAAAAAAACAAAABYoSW52YWxpZCBGb3JtdWxhIE5hbWUpo7iZ5yll2ggh9+n3KWXaCDBDSVEuT006QVJKTyBCLklRX0JBU0lDX0VQU19FU1QuSVFfTlRNLjIwMjItMDctMTMFAAAAAAAAAAgAAAAWKEludmFsaWQgRm9ybXVsYSBOYW1lKaO4mecpZdoIhIPp9yll2ggjQ0lRLk5BU0RBUUdTOkFNU0MuSVFfTEFTVFNBTEVQUklDRS4BAAAAdYgAAAIAAAAENC44NACdapr9CmXaCEqpAegpZdoIFENJUS5OWVNFOkZMUi5JUV9URVYuAQAAACsBCgACAAAACjI1NTIuMDI0MzQBBgAAAAUAAAABMQEAAAALLTIwOTg0NDYxNjADAAAAAzE2MAIAAAAGMTAwMDYwBAAAAAEwBwAAAAk3LzEzLzIwMjKdapr9CmXaCIjmAOgpZdoIHkNJUS5LTFNFOkxLTC5JUV9MQVNUU0FMRVBSSUNFLgEAAABcWQITAgAAAAUwLjA0NQCdapr9CmXaCAdsAugpZdoIH0NJUS5OQVNEQVFHUzpBTVNDLklRX01BUktFVENBUC4BAAAAdYgAAAIAAAAKMTM4LjA5MzYwMgEGAAAABQAAAAExAQAAAAstMjA5Mjc1ODc4NQMAAAADMTYwAgAAAAYxMDAwNTQEAAAAATAHAAAACTcvMTMvMjAyMp1qmv0KZdoISqkB6Cll2gga | D1: Q0lRLk5ZU0U6RkxSLklRX01BUktFVENBUC4BAAAAKwEKAAIAAAALMzI5Ni4wMjQzNDEBBgAAAAUAAAABMQEAAAALLTIwOTg0NDYxNjADAAAAAzE2MAIAAAAGMTAwMDU0BAAAAAEwBwAAAAk3LzEzLzIwMjKdapr9CmXaCIjmAOgpZdoIGkNJUS5LTFNFOkxLTC5JUV9NQVJLRVRDQVAuAQAAAFxZAhMCAAAACTQzLjcyMjAyNwEGAAAABQAAAAExAQAAAAstMjA5Mzc0OTcyNAMAAAADMTExAgAAAAYxMDAwNTQEAAAAATAHAAAACTcvMTMvMjAyMp1qmv0KZdoIB2wC6Cll2ggZQ0lRLk5BU0RBUUdTOkFNU0MuSVFfVEVWLgEAAAB1iAAAAgAAAAoxMDEuMzExNjAyAQYAAAAFAAAAATEBAAAACy0yMDkyNzU4Nzg1AwAAAAMxNjACAAAABjEwMDA2MAQAAAABMAcAAAAJNy8xMy8yMDIynWqa/Qpl2ghKqQHoKWXaCBRDSVEuS0xTRTpMS0wuSVFfVEVWLgEAAABcWQITAgAAAAkzMS43NjgwMjcBBgAAAAUAAAABMQEAAAALLTIwOTM3NDk3MjQDAAAAAzExMQIAAAAGMTAwMDYwBAAAAAEwBwAAAAk3LzEzLzIwMjKdapr9CmXaCE1GAugpZdoIHkNJUS5OWVNFOkdWQS5JUV9MQVNUU0FMRVBSSUNFLgEAAAC6NQQAAgAAAAUyOC40OACdapr9CmXaCKNxAOgpZdoIGkNJUS5OWVNFOkdWQS5JUV9NQVJLRVRDQVAuAQAAALo1BAACAAAACzEyOTEuOTc4OTA5AQYAAAAFAAAAATEBAAAACy0yMDk5ODI0MTMxAwAAAAMxNjACAAAABjEwMDA1 | E1: NAQAAAABMAcAAAAJNy8xMy8yMDIynWqa/Qpl2gijcQDoKWXaCBRDSVEuTllTRTpHVkEuSVFfVEVWLgEAAAC6NQQAAgAAAAsxMDcyLjk1MzkwOQEGAAAABQAAAAExAQAAAAstMjA5OTgyNDEzMQMAAAADMTYwAgAAAAYxMDAwNjAEAAAAATAHAAAACTcvMTMvMjAyMp1qmv0KZdoIGCQA6Cll2ggeQ0lRLlRTRTo3ODE3LklRX0xBU1RTQUxFUFJJQ0UuAQAAAJ1zDQACAAAABDIzMjQAnWqa/Qpl2gjnuQLoKWXaCBpDSVEuVFNFOjc4MTcuSVFfTUFSS0VUQ0FQLgEAAACdcw0AAgAAAAwxMzUxMzcuMjc2NjgBBgAAAAUAAAABMQEAAAALLTIwODk3ODQ0MTEDAAAAAjc5AgAAAAYxMDAwNTQEAAAAATAHAAAACTcvMTMvMjAyMp1qmv0KZdoI57kC6Cll2ggfQ0lRLlRXU0U6NDEwNi5JUV9MQVNUU0FMRVBSSUNFLgEAAAAqQjYBAgAAAAQyNC4zAJ1qmv0KZdoILR4C6Cll2ggUQ0lRLlRTRTo3ODE3LklRX1RFVi4BAAAAnXMNAAIAAAALODcyMDMuMjc2NjgBBgAAAAUAAAABMQEAAAALLTIwODk3ODQ0MTEDAAAAAjc5AgAAAAYxMDAwNjAEAAAAATAHAAAACTcvMTMvMjAyMp1qmv0KZdoI57kC6Cll2ggbQ0lRLlRXU0U6NDEwNi5JUV9NQVJLRVRDQVAuAQAAACpCNgECAAAACzI0NTIuMTUwODM1AQYAAAAFAAAAATEBAAAACy0yMDkxNTYxOTEzAwAAAAMxNTYCAAAABjEwMDA1NAQAAAABMAcAAAAJNy8xMy8yMDIynWqa/Qpl2gjO | F1: +AHoKWXaCB1DSVEuVFNYOlNJUy5JUV9MQVNUU0FMRVBSSUNFLgEAAABIgDAAAgAAAAUxMi4zNQCdapr9CmXaCH80AegpZdoIFUNJUS5UV1NFOjQxMDYuSVFfVEVWLgEAAAAqQjYBAgAAAAsyNDQ1Ljk5OTgzNQEGAAAABQAAAAExAQAAAAstMjA5MTU2MTkxMwMAAAADMTU2AgAAAAYxMDAwNjAEAAAAATAHAAAACTcvMTMvMjAyMp1qmv0KZdoIzvgB6Cll2ggbQ0lRLk9NOkFSSk8gQi5JUV9NQVJLRVRDQVAuAQAAAFOW8Q4CAAAADDE5NDA2LjMzMjA3NgEGAAAABQAAAAExAQAAAAstMjEwMjI2NTgxNgMAAAADMTM3AgAAAAYxMDAwNTQEAAAAATAHAAAACTcvMTMvMjAyMp1qmv0KZdoI0AcD6Cll2ggZQ0lRLlRTWDpTSVMuSVFfTUFSS0VUQ0FQLgEAAABIgDAAAgAAAAk3OTUuMDcwMTkBBgAAAAUAAAABMQEAAAALLTIwOTczNjQ2NzgDAAAAAjI3AgAAAAYxMDAwNTQEAAAAATAHAAAACTcvMTMvMjAyMp1qmv0KZdoIfzQB6Cll2ggTQ0lRLlRTWDpTSVMuSVFfVEVWLgEAAABIgDAAAgAAAAsxMTY1LjI5ODE4OQEGAAAABQAAAAExAQAAAAstMjA5NzM2NDY3OAMAAAACMjcCAAAABjEwMDA2MAQAAAABMAcAAAAJNy8xMy8yMDIynWqa/Qpl2gh/NAHoKWXaCB5DSVEuVFNFOjc4MTMuSVFfTEFTVFNBTEVQUklDRS4BAAAAFP8dAwIAAAADODEzAJ1qmv0KZdoI+ZIC6Cll2ggfQ0lRLk9NOkFSSk8gQi5JUV9MQVNUU0FMRVBS | G1: SUNFLgEAAABTlvEOAgAAAAU3MS4yNQCdapr9CmXaCNAHA+gpZdoIGkNJUS5UU0U6NzgxMy5JUV9NQVJLRVRDQVAuAQAAABT/HQMCAAAACzI4NzMuMDgyNjUxAQYAAAAFAAAAATEBAAAACy0yMDk1MzI2MTQ4AwAAAAI3OQIAAAAGMTAwMDU0BAAAAAEwBwAAAAk3LzEzLzIwMjKdapr9CmXaCPmSAugpZdoIFUNJUS5PTTpBUkpPIEIuSVFfVEVWLgEAAABTlvEOAgAAAAwyNDI3MS4zMzIwNzYBBgAAAAUAAAABMQEAAAALLTIxMDIyNjU4MTYDAAAAAzEzNwIAAAAGMTAwMDYwBAAAAAEwBwAAAAk3LzEzLzIwMjKdapr9CmXaCNAHA+gpZdoIFENJUS5UU0U6NzgxMy5JUV9URVYuAQAAABT/HQMCAAAACzM5MTYuMDgyNjUxAQYAAAAFAAAAATEBAAAACy0yMDk1MzI2MTQ4AwAAAAI3OQIAAAAGMTAwMDYwBAAAAAEwBwAAAAk3LzEzLzIwMjKdapr9CmXaCPmSAugpZdoIHkNJUS5OWVNFOkZMUi5JUV9MQVNUU0FMRVBSSUNFLgEAAAArAQoAAgAAAAUyMy4yMQCdapr9CmXaCIjmAOgpZdoIKENJUS5OWVNFOkZMUi5JUV9MQVNUU0FMRVBSSUNFLjIwMjItMDctMTMBAAAAKwEKAAIAAAAFMjMuMjEAo7iZ5yll2gg7lOr3KWXaCB5DSVEuVFNFOjc4MTMuSVFfVEVWLjIwMjItMDctMTMBAAAAFP8dAwIAAAALMzkxNi4wODI2NTEBBgAAAAUAAAABMQEAAAALLTIwOTUzMjYxNDgDAAAAAjc5AgAAAAYxMDAwNjAEAAAAATAHAAAACTcv | H1: MTMvMjAyMqO4mecpZdoINqnp9yll2ggfQ0lRLk9NOkFSSk8gQi5JUV9URVYuMjAyMi0wNy0xMwEAAABTlvEOAgAAAAwyNDI3MS4zMzIwNzYBBgAAAAUAAAABMQEAAAALLTIxMDIyNjU4MTYDAAAAAzEzNwIAAAAGMTAwMDYwBAAAAAEwBwAAAAk3LzEzLzIwMjKjuJnnKWXaCEVb6fcpZdoIJENJUS5UU0U6NzgxMy5JUV9NQVJLRVRDQVAuMjAyMi0wNy0xMwEAAAAU/x0DAgAAAAsyODczLjA4MjY1MQEGAAAABQAAAAExAQAAAAstMjA5NTMyNjE0OAMAAAACNzkCAAAABjEwMDA1NAQAAAABMAcAAAAJNy8xMy8yMDIyo7iZ5yll2gg2qen3KWXaCClDSVEuT006QVJKTyBCLklRX0xBU1RTQUxFUFJJQ0UuMjAyMi0wNy0xMwEAAABTlvEOAgAAAAU3MS4yNQCjuJnnKWXaCEVb6fcpZdoIKENJUS5UU0U6NzgxMy5JUV9MQVNUU0FMRVBSSUNFLjIwMjItMDctMTMBAAAAFP8dAwIAAAADODEyAKO4mecpZdoINqnp9yll2ggdQ0lRLlRTWDpTSVMuSVFfVEVWLjIwMjItMDctMTMBAAAASIAwAAIAAAALMTE2NS4yOTgxODkBBgAAAAUAAAABMQEAAAALLTIwOTczNjQ2NzgDAAAAAjI3AgAAAAYxMDAwNjAEAAAAATAHAAAACTcvMTMvMjAyMqO4mecpZdoIBmzq9yll2ggjQ0lRLlRTWDpTSVMuSVFfTUFSS0VUQ0FQLjIwMjItMDctMTMBAAAASIAwAAIAAAAJNzk1LjA3MDE5AQYAAAAFAAAAATEBAAAACy0yMDk3MzY0Njc4AwAAAAIy | I1: NwIAAAAGMTAwMDU0BAAAAAEwBwAAAAk3LzEzLzIwMjKjuJnnKWXaCAZs6vcpZdoIJUNJUS5PTTpBUkpPIEIuSVFfTUFSS0VUQ0FQLjIwMjItMDctMTMBAAAAU5bxDgIAAAAMMTk0MDYuMzMyMDc2AQYAAAAFAAAAATEBAAAACy0yMTAyMjY1ODE2AwAAAAMxMzcCAAAABjEwMDA1NAQAAAABMAcAAAAJNy8xMy8yMDIyo7iZ5yll2ghFW+n3KWXaCB9DSVEuVFdTRTo0MTA2LklRX1RFVi4yMDIyLTA3LTEzAQAAACpCNgECAAAACzI0NDUuOTk5ODM1AQYAAAAFAAAAATEBAAAACy0yMDkxNTYxOTEzAwAAAAMxNTYCAAAABjEwMDA2MAQAAAABMAcAAAAJNy8xMy8yMDIyo7iZ5yll2ggh9+n3KWXaCCdDSVEuVFNYOlNJUy5JUV9MQVNUU0FMRVBSSUNFLjIwMjItMDctMTMBAAAASIAwAAIAAAAFMTIuMzUAo7iZ5yll2ggGbOr3KWXaCCVDSVEuVFdTRTo0MTA2LklRX01BUktFVENBUC4yMDIyLTA3LTEzAQAAACpCNgECAAAACzI0NTIuMTUwODM1AQYAAAAFAAAAATEBAAAACy0yMDkxNTYxOTEzAwAAAAMxNTYCAAAABjEwMDA1NAQAAAABMAcAAAAJNy8xMy8yMDIyo7iZ5yll2ggh9+n3KWXaCB5DSVEuVFNFOjc4MTcuSVFfVEVWLjIwMjItMDctMTMBAAAAnXMNAAIAAAALODcyMDMuMjc2NjgBBgAAAAUAAAABMQEAAAALLTIwODk3ODQ0MTEDAAAAAjc5AgAAAAYxMDAwNjAEAAAAATAHAAAACTcvMTMvMjAyMqO4mecpZdoIhIPp | J1: 9yll2ggpQ0lRLlRXU0U6NDEwNi5JUV9MQVNUU0FMRVBSSUNFLjIwMjItMDctMTMBAAAAKkI2AQIAAAAEMjQuMQCjuJnnKWXaCCH36fcpZdoIJENJUS5UU0U6NzgxNy5JUV9NQVJLRVRDQVAuMjAyMi0wNy0xMwEAAACdcw0AAgAAAAwxMzUxMzcuMjc2NjgBBgAAAAUAAAABMQEAAAALLTIwODk3ODQ0MTEDAAAAAjc5AgAAAAYxMDAwNTQEAAAAATAHAAAACTcvMTMvMjAyMqO4mecpZdoIhIPp9yll2ggoQ0lRLlRTRTo3ODE3LklRX0xBU1RTQUxFUFJJQ0UuMjAyMi0wNy0xMwEAAACdcw0AAgAAAAQyMzM2AKO4mecpZdoIhIPp9yll2ggeQ0lRLk5ZU0U6R1ZBLklRX1RFVi4yMDIyLTA3LTEzAQAAALo1BAACAAAACzEwNzIuOTUzOTA5AQYAAAAFAAAAATEBAAAACy0yMDk5ODI0MTMxAwAAAAMxNjACAAAABjEwMDA2MAQAAAABMAcAAAAJNy8xMy8yMDIyo7iZ5yll2ggxu+r3KWXaCCRDSVEuTllTRTpHVkEuSVFfTUFSS0VUQ0FQLjIwMjItMDctMTMBAAAAujUEAAIAAAALMTI5MS45Nzg5MDkBBgAAAAUAAAABMQEAAAALLTIwOTk4MjQxMzEDAAAAAzE2MAIAAAAGMTAwMDU0BAAAAAEwBwAAAAk3LzEzLzIwMjKjuJnnKWXaCDuU6vcpZdoIKENJUS5OWVNFOkdWQS5JUV9MQVNUU0FMRVBSSUNFLjIwMjItMDctMTMBAAAAujUEAAIAAAAFMjguNDgAo7iZ5yll2gg7lOr3KWXaCB5DSVEuS0xTRTpMS0wuSVFfVEVWLjIwMjIt | K1: MDctMTMBAAAAXFkCEwIAAAAJMzEuNzY4MDI3AQYAAAAFAAAAATEBAAAACy0yMDkzNzQ5NzI0AwAAAAMxMTECAAAABjEwMDA2MAQAAAABMAcAAAAJNy8xMy8yMDIyo7iZ5yll2ggh9+n3KWXaCCNDSVEuTkFTREFRR1M6QU1TQy5JUV9URVYuMjAyMi0wNy0xMwEAAAB1iAAAAgAAAAoxMDEuMzExNjAyAQYAAAAFAAAAATEBAAAACy0yMDkyNzU4Nzg1AwAAAAMxNjACAAAABjEwMDA2MAQAAAABMAcAAAAJNy8xMy8yMDIyo7iZ5yll2ghWRer3KWXaCCRDSVEuS0xTRTpMS0wuSVFfTUFSS0VUQ0FQLjIwMjItMDctMTMBAAAAXFkCEwIAAAAJNDMuNzIyMDI3AQYAAAAFAAAAATEBAAAACy0yMDkzNzQ5NzI0AwAAAAMxMTECAAAABjEwMDA1NAQAAAABMAcAAAAJNy8xMy8yMDIyo7iZ5yll2gjn0en3KWXaCCRDSVEuTllTRTpGTFIuSVFfTUFSS0VUQ0FQLjIwMjItMDctMTMBAAAAKwEKAAIAAAALMzI5Ni4wMjQzNDEBBgAAAAUAAAABMQEAAAALLTIwOTg0NDYxNjADAAAAAzE2MAIAAAAGMTAwMDU0BAAAAAEwBwAAAAk3LzEzLzIwMjKjuJnnKWXaCDuU6vcpZdoIKUNJUS5OQVNEQVFHUzpBTVNDLklRX01BUktFVENBUC4yMDIyLTA3LTEzAQAAAHWIAAACAAAACjEzOC4wOTM2MDIBBgAAAAUAAAABMQEAAAALLTIwOTI3NTg3ODUDAAAAAzE2MAIAAAAGMTAwMDU0BAAAAAEwBwAAAAk3LzEzLzIwMjKjuJnnKWXaCFZF6vcpZdoI | L1: KENJUS5LTFNFOkxLTC5JUV9MQVNUU0FMRVBSSUNFLjIwMjItMDctMTMBAAAAXFkCEwIAAAAFMC4wNDUAo7iZ5yll2gjn0en3KWXaCB5DSVEuTllTRTpGTFIuSVFfVEVWLjIwMjItMDctMTMBAAAAKwEKAAIAAAAKMjU1Mi4wMjQzNAEGAAAABQAAAAExAQAAAAstMjA5ODQ0NjE2MAMAAAADMTYwAgAAAAYxMDAwNjAEAAAAATAHAAAACTcvMTMvMjAyMqO4mecpZdoIO5Tq9yll2ggtQ0lRLk5BU0RBUUdTOkFNU0MuSVFfTEFTVFNBTEVQUklDRS4yMDIyLTA3LTEzAQAAAHWIAAACAAAABDQuODQAo7iZ5yll2ghWRer3KWXaCCdDSVEuTkFTREFRR1M6QU1TQy5JUV9UT1RBTF9ERUJULklRX0xUTS4BAAAAdYgAAAIAAAAFMy44MDIBCAAAAAUAAAABMQEAAAALLTIwOTI3NTg3ODMDAAAAAzE2MAIAAAAENDE3MwQAAAABMAcAAAAJNy8xMy8yMDIyCAAAAAkzLzMxLzIwMjIJAAAAATCdapr9CmXaCK9bAegpZdoIH0NJUS5OWVNFOkZMUi5JUV9TVF9ERUJULklRX0xUTS4BAAAAKwEKAAMAAAAAAJ1qmv0KZdoIo3EA6Cll2gggQ0lRLk9NOkFSSk8gQi5JUV9TVF9ERUJULklRX0xUTS4BAAAAU5bxDgMAAAAAAJ1qmv0KZdoI2+AC6Cll2ggdQ0lRLk5ZU0U6R1ZBLklRX0NBUEVYLklRX0xUTS4BAAAAujUEAAIAAAAILTEwNy4zMDIBCAAAAAUAAAABMQEAAAALLTIwOTk3OTY5MzcDAAAAAzE2MAIAAAAEMjAyMQQAAAABMAcAAAAJ | M1: Ny8xMy8yMDIyCAAAAAkzLzMxLzIwMjIJAAAAATCdapr9CmXaCEaI/+cpZdoIIkNJUS5LTFNFOkxLTC5JUV9UT1RBTF9ERUJULklRX0xUTS4BAAAAXFkCEwIAAAAIOC4yMzI3MTgBCAAAAAUAAAABMQEAAAALLTIxMTM4ODkxMTcDAAAAAzExMQIAAAAENDE3MwQAAAABMAcAAAAJNy8xMy8yMDIyCAAAAAk5LzMwLzIwMjEJAAAAATCdapr9CmXaCC0eAugpZdoIJENJUS5OQVNEQVFHUzpBTVNDLklRX0xUX0RFQlQuSVFfTFRNLgEAAAB1iAAAAgAAAAUwLjA4OQEIAAAABQAAAAExAQAAAAstMjA5Mjc1ODc4MwMAAAADMTYwAgAAAAQxMDQ5BAAAAAEwBwAAAAk3LzEzLzIwMjIIAAAACTMvMzEvMjAyMgkAAAABMJ1qmv0KZdoIr1sB6Cll2gggQ0lRLlRXU0U6NDEwNi5JUV9SRVZFTlVFLklRX0xUTS4BAAAAKkI2AQIAAAAIMjM4OC41ODIBCAAAAAUAAAABMQEAAAALLTIwOTE1NjAwNzgDAAAAAzE1NgIAAAADMTEyBAAAAAEwBwAAAAk3LzEzLzIwMjIIAAAACTMvMzEvMjAyMgkAAAABMJ1qmv0KZdoIzvgB6Cll2ggmQ0lRLk5ZU0U6RkxSLklRX0JBU0lDX0VQU19JTkNMLklRX0xUTS4BAAAAKwEKAAIAAAAJLTIuMzk5MTg3AQgAAAAFAAAAATEBAAAACy0yMDk4NDQ1ODk1AwAAAAMxNjACAAAAATkEAAAAATAHAAAACTcvMTMvMjAyMggAAAAJMy8zMS8yMDIyCQAAAAEwnWqa/Qpl2gijcQDoKWXaCCFDSVEuTllTRTpGTFIu | N1: SVFfQ0FTSF9FUVVJVi5JUV9MVE0BAAAAKwEKAAIAAAAEMTkxMwEIAAAABQAAAAExAQAAAAstMjA5ODQ0NTg5NQMAAAADMTYwAgAAAAQxMDk2BAAAAAEwBwAAAAk3LzEzLzIwMjIIAAAACTMvMzEvMjAyMgkAAAABMKO4mecpZdoIfL8A6Cll2ggjQ0lRLk9NOkFSSk8gQi5JUV9UT1RBTF9ERUJULklRX0xUTS4BAAAAU5bxDgIAAAAENTg1MAEIAAAABQAAAAExAQAAAAstMjEwMjI2NTY5OAMAAAADMTM3AgAAAAQ0MTczBAAAAAEwBwAAAAk3LzEzLzIwMjIIAAAACTMvMzEvMjAyMgkAAAABMJ1qmv0KZdoI2+AC6Cll2ggfQ0lRLktMU0U6TEtMLklRX0xUX0RFQlQuSVFfTFRNLgEAAABcWQITAgAAAAg0Ljg4ODczNwEIAAAABQAAAAExAQAAAAstMjExMzg4OTExNwMAAAADMTExAgAAAAQxMDQ5BAAAAAEwBwAAAAk3LzEzLzIwMjIIAAAACTkvMzAvMjAyMQkAAAABMJ1qmv0KZdoILR4C6Cll2ggeQ0lRLlRTRTo3ODEzLklRX0VCSVREQS5JUV9MVE0uAQAAABT/HQMCAAAAAzI4OQEIAAAABQAAAAExAQAAAAstMjA5NTMyMzA5MAMAAAACNzkCAAAABDQwNTEEAAAAATAHAAAACTcvMTMvMjAyMggAAAAJMy8zMS8yMDIyCQAAAAEwnWqa/Qpl2gj5kgLoKWXaCCRDSVEuTkFTREFRR1M6QU1TQy5JUV9TVF9ERUJULklRX0xUTS4BAAAAdYgAAAMAAAAAAJ1qmv0KZdoIr1sB6Cll2ggmQ0lRLk5ZU0U6RkxSLklRX0JBU0lDX0VQ | O1: U19JTkNMLklRX05UTS4BAAAAKwEKAAMAAAAAAJ1qmv0KZdoIo3EA6Cll2ggcQ0lRLk5ZU0U6RkxSLklRX0VCSVQuSVFfTFRNLgEAAAArAQoAAgAAAAcyNDUuMTQ0AQgAAAAFAAAAATEBAAAACy0yMDk4NDQ1ODk1AwAAAAMxNjACAAAAAzQwMAQAAAABMAcAAAAJNy8xMy8yMDIyCAAAAAkzLzMxLzIwMjIJAAAAATCdapr9CmXaCHy/AOgpZdoIHkNJUS5UU1g6U0lTLklRX1JFVkVOVUUuSVFfTFRNLgEAAABIgDAAAgAAAAc3MzIuNDQ0AQgAAAAFAAAAATEBAAAACy0yMDk3MzY0MzM3AwAAAAIyNwIAAAADMTEyBAAAAAEwBwAAAAk3LzEzLzIwMjIIAAAACTMvMzEvMjAyMgkAAAABMJ1qmv0KZdoIgA0B6Cll2ggfQ0lRLktMU0U6TEtMLklRX1NUX0RFQlQuSVFfTFRNLgEAAABcWQITAgAAAAgwLjIzNzY4MQEIAAAABQAAAAExAQAAAAstMjExMzg4OTExNwMAAAADMTExAgAAAAQxMDQ2BAAAAAEwBwAAAAk3LzEzLzIwMjIIAAAACTkvMzAvMjAyMQkAAAABMJ1qmv0KZdoILR4C6Cll2ggrQ0lRLk5BU0RBUUdTOkFNU0MuSVFfQkFTSUNfRVBTX0lOQ0wuSVFfTFRNLgEAAAB1iAAAAgAAAAktMC43MDU1NDcBCAAAAAUAAAABMQEAAAALLTIwOTI3NTg3ODMDAAAAAzE2MAIAAAABOQQAAAABMAcAAAAJNy8xMy8yMDIyCAAAAAkzLzMxLzIwMjIJAAAAATCdapr9CmXaCK9bAegpZdoIJkNJUS5OQVNEQVFHUzpBTVNDLklRX0NB | P1: U0hfRVFVSVYuSVFfTFRNAQAAAHWIAAACAAAABjQwLjU4NAEIAAAABQAAAAExAQAAAAstMjA5Mjc1ODc4MwMAAAADMTYwAgAAAAQxMDk2BAAAAAEwBwAAAAk3LzEzLzIwMjIIAAAACTMvMzEvMjAyMgkAAAABMKO4mecpZdoISqkB6Cll2ggiQ0lRLk5ZU0U6R1ZBLklRX1RPVEFMX0RFQlQuSVFfTFRNLgEAAAC6NQQAAgAAAAczMzIuNDczAQgAAAAFAAAAATEBAAAACy0yMDk5Nzk2OTM3AwAAAAMxNjACAAAABDQxNzMEAAAAATAHAAAACTcvMTMvMjAyMggAAAAJMy8zMS8yMDIyCQAAAAEwnWqa/Qpl2ggKr//nKWXaCB1DSVEuT006QVJKTyBCLklRX0VCSVQuSVFfTFRNLgEAAABTlvEOAgAAAAQxMTE5AQgAAAAFAAAAATEBAAAACy0yMTAyMjY1Njk4AwAAAAMxMzcCAAAAAzQwMAQAAAABMAcAAAAJNy8xMy8yMDIyCAAAAAkzLzMxLzIwMjIJAAAAATCdapr9CmXaCNAHA+gpZdoIJ0NJUS5PTTpBUkpPIEIuSVFfQkFTSUNfRVBTX0lOQ0wuSVFfTFRNLgEAAABTlvEOAgAAAAgyLjY5MTE5NgEIAAAABQAAAAExAQAAAAstMjEwMjI2NTY5OAMAAAADMTM3AgAAAAE5BAAAAAEwBwAAAAk3LzEzLzIwMjIIAAAACTMvMzEvMjAyMgkAAAABMJ1qmv0KZdoI2+AC6Cll2gghQ0lRLktMU0U6TEtMLklRX0NBU0hfRVFVSVYuSVFfTFRNAQAAAFxZAhMCAAAACTY1LjY2MTg1MgEIAAAABQAAAAExAQAAAAstMjExMzg4OTExNwMAAAAD | Q1: MTExAgAAAAQxMDk2BAAAAAEwBwAAAAk3LzEzLzIwMjIIAAAACTkvMzAvMjAyMQkAAAABMKO4mecpZdoITUYC6Cll2gghQ0lRLk5BU0RBUUdTOkFNU0MuSVFfRUJJVC5JUV9MVE0uAQAAAHWIAAACAAAABy0yNS42NTgBCAAAAAUAAAABMQEAAAALLTIwOTI3NTg3ODMDAAAAAzE2MAIAAAADNDAwBAAAAAEwBwAAAAk3LzEzLzIwMjIIAAAACTMvMzEvMjAyMgkAAAABMJ1qmv0KZdoISqkB6Cll2ggeQ0lRLlRXU0U6NDEwNi5JUV9DQVBFWC5JUV9MVE0uAQAAACpCNgECAAAABy00Ni41MjgBCAAAAAUAAAABMQEAAAALLTIwOTE1NjAwNzgDAAAAAzE1NgIAAAAEMjAyMQQAAAABMAcAAAAJNy8xMy8yMDIyCAAAAAkzLzMxLzIwMjIJAAAAATCdapr9CmXaCGfRAegpZdoIJkNJUS5LTFNFOkxLTC5JUV9CQVNJQ19FUFNfSU5DTC5JUV9MVE0uAQAAAFxZAhMCAAAACS0wLjA3MzMzMwEIAAAABQAAAAExAQAAAAstMjExMzg4OTExNwMAAAADMTExAgAAAAE5BAAAAAEwBwAAAAk3LzEzLzIwMjIIAAAACTkvMzAvMjAyMQkAAAABMJ1qmv0KZdoILR4C6Cll2ggrQ0lRLk5BU0RBUUdTOkFNU0MuSVFfQkFTSUNfRVBTX0lOQ0wuSVFfTlRNLgEAAAB1iAAAAwAAAAAAnWqa/Qpl2gh/NAHoKWXaCB9DSVEuTllTRTpHVkEuSVFfTFRfREVCVC5JUV9MVE0uAQAAALo1BAACAAAABzI5MC41NDkBCAAAAAUAAAABMQEAAAALLTIwOTk3OTY5 | R1: MzcDAAAAAzE2MAIAAAAEMTA0OQQAAAABMAcAAAAJNy8xMy8yMDIyCAAAAAkzLzMxLzIwMjIJAAAAATCdapr9CmXaCBg6/+cpZdoIH0NJUS5UU0U6NzgxMy5JUV9SRVZFTlVFLklRX0xUTS4BAAAAFP8dAwIAAAAENjY5MAEIAAAABQAAAAExAQAAAAstMjA5NTMyMzA5MAMAAAACNzkCAAAAAzExMgQAAAABMAcAAAAJNy8xMy8yMDIyCAAAAAkzLzMxLzIwMjIJAAAAATCdapr9CmXaCAdsAugpZdoIIkNJUS5UU0U6NzgxNy5JUV9UT1RBTF9ERUJULklRX0xUTS4BAAAAnXMNAAIAAAAENjEzNQEIAAAABQAAAAExAQAAAAstMjA4OTc4NDQ2MAMAAAACNzkCAAAABDQxNzMEAAAAATAHAAAACTcvMTMvMjAyMggAAAAJMy8zMS8yMDIyCQAAAAEwnWqa/Qpl2gj5kgLoKWXaCBxDSVEuS0xTRTpMS0wuSVFfRUJJVC5JUV9MVE0uAQAAAFxZAhMCAAAACS05LjU5MDgxOQEIAAAABQAAAAExAQAAAAstMjExMzg4OTExNwMAAAADMTExAgAAAAM0MDAEAAAAATAHAAAACTcvMTMvMjAyMggAAAAJOS8zMC8yMDIxCQAAAAEwnWqa/Qpl2ghNRgLoKWXaCB5DSVEuTllTRTpGTFIuSVFfRUJJVERBLklRX0xUTS4BAAAAKwEKAAIAAAAFMzEwLjUBCAAAAAUAAAABMQEAAAALLTIwOTg0NDU4OTUDAAAAAzE2MAIAAAAENDA1MQQAAAABMAcAAAAJNy8xMy8yMDIyCAAAAAkzLzMxLzIwMjIJAAAAATCdapr9CmXaCIjmAOgpZdoIHENJUS5UU1g6 | S1: U0lTLklRX0NBUEVYLklRX0xUTS4BAAAASIAwAAIAAAAGLTcuNDg3AQgAAAAFAAAAATEBAAAACy0yMDk3MzY0MzM3AwAAAAIyNwIAAAAEMjAyMQQAAAABMAcAAAAJNy8xMy8yMDIyCAAAAAkzLzMxLzIwMjIJAAAAATCdapr9CmXaCIANAegpZdoIH0NJUS5UU0U6NzgxNy5JUV9SRVZFTlVFLklRX0xUTS4BAAAAnXMNAAIAAAAFOTAzNTIBCAAAAAUAAAABMQEAAAALLTIwODk3ODQ0NjADAAAAAjc5AgAAAAMxMTIEAAAAATAHAAAACTcvMTMvMjAyMggAAAAJMy8zMS8yMDIyCQAAAAEwnWqa/Qpl2gjnuQLoKWXaCB9DSVEuTllTRTpHVkEuSVFfU1RfREVCVC5JUV9MVE0uAQAAALo1BAADAAAAAACdapr9CmXaCBg6/+cpZdoIH0NJUS5UU0U6NzgxNy5JUV9MVF9ERUJULklRX0xUTS4BAAAAnXMNAAMAAAAAAJ1qmv0KZdoI+ZIC6Cll2ggfQ0lRLk9NOkFSSk8gQi5JUV9FQklUREEuSVFfTFRNLgEAAABTlvEOAgAAAAQxNzE0AQgAAAAFAAAAATEBAAAACy0yMTAyMjY1Njk4AwAAAAMxMzcCAAAABDQwNTEEAAAAATAHAAAACTcvMTMvMjAyMggAAAAJMy8zMS8yMDIyCQAAAAEwnWqa/Qpl2gjb4ALoKWXaCB1DSVEuVFNYOlNJUy5JUV9FQklUREEuSVFfTFRNLgEAAABIgDAAAgAAAAY4NS4yNjMBCAAAAAUAAAABMQEAAAALLTIwOTczNjQzMzcDAAAAAjI3AgAAAAQ0MDUxBAAAAAEwBwAAAAk3LzEzLzIwMjIIAAAACTMvMzEv | T1: MjAyMgkAAAABMJ1qmv0KZdoIfzQB6Cll2ggmQ0lRLk5ZU0U6R1ZBLklRX0JBU0lDX0VQU19JTkNMLklRX0xUTS4BAAAAujUEAAIAAAAIMS4zODMzNDQBCAAAAAUAAAABMQEAAAALLTIwOTk3OTY5MzcDAAAAAzE2MAIAAAABOQQAAAABMAcAAAAJNy8xMy8yMDIyCAAAAAkzLzMxLzIwMjIJAAAAATCdapr9CmXaCIxh/+cpZdoIIUNJUS5OWVNFOkdWQS5JUV9DQVNIX0VRVUlWLklRX0xUTQEAAAC6NQQAAgAAAAczNjAuOTExAQgAAAAFAAAAATEBAAAACy0yMDk5Nzk2OTM3AwAAAAMxNjACAAAABDEwOTYEAAAAATAHAAAACTcvMTMvMjAyMggAAAAJMy8zMS8yMDIyCQAAAAEwpt+Z5yll2ggYJADoKWXaCB9DSVEuVFNFOjc4MTcuSVFfU1RfREVCVC5JUV9MVE0uAQAAAJ1zDQADAAAAAACdapr9CmXaCPmSAugpZdoIHUNJUS5UU0U6NzgxNy5JUV9DQVBFWC5JUV9MVE0uAQAAAJ1zDQACAAAABS0xMDQ3AQgAAAAFAAAAATEBAAAACy0yMDg5Nzg0NDYwAwAAAAI3OQIAAAAEMjAyMQQAAAABMAcAAAAJNy8xMy8yMDIyCAAAAAkzLzMxLzIwMjIJAAAAATCdapr9CmXaCOe5AugpZdoII0NJUS5OQVNEQVFHUzpBTVNDLklRX0VCSVREQS5JUV9MVE0uAQAAAHWIAAACAAAABy0yMC4zMTcBCAAAAAUAAAABMQEAAAALLTIwOTI3NTg3ODMDAAAAAzE2MAIAAAAENDA1MQQAAAABMAcAAAAJNy8xMy8yMDIyCAAAAAkzLzMxLzIwMjIJ | U1: AAAAATCdapr9CmXaCEqpAegpZdoII0NJUS5UV1NFOjQxMDYuSVFfVE9UQUxfREVCVC5JUV9MVE0uAQAAACpCNgECAAAABzU3NC42NDQBCAAAAAUAAAABMQEAAAALLTIwOTE1NjAwNzgDAAAAAzE1NgIAAAAENDE3MwQAAAABMAcAAAAJNy8xMy8yMDIyCAAAAAkzLzMxLzIwMjIJAAAAATCdapr9CmXaCGfRAegpZdoIHENJUS5OWVNFOkdWQS5JUV9FQklULklRX0xUTS4BAAAAujUEAAIAAAAGNjEuMjkxAQgAAAAFAAAAATEBAAAACy0yMDk5Nzk2OTM3AwAAAAMxNjACAAAAAzQwMAQAAAABMAcAAAAJNy8xMy8yMDIyCAAAAAkzLzMxLzIwMjIJAAAAATCdapr9CmXaCNVKAOgpZdoIIkNJUS5PTTpBUkpPIEIuSVFfQ0FTSF9FUVVJVi5JUV9MVE0BAAAAU5bxDgIAAAADOTg1AQgAAAAFAAAAATEBAAAACy0yMTAyMjY1Njk4AwAAAAMxMzcCAAAABDEwOTYEAAAAATAHAAAACTcvMTMvMjAyMggAAAAJMy8zMS8yMDIyCQAAAAEwo7iZ5yll2gjQBwPoKWXaCCZDSVEuTllTRTpHVkEuSVFfQkFTSUNfRVBTX0lOQ0wuSVFfTlRNLgEAAAC6NQQAAwAAAAAAnWqa/Qpl2giMYf/nKWXaCB1DSVEuVFNFOjc4MTMuSVFfQ0FQRVguSVFfTFRNLgEAAAAU/x0DAwAAAAAAnWqa/Qpl2ggHbALoKWXaCCZDSVEuVFNFOjc4MTcuSVFfQkFTSUNfRVBTX0lOQ0wuSVFfTFRNLgEAAACdcw0AAgAAAAoxNTYuMzc3MTA2AQgAAAAFAAAAATEBAAAA | V1: Cy0yMDg5Nzg0NDYwAwAAAAI3OQIAAAABOQQAAAABMAcAAAAJNy8xMy8yMDIyCAAAAAkzLzMxLzIwMjIJAAAAATCdapr9CmXaCPmSAugpZdoIIUNJUS5UU0U6NzgxNy5JUV9DQVNIX0VRVUlWLklRX0xUTQEAAACdcw0AAgAAAAUzOTY3MgEIAAAABQAAAAExAQAAAAstMjA4OTc4NDQ2MAMAAAACNzkCAAAABDEwOTYEAAAAATAHAAAACTcvMTMvMjAyMggAAAAJMy8zMS8yMDIyCQAAAAEwo7iZ5yll2gjnuQLoKWXaCCBDSVEuVFdTRTo0MTA2LklRX0xUX0RFQlQuSVFfTFRNLgEAAAAqQjYBAgAAAAcxMjIuMjk4AQgAAAAFAAAAATEBAAAACy0yMDkxNTYwMDc4AwAAAAMxNTYCAAAABDEwNDkEAAAAATAHAAAACTcvMTMvMjAyMggAAAAJMy8zMS8yMDIyCQAAAAEwnWqa/Qpl2ghn0QHoKWXaCB5DSVEuS0xTRTpMS0wuSVFfRUJJVERBLklRX0xUTS4BAAAAXFkCEwIAAAAILTcuOTAyNjgBCAAAAAUAAAABMQEAAAALLTIxMTM4ODkxMTcDAAAAAzExMQIAAAAENDA1MQQAAAABMAcAAAAJNy8xMy8yMDIyCAAAAAk5LzMwLzIwMjEJAAAAATCdapr9CmXaCC0eAugpZdoIIUNJUS5UU1g6U0lTLklRX1RPVEFMX0RFQlQuSVFfTFRNLgEAAABIgDAAAgAAAAc0MTQuMTMxAQgAAAAFAAAAATEBAAAACy0yMDk3MzY0MzM3AwAAAAIyNwIAAAAENDE3MwQAAAABMAcAAAAJNy8xMy8yMDIyCAAAAAkzLzMxLzIwMjIJAAAAATCdapr9CmXa | W1: CIjmAOgpZdoIH0NJUS5OWVNFOkZMUi5JUV9SRVZFTlVFLklRX0xUTS4BAAAAKwEKAAIAAAAJMTIyMDkuODc5AQgAAAAFAAAAATEBAAAACy0yMDk4NDQ1ODk1AwAAAAMxNjACAAAAAzExMgQAAAABMAcAAAAJNy8xMy8yMDIyCAAAAAkzLzMxLzIwMjIJAAAAATCdapr9CmXaCHy/AOgpZdoIIENJUS5UV1NFOjQxMDYuSVFfU1RfREVCVC5JUV9MVE0uAQAAACpCNgECAAAABzM5MC45MzQBCAAAAAUAAAABMQEAAAALLTIwOTE1NjAwNzgDAAAAAzE1NgIAAAAEMTA0NgQAAAABMAcAAAAJNy8xMy8yMDIyCAAAAAkzLzMxLzIwMjIJAAAAATCdapr9CmXaCGfRAegpZdoIHkNJUS5UU1g6U0lTLklRX0xUX0RFQlQuSVFfTFRNLgEAAABIgDAAAgAAAAczNjIuMzk4AQgAAAAFAAAAATEBAAAACy0yMDk3MzY0MzM3AwAAAAIyNwIAAAAEMTA0OQQAAAABMAcAAAAJNy8xMy8yMDIyCAAAAAkzLzMxLzIwMjIJAAAAATCdapr9CmXaCIANAegpZdoIHENJUS5UU0U6NzgxNy5JUV9FQklULklRX0xUTS4BAAAAnXMNAAIAAAAFMTE5NzUBCAAAAAUAAAABMQEAAAALLTIwODk3ODQ0NjADAAAAAjc5AgAAAAM0MDAEAAAAATAHAAAACTcvMTMvMjAyMggAAAAJMy8zMS8yMDIyCQAAAAEwnWqa/Qpl2gjnuQLoKWXaCBxDSVEuVFNFOjc4MTMuSVFfRUJJVC5JUV9MVE0uAQAAABT/HQMCAAAAAzI1MQEIAAAABQAAAAExAQAAAAstMjA5NTMyMzA5 | X1: MAMAAAACNzkCAAAAAzQwMAQAAAABMAcAAAAJNy8xMy8yMDIyCAAAAAkzLzMxLzIwMjIJAAAAATCdapr9CmXaCPmSAugpZdoIJ0NJUS5UV1NFOjQxMDYuSVFfQkFTSUNfRVBTX0lOQ0wuSVFfTFRNLgEAAAAqQjYBAgAAAAgxLjAyOTY5OQEIAAAABQAAAAExAQAAAAstMjA5MTU2MDA3OAMAAAADMTU2AgAAAAE5BAAAAAEwBwAAAAk3LzEzLzIwMjIIAAAACTMvMzEvMjAyMgkAAAABMJ1qmv0KZdoIZ9EB6Cll2ggiQ0lRLlRXU0U6NDEwNi5JUV9DQVNIX0VRVUlWLklRX0xUTQEAAAAqQjYBAgAAAAc0NzMuNjEyAQgAAAAFAAAAATEBAAAACy0yMDkxNTYwMDc4AwAAAAMxNTYCAAAABDEwOTYEAAAAATAHAAAACTcvMTMvMjAyMggAAAAJMy8zMS8yMDIyCQAAAAEwo7iZ5yll2ggtHgLoKWXaCB5DSVEuVFNYOlNJUy5JUV9TVF9ERUJULklRX0xUTS4BAAAASIAwAAMAAAAAAJ1qmv0KZdoIgA0B6Cll2ggkQ0lRLk5BU0RBUUdTOkFNU0MuSVFfUkVWRU5VRS5JUV9MVE0uAQAAAHWIAAACAAAABzEwOC40MzUBCAAAAAUAAAABMQEAAAALLTIwOTI3NTg3ODMDAAAAAzE2MAIAAAADMTEyBAAAAAEwBwAAAAk3LzEzLzIwMjIIAAAACTMvMzEvMjAyMgkAAAABMJ1qmv0KZdoIr1sB6Cll2gggQ0lRLk9NOkFSSk8gQi5JUV9MVF9ERUJULklRX0xUTS4BAAAAU5bxDgIAAAAEMTA3NQEIAAAABQAAAAExAQAAAAstMjEwMjI2NTY5OAMA | Y1: AAADMTM3AgAAAAQxMDQ5BAAAAAEwBwAAAAk3LzEzLzIwMjIIAAAACTMvMzEvMjAyMgkAAAABMJ1qmv0KZdoI2+AC6Cll2ggeQ0lRLk5ZU0U6R1ZBLklRX0VCSVREQS5JUV9MVE0uAQAAALo1BAACAAAABzEyMi45NDEBCAAAAAUAAAABMQEAAAALLTIwOTk3OTY5MzcDAAAAAzE2MAIAAAAENDA1MQQAAAABMAcAAAAJNy8xMy8yMDIyCAAAAAkzLzMxLzIwMjIJAAAAATCdapr9CmXaCAqv/+cpZdoIIkNJUS5UU0U6NzgxMy5JUV9UT1RBTF9ERUJULklRX0xUTS4BAAAAFP8dAwIAAAAEMjQxMgEIAAAABQAAAAExAQAAAAstMjA5NTMyMzA5MAMAAAACNzkCAAAABDQxNzMEAAAAATAHAAAACTcvMTMvMjAyMggAAAAJMy8zMS8yMDIyCQAAAAEwnWqa/Qpl2ggHbALoKWXaCCdDSVEuVFdTRTo0MTA2LklRX0JBU0lDX0VQU19JTkNMLklRX05UTS4BAAAAKkI2AQMAAAAAAJ1qmv0KZdoIZ9EB6Cll2ggdQ0lRLlRXU0U6NDEwNi5JUV9FQklULklRX0xUTS4BAAAAKkI2AQIAAAAHMTAxLjMwOAEIAAAABQAAAAExAQAAAAstMjA5MTU2MDA3OAMAAAADMTU2AgAAAAM0MDAEAAAAATAHAAAACTcvMTMvMjAyMggAAAAJMy8zMS8yMDIyCQAAAAEwnWqa/Qpl2ggtHgLoKWXaCB9DSVEuS0xTRTpMS0wuSVFfUkVWRU5VRS5JUV9MVE0uAQAAAFxZAhMCAAAACTUzLjI5NzM2MQEIAAAABQAAAAExAQAAAAstMjExMzg4OTExNwMAAAADMTEx | Z1: AgAAAAMxMTIEAAAAATAHAAAACTcvMTMvMjAyMggAAAAJOS8zMC8yMDIxCQAAAAEwnWqa/Qpl2ghNRgLoKWXaCCVDSVEuVFNYOlNJUy5JUV9CQVNJQ19FUFNfSU5DTC5JUV9MVE0uAQAAAEiAMAACAAAACDAuMjAzNjM5AQgAAAAFAAAAATEBAAAACy0yMDk3MzY0MzM3AwAAAAIyNwIAAAABOQQAAAABMAcAAAAJNy8xMy8yMDIyCAAAAAkzLzMxLzIwMjIJAAAAATCdapr9CmXaCIjmAOgpZdoIIENJUS5UU1g6U0lTLklRX0NBU0hfRVFVSVYuSVFfTFRNAQAAAEiAMAACAAAABjQzLjkwMwEIAAAABQAAAAExAQAAAAstMjA5NzM2NDMzNwMAAAACMjcCAAAABDEwOTYEAAAAATAHAAAACTcvMTMvMjAyMggAAAAJMy8zMS8yMDIyCQAAAAEwo7iZ5yll2gh/NAHoKWXaCB1DSVEuTllTRTpGTFIuSVFfQ0FQRVguSVFfTFRNLgEAAAArAQoAAgAAAActNTUuMDczAQgAAAAFAAAAATEBAAAACy0yMDk4NDQ1ODk1AwAAAAMxNjACAAAABDIwMjEEAAAAATAHAAAACTcvMTMvMjAyMggAAAAJMy8zMS8yMDIyCQAAAAEwnWqa/Qpl2gijcQDoKWXaCB5DSVEuVFNFOjc4MTcuSVFfRUJJVERBLklRX0xUTS4BAAAAnXMNAAIAAAAFMTk5NDkBCAAAAAUAAAABMQEAAAALLTIwODk3ODQ0NjADAAAAAjc5AgAAAAQ0MDUxBAAAAAEwBwAAAAk3LzEzLzIwMjIIAAAACTMvMzEvMjAyMgkAAAABMJ1qmv0KZdoI57kC6Cll2gggQ0lRLk9NOkFSSk8g | AA1: Qi5JUV9SRVZFTlVFLklRX0xUTS4BAAAAU5bxDgIAAAAEOTI3MgEIAAAABQAAAAExAQAAAAstMjEwMjI2NTY5OAMAAAADMTM3AgAAAAMxMTIEAAAAATAHAAAACTcvMTMvMjAyMggAAAAJMy8zMS8yMDIyCQAAAAEwnWqa/Qpl2gjb4ALoKWXaCB9DSVEuTllTRTpGTFIuSVFfTFRfREVCVC5JUV9MVE0uAQAAACsBCgACAAAAAzk4MgEIAAAABQAAAAExAQAAAAstMjA5ODQ0NTg5NQMAAAADMTYwAgAAAAQxMDQ5BAAAAAEwBwAAAAk3LzEzLzIwMjIIAAAACTMvMzEvMjAyMgkAAAABMJ1qmv0KZdoIuZgA6Cll2ggfQ0lRLlRTRTo3ODEzLklRX0xUX0RFQlQuSVFfTFRNLgEAAAAU/x0DAgAAAAM3NjQBCAAAAAUAAAABMQEAAAALLTIwOTUzMjMwOTADAAAAAjc5AgAAAAQxMDQ5BAAAAAEwBwAAAAk3LzEzLzIwMjIIAAAACTMvMzEvMjAyMgkAAAABMJ1qmv0KZdoIB2wC6Cll2ggbQ0lRLlRTWDpTSVMuSVFfRUJJVC5JUV9MVE0uAQAAAEiAMAACAAAABjUwLjU4NwEIAAAABQAAAAExAQAAAAstMjA5NzM2NDMzNwMAAAACMjcCAAAAAzQwMAQAAAABMAcAAAAJNy8xMy8yMDIyCAAAAAkzLzMxLzIwMjIJAAAAATCdapr9CmXaCIANAegpZdoIHkNJUS5PTTpBUkpPIEIuSVFfQ0FQRVguSVFfTFRNLgEAAABTlvEOAgAAAAQtODA1AQgAAAAFAAAAATEBAAAACy0yMTAyMjY1Njk4AwAAAAMxMzcCAAAABDIwMjEEAAAAATAHAAAACTcv | AB1: MTMvMjAyMggAAAAJMy8zMS8yMDIyCQAAAAEwnWqa/Qpl2gjb4ALoKWXaCB9DSVEuVFNFOjc4MTMuSVFfU1RfREVCVC5JUV9MVE0uAQAAABT/HQMCAAAABDEyNTABCAAAAAUAAAABMQEAAAALLTIwOTUzMjMwOTADAAAAAjc5AgAAAAQxMDQ2BAAAAAEwBwAAAAk3LzEzLzIwMjIIAAAACTMvMzEvMjAyMgkAAAABMJ1qmv0KZdoITUYC6Cll2ggiQ0lRLk5BU0RBUUdTOkFNU0MuSVFfQ0FQRVguSVFfTFRNLgEAAAB1iAAAAgAAAAYtMC45MzgBCAAAAAUAAAABMQEAAAALLTIwOTI3NTg3ODMDAAAAAzE2MAIAAAAEMjAyMQQAAAABMAcAAAAJNy8xMy8yMDIyCAAAAAkzLzMxLzIwMjIJAAAAATCdapr9CmXaCM6DAegpZdoIH0NJUS5OWVNFOkdWQS5JUV9SRVZFTlVFLklRX0xUTS4BAAAAujUEAAIAAAAIMjk5MS4zMDcBCAAAAAUAAAABMQEAAAALLTIwOTk3OTY5MzcDAAAAAzE2MAIAAAADMTEyBAAAAAEwBwAAAAk3LzEzLzIwMjIIAAAACTMvMzEvMjAyMgkAAAABMJ1qmv0KZdoIMP3/5yll2ggdQ0lRLktMU0U6TEtMLklRX0NBUEVYLklRX0xUTS4BAAAAXFkCEwIAAAAJLTkuMTE5MjU4AQgAAAAFAAAAATEBAAAACy0yMTEzODg5MTE3AwAAAAMxMTECAAAABDIwMjEEAAAAATAHAAAACTcvMTMvMjAyMggAAAAJOS8zMC8yMDIxCQAAAAEwnWqa/Qpl2ggtHgLoKWXaCCZDSVEuVFNFOjc4MTMuSVFfQkFTSUNfRVBTX0lOQ0wu | AC1: SVFfTFRNLgEAAAAU/x0DAgAAAAk5Mi4wNzAxMjcBCAAAAAUAAAABMQEAAAALLTIwOTUzMjMwOTADAAAAAjc5AgAAAAE5BAAAAAEwBwAAAAk3LzEzLzIwMjIIAAAACTMvMzEvMjAyMgkAAAABMJ1qmv0KZdoITUYC6Cll2gghQ0lRLlRTRTo3ODEzLklRX0NBU0hfRVFVSVYuSVFfTFRNAQAAABT/HQMCAAAABDEzNjkBCAAAAAUAAAABMQEAAAALLTIwOTUzMjMwOTADAAAAAjc5AgAAAAQxMDk2BAAAAAEwBwAAAAk3LzEzLzIwMjIIAAAACTMvMzEvMjAyMgkAAAABMKO4mecpZdoI+ZIC6Cll2ggfQ0lRLlRXU0U6NDEwNi5JUV9FQklUREEuSVFfTFRNLgEAAAAqQjYBAgAAAAcxOTMuNzMzAQgAAAAFAAAAATEBAAAACy0yMDkxNTYwMDc4AwAAAAMxNTYCAAAABDQwNTEEAAAAATAHAAAACTcvMTMvMjAyMggAAAAJMy8zMS8yMDIyCQAAAAEwnWqa/Qpl2gjO+AHoKWXaCCJDSVEuTllTRTpGTFIuSVFfVE9UQUxfREVCVC5JUV9MVE0uAQAAACsBCgACAAAABDExOTYBCAAAAAUAAAABMQEAAAALLTIwOTg0NDU4OTUDAAAAAzE2MAIAAAAENDE3MwQAAAABMAcAAAAJNy8xMy8yMDIyCAAAAAkzLzMxLzIwMjIJAAAAATCdapr9CmXaCLmYAOgpZdoILENJUS5OWVNFOkZMUi5JUV9UT1RBTF9ERUJULklRX0xUTS4yMDIyLTA3LTEzAQAAACsBCgACAAAABDExOTYBCAAAAAUAAAABMQEAAAALLTIwOTg0NDU4OTUDAAAAAzE2MAIAAAAE | AD1: NDE3MwQAAAABMAcAAAAJNy8xMy8yMDIyCAAAAAkzLzMxLzIwMjIJAAAAATCm35nnKWXaCDuU6vcpZdoIKUNJUS5UV1NFOjQxMDYuSVFfRUJJVERBLklRX0xUTS4yMDIyLTA3LTEzAQAAACpCNgECAAAABzE5My43MzMBCAAAAAUAAAABMQEAAAALLTIwOTE1NjAwNzgDAAAAAzE1NgIAAAAENDA1MQQAAAABMAcAAAAJNy8xMy8yMDIyCAAAAAkzLzMxLzIwMjIJAAAAATCjuJnnKWXaCCkf6vcpZdoIMENJUS5UU0U6NzgxMy5JUV9CQVNJQ19FUFNfSU5DTC5JUV9MVE0uMjAyMi0wNy0xMwEAAAAU/x0DAgAAAAk5Mi4wNzAxMjcBCAAAAAUAAAABMQEAAAALLTIwOTUzMjMwOTADAAAAAjc5AgAAAAE5BAAAAAEwBwAAAAk3LzEzLzIwMjIIAAAACTMvMzEvMjAyMgkAAAABMKO4mecpZdoI59Hp9yll2ggnQ0lRLktMU0U6TEtMLklRX0NBUEVYLklRX0xUTS4yMDIyLTA3LTEzAQAAAFxZAhMCAAAACS05LjExOTI1OAEIAAAABQAAAAExAQAAAAstMjExMzg4OTExNwMAAAADMTExAgAAAAQyMDIxBAAAAAEwBwAAAAk3LzEzLzIwMjIIAAAACTkvMzAvMjAyMQkAAAABMKO4mecpZdoIIffp9yll2ggpQ0lRLk5ZU0U6R1ZBLklRX1JFVkVOVUUuSVFfTFRNLjIwMjItMDctMTMBAAAAujUEAAIAAAAIMjk5MS4zMDcBCAAAAAUAAAABMQEAAAALLTIwOTk3OTY5MzcDAAAAAzE2MAIAAAADMTEyBAAAAAEwBwAAAAk3LzEzLzIwMjIIAAAA | AE1: CTMvMzEvMjAyMgkAAAABMKbfmecpZdoIMbvq9yll2ggsQ0lRLk5BU0RBUUdTOkFNU0MuSVFfQ0FQRVguSVFfTFRNLjIwMjItMDctMTMBAAAAdYgAAAIAAAAGLTAuOTM4AQgAAAAFAAAAATEBAAAACy0yMDkyNzU4NzgzAwAAAAMxNjACAAAABDIwMjEEAAAAATAHAAAACTcvMTMvMjAyMggAAAAJMy8zMS8yMDIyCQAAAAEwo7iZ5yll2ghWRer3KWXaCClDSVEuVFNFOjc4MTMuSVFfU1RfREVCVC5JUV9MVE0uMjAyMi0wNy0xMwEAAAAU/x0DAgAAAAQxMjUwAQgAAAAFAAAAATEBAAAACy0yMDk1MzIzMDkwAwAAAAI3OQIAAAAEMTA0NgQAAAABMAcAAAAJNy8xMy8yMDIyCAAAAAkzLzMxLzIwMjIJAAAAATCjuJnnKWXaCOfR6fcpZdoIKENJUS5PTTpBUkpPIEIuSVFfQ0FQRVguSVFfTFRNLjIwMjItMDctMTMBAAAAU5bxDgIAAAAELTgwNQEIAAAABQAAAAExAQAAAAstMjEwMjI2NTY5OAMAAAADMTM3AgAAAAQyMDIxBAAAAAEwBwAAAAk3LzEzLzIwMjIIAAAACTMvMzEvMjAyMgkAAAABMKO4mecpZdoIhIPp9yll2gglQ0lRLlRTWDpTSVMuSVFfRUJJVC5JUV9MVE0uMjAyMi0wNy0xMwEAAABIgDAAAgAAAAY1MC41ODcBCAAAAAUAAAABMQEAAAALLTIwOTczNjQzMzcDAAAAAjI3AgAAAAM0MDAEAAAAATAHAAAACTcvMTMvMjAyMggAAAAJMy8zMS8yMDIyCQAAAAEwo7iZ5yll2ggGbOr3KWXaCClDSVEuVFNFOjc4MTMu | AF1: SVFfTFRfREVCVC5JUV9MVE0uMjAyMi0wNy0xMwEAAAAU/x0DAgAAAAM3NjQBCAAAAAUAAAABMQEAAAALLTIwOTUzMjMwOTADAAAAAjc5AgAAAAQxMDQ5BAAAAAEwBwAAAAk3LzEzLzIwMjIIAAAACTMvMzEvMjAyMgkAAAABMKO4mecpZdoI59Hp9yll2ggpQ0lRLk5ZU0U6RkxSLklRX0xUX0RFQlQuSVFfTFRNLjIwMjItMDctMTMBAAAAKwEKAAIAAAADOTgyAQgAAAAFAAAAATEBAAAACy0yMDk4NDQ1ODk1AwAAAAMxNjACAAAABDEwNDkEAAAAATAHAAAACTcvMTMvMjAyMggAAAAJMy8zMS8yMDIyCQAAAAEwpt+Z5yll2gg7lOr3KWXaCCpDSVEuT006QVJKTyBCLklRX1JFVkVOVUUuSVFfTFRNLjIwMjItMDctMTMBAAAAU5bxDgIAAAAEOTI3MgEIAAAABQAAAAExAQAAAAstMjEwMjI2NTY5OAMAAAADMTM3AgAAAAMxMTIEAAAAATAHAAAACTcvMTMvMjAyMggAAAAJMy8zMS8yMDIyCQAAAAEwo7iZ5yll2giEg+n3KWXaCChDSVEuVFNFOjc4MTcuSVFfRUJJVERBLklRX0xUTS4yMDIyLTA3LTEzAQAAAJ1zDQACAAAABTE5OTQ5AQgAAAAFAAAAATEBAAAACy0yMDg5Nzg0NDYwAwAAAAI3OQIAAAAENDA1MQQAAAABMAcAAAAJNy8xMy8yMDIyCAAAAAkzLzMxLzIwMjIJAAAAATCjuJnnKWXaCISD6fcpZdoIJ0NJUS5OWVNFOkZMUi5JUV9DQVBFWC5JUV9MVE0uMjAyMi0wNy0xMwEAAAArAQoAAgAAAActNTUuMDczAQgA | AG1: AAAFAAAAATEBAAAACy0yMDk4NDQ1ODk1AwAAAAMxNjACAAAABDIwMjEEAAAAATAHAAAACTcvMTMvMjAyMggAAAAJMy8zMS8yMDIyCQAAAAEwo7iZ5yll2gg7lOr3KWXaCC9DSVEuVFNYOlNJUy5JUV9CQVNJQ19FUFNfSU5DTC5JUV9MVE0uMjAyMi0wNy0xMwEAAABIgDAAAgAAAAgwLjIwMzYzOQEIAAAABQAAAAExAQAAAAstMjA5NzM2NDMzNwMAAAACMjcCAAAAATkEAAAAATAHAAAACTcvMTMvMjAyMggAAAAJMy8zMS8yMDIyCQAAAAEwo7iZ5yll2gg7lOr3KWXaCClDSVEuS0xTRTpMS0wuSVFfUkVWRU5VRS5JUV9MVE0uMjAyMi0wNy0xMwEAAABcWQITAgAAAAk1My4yOTczNjEBCAAAAAUAAAABMQEAAAALLTIxMTM4ODkxMTcDAAAAAzExMQIAAAADMTEyBAAAAAEwBwAAAAk3LzEzLzIwMjIIAAAACTkvMzAvMjAyMQkAAAABMKO4mecpZdoIIffp9yll2ggnQ0lRLlRXU0U6NDEwNi5JUV9FQklULklRX0xUTS4yMDIyLTA3LTEzAQAAACpCNgECAAAABzEwMS4zMDgBCAAAAAUAAAABMQEAAAALLTIwOTE1NjAwNzgDAAAAAzE1NgIAAAADNDAwBAAAAAEwBwAAAAk3LzEzLzIwMjIIAAAACTMvMzEvMjAyMgkAAAABMKO4mecpZdoIIffp9yll2ggxQ0lRLlRXU0U6NDEwNi5JUV9CQVNJQ19FUFNfSU5DTC5JUV9OVE0uMjAyMi0wNy0xMwEAAAAqQjYBAwAAAAAAo7iZ5yll2ggpH+r3KWXaCCxDSVEuVFNFOjc4MTMuSVFf | AH1: VE9UQUxfREVCVC5JUV9MVE0uMjAyMi0wNy0xMwEAAAAU/x0DAgAAAAQyNDEyAQgAAAAFAAAAATEBAAAACy0yMDk1MzIzMDkwAwAAAAI3OQIAAAAENDE3MwQAAAABMAcAAAAJNy8xMy8yMDIyCAAAAAkzLzMxLzIwMjIJAAAAATCjuJnnKWXaCOfR6fcpZdoIKENJUS5OWVNFOkdWQS5JUV9FQklUREEuSVFfTFRNLjIwMjItMDctMTMBAAAAujUEAAIAAAAHMTIyLjk0MQEIAAAABQAAAAExAQAAAAstMjA5OTc5NjkzNwMAAAADMTYwAgAAAAQ0MDUxBAAAAAEwBwAAAAk3LzEzLzIwMjIIAAAACTMvMzEvMjAyMgkAAAABMKbfmecpZdoIMbvq9yll2ggqQ0lRLk9NOkFSSk8gQi5JUV9MVF9ERUJULklRX0xUTS4yMDIyLTA3LTEzAQAAAFOW8Q4CAAAABDEwNzUBCAAAAAUAAAABMQEAAAALLTIxMDIyNjU2OTgDAAAAAzEzNwIAAAAEMTA0OQQAAAABMAcAAAAJNy8xMy8yMDIyCAAAAAkzLzMxLzIwMjIJAAAAATCjuJnnKWXaCISD6fcpZdoILkNJUS5OQVNEQVFHUzpBTVNDLklRX1JFVkVOVUUuSVFfTFRNLjIwMjItMDctMTMBAAAAdYgAAAIAAAAHMTA4LjQzNQEIAAAABQAAAAExAQAAAAstMjA5Mjc1ODc4MwMAAAADMTYwAgAAAAMxMTIEAAAAATAHAAAACTcvMTMvMjAyMggAAAAJMy8zMS8yMDIyCQAAAAEwo7iZ5yll2ghWRer3KWXaCChDSVEuVFNYOlNJUy5JUV9TVF9ERUJULklRX0xUTS4yMDIyLTA3LTEzAQAAAEiAMAAD | AI1: AAAAAACjuJnnKWXaCAZs6vcpZdoIMUNJUS5UV1NFOjQxMDYuSVFfQkFTSUNfRVBTX0lOQ0wuSVFfTFRNLjIwMjItMDctMTMBAAAAKkI2AQIAAAAIMS4wMjk2OTkBCAAAAAUAAAABMQEAAAALLTIwOTE1NjAwNzgDAAAAAzE1NgIAAAABOQQAAAABMAcAAAAJNy8xMy8yMDIyCAAAAAkzLzMxLzIwMjIJAAAAATCjuJnnKWXaCCkf6vcpZdoIJkNJUS5UU0U6NzgxMy5JUV9FQklULklRX0xUTS4yMDIyLTA3LTEzAQAAABT/HQMCAAAAAzI1MQEIAAAABQAAAAExAQAAAAstMjA5NTMyMzA5MAMAAAACNzkCAAAAAzQwMAQAAAABMAcAAAAJNy8xMy8yMDIyCAAAAAkzLzMxLzIwMjIJAAAAATCjuJnnKWXaCDap6fcpZdoIJkNJUS5UU0U6NzgxNy5JUV9FQklULklRX0xUTS4yMDIyLTA3LTEzAQAAAJ1zDQACAAAABTExOTc1AQgAAAAFAAAAATEBAAAACy0yMDg5Nzg0NDYwAwAAAAI3OQIAAAADNDAwBAAAAAEwBwAAAAk3LzEzLzIwMjIIAAAACTMvMzEvMjAyMgkAAAABMKO4mecpZdoIhIPp9yll2ggoQ0lRLlRTWDpTSVMuSVFfTFRfREVCVC5JUV9MVE0uMjAyMi0wNy0xMwEAAABIgDAAAgAAAAczNjIuMzk4AQgAAAAFAAAAATEBAAAACy0yMDk3MzY0MzM3AwAAAAIyNwIAAAAEMTA0OQQAAAABMAcAAAAJNy8xMy8yMDIyCAAAAAkzLzMxLzIwMjIJAAAAATCjuJnnKWXaCAZs6vcpZdoIKkNJUS5UV1NFOjQxMDYuSVFfU1RfREVC | AJ1: VC5JUV9MVE0uMjAyMi0wNy0xMwEAAAAqQjYBAgAAAAczOTAuOTM0AQgAAAAFAAAAATEBAAAACy0yMDkxNTYwMDc4AwAAAAMxNTYCAAAABDEwNDYEAAAAATAHAAAACTcvMTMvMjAyMggAAAAJMy8zMS8yMDIyCQAAAAEwo7iZ5yll2ggpH+r3KWXaCClDSVEuTllTRTpGTFIuSVFfUkVWRU5VRS5JUV9MVE0uMjAyMi0wNy0xMwEAAAArAQoAAgAAAAkxMjIwOS44NzkBCAAAAAUAAAABMQEAAAALLTIwOTg0NDU4OTUDAAAAAzE2MAIAAAADMTEyBAAAAAEwBwAAAAk3LzEzLzIwMjIIAAAACTMvMzEvMjAyMgkAAAABMKO4mecpZdoIO5Tq9yll2ggrQ0lRLlRTWDpTSVMuSVFfVE9UQUxfREVCVC5JUV9MVE0uMjAyMi0wNy0xMwEAAABIgDAAAgAAAAc0MTQuMTMxAQgAAAAFAAAAATEBAAAACy0yMDk3MzY0MzM3AwAAAAIyNwIAAAAENDE3MwQAAAABMAcAAAAJNy8xMy8yMDIyCAAAAAkzLzMxLzIwMjIJAAAAATCjuJnnKWXaCAZs6vcpZdoIKENJUS5LTFNFOkxLTC5JUV9FQklUREEuSVFfTFRNLjIwMjItMDctMTMBAAAAXFkCEwIAAAAILTcuOTAyNjgBCAAAAAUAAAABMQEAAAALLTIxMTM4ODkxMTcDAAAAAzExMQIAAAAENDA1MQQAAAABMAcAAAAJNy8xMy8yMDIyCAAAAAk5LzMwLzIwMjEJAAAAATCjuJnnKWXaCCH36fcpZdoIKkNJUS5UV1NFOjQxMDYuSVFfTFRfREVCVC5JUV9MVE0uMjAyMi0wNy0xMwEAAAAqQjYBAgAA | AK1: AAcxMjIuMjk4AQgAAAAFAAAAATEBAAAACy0yMDkxNTYwMDc4AwAAAAMxNTYCAAAABDEwNDkEAAAAATAHAAAACTcvMTMvMjAyMggAAAAJMy8zMS8yMDIyCQAAAAEwo7iZ5yll2ggpH+r3KWXaCDBDSVEuVFNFOjc4MTcuSVFfQkFTSUNfRVBTX0lOQ0wuSVFfTFRNLjIwMjItMDctMTMBAAAAnXMNAAIAAAAKMTU2LjM3NzEwNgEIAAAABQAAAAExAQAAAAstMjA4OTc4NDQ2MAMAAAACNzkCAAAAATkEAAAAATAHAAAACTcvMTMvMjAyMggAAAAJMy8zMS8yMDIyCQAAAAEwo7iZ5yll2gg2qen3KWXaCCdDSVEuVFNFOjc4MTMuSVFfQ0FQRVguSVFfTFRNLjIwMjItMDctMTMBAAAAFP8dAwMAAAAAAKO4mecpZdoI59Hp9yll2ggwQ0lRLk5ZU0U6R1ZBLklRX0JBU0lDX0VQU19JTkNMLklRX05UTS4yMDIyLTA3LTEzAQAAALo1BAADAAAAAACm35nnKWXaCDG76vcpZdoIJkNJUS5OWVNFOkdWQS5JUV9FQklULklRX0xUTS4yMDIyLTA3LTEzAQAAALo1BAACAAAABjYxLjI5MQEIAAAABQAAAAExAQAAAAstMjA5OTc5NjkzNwMAAAADMTYwAgAAAAM0MDAEAAAAATAHAAAACTcvMTMvMjAyMggAAAAJMy8zMS8yMDIyCQAAAAEwpt+Z5yll2ggxu+r3KWXaCC1DSVEuVFdTRTo0MTA2LklRX1RPVEFMX0RFQlQuSVFfTFRNLjIwMjItMDctMTMBAAAAKkI2AQIAAAAHNTc0LjY0NAEIAAAABQAAAAExAQAAAAstMjA5MTU2MDA3OAMAAAAD | AL1: MTU2AgAAAAQ0MTczBAAAAAEwBwAAAAk3LzEzLzIwMjIIAAAACTMvMzEvMjAyMgkAAAABMKO4mecpZdoIVkXq9yll2ggtQ0lRLk5BU0RBUUdTOkFNU0MuSVFfRUJJVERBLklRX0xUTS4yMDIyLTA3LTEzAQAAAHWIAAACAAAABy0yMC4zMTcBCAAAAAUAAAABMQEAAAALLTIwOTI3NTg3ODMDAAAAAzE2MAIAAAAENDA1MQQAAAABMAcAAAAJNy8xMy8yMDIyCAAAAAkzLzMxLzIwMjIJAAAAATCjuJnnKWXaCFZF6vcpZdoIJ0NJUS5UU0U6NzgxNy5JUV9DQVBFWC5JUV9MVE0uMjAyMi0wNy0xMwEAAACdcw0AAgAAAAUtMTA0NwEIAAAABQAAAAExAQAAAAstMjA4OTc4NDQ2MAMAAAACNzkCAAAABDIwMjEEAAAAATAHAAAACTcvMTMvMjAyMggAAAAJMy8zMS8yMDIyCQAAAAEwo7iZ5yll2giEg+n3KWXaCClDSVEuVFNFOjc4MTcuSVFfU1RfREVCVC5JUV9MVE0uMjAyMi0wNy0xMwEAAACdcw0AAwAAAAAAo7iZ5yll2gg2qen3KWXaCDBDSVEuTllTRTpHVkEuSVFfQkFTSUNfRVBTX0lOQ0wuSVFfTFRNLjIwMjItMDctMTMBAAAAujUEAAIAAAAIMS4zODMzNDQBCAAAAAUAAAABMQEAAAALLTIwOTk3OTY5MzcDAAAAAzE2MAIAAAABOQQAAAABMAcAAAAJNy8xMy8yMDIyCAAAAAkzLzMxLzIwMjIJAAAAATCm35nnKWXaCDG76vcpZdoIJ0NJUS5UU1g6U0lTLklRX0VCSVREQS5JUV9MVE0uMjAyMi0wNy0xMwEAAABIgDAAAgAA | AM1: AAY4NS4yNjMBCAAAAAUAAAABMQEAAAALLTIwOTczNjQzMzcDAAAAAjI3AgAAAAQ0MDUxBAAAAAEwBwAAAAk3LzEzLzIwMjIIAAAACTMvMzEvMjAyMgkAAAABMKO4mecpZdoIBmzq9yll2ggpQ0lRLk9NOkFSSk8gQi5JUV9FQklUREEuSVFfTFRNLjIwMjItMDctMTMBAAAAU5bxDgIAAAAEMTcxNAEIAAAABQAAAAExAQAAAAstMjEwMjI2NTY5OAMAAAADMTM3AgAAAAQ0MDUxBAAAAAEwBwAAAAk3LzEzLzIwMjIIAAAACTMvMzEvMjAyMgkAAAABMKO4mecpZdoIRVvp9yll2ggpQ0lRLlRTRTo3ODE3LklRX0xUX0RFQlQuSVFfTFRNLjIwMjItMDctMTMBAAAAnXMNAAMAAAAAAKO4mecpZdoINqnp9yll2ggpQ0lRLk5ZU0U6R1ZBLklRX1NUX0RFQlQuSVFfTFRNLjIwMjItMDctMTMBAAAAujUEAAMAAAAAAKbfmecpZdoIMbvq9yll2ggpQ0lRLlRTRTo3ODE3LklRX1JFVkVOVUUuSVFfTFRNLjIwMjItMDctMTMBAAAAnXMNAAIAAAAFOTAzNTIBCAAAAAUAAAABMQEAAAALLTIwODk3ODQ0NjADAAAAAjc5AgAAAAMxMTIEAAAAATAHAAAACTcvMTMvMjAyMggAAAAJMy8zMS8yMDIyCQAAAAEwo7iZ5yll2gg2qen3KWXaCCZDSVEuVFNYOlNJUy5JUV9DQVBFWC5JUV9MVE0uMjAyMi0wNy0xMwEAAABIgDAAAgAAAAYtNy40ODcBCAAAAAUAAAABMQEAAAALLTIwOTczNjQzMzcDAAAAAjI3AgAAAAQyMDIxBAAAAAEwBwAAAAk3 | AN1: LzEzLzIwMjIIAAAACTMvMzEvMjAyMgkAAAABMKO4mecpZdoIBmzq9yll2ggoQ0lRLk5ZU0U6RkxSLklRX0VCSVREQS5JUV9MVE0uMjAyMi0wNy0xMwEAAAArAQoAAgAAAAUzMTAuNQEIAAAABQAAAAExAQAAAAstMjA5ODQ0NTg5NQMAAAADMTYwAgAAAAQ0MDUxBAAAAAEwBwAAAAk3LzEzLzIwMjIIAAAACTMvMzEvMjAyMgkAAAABMKO4mecpZdoIO5Tq9yll2ggmQ0lRLktMU0U6TEtMLklRX0VCSVQuSVFfTFRNLjIwMjItMDctMTMBAAAAXFkCEwIAAAAJLTkuNTkwODE5AQgAAAAFAAAAATEBAAAACy0yMTEzODg5MTE3AwAAAAMxMTECAAAAAzQwMAQAAAABMAcAAAAJNy8xMy8yMDIyCAAAAAk5LzMwLzIwMjEJAAAAATCjuJnnKWXaCCH36fcpZdoILENJUS5UU0U6NzgxNy5JUV9UT1RBTF9ERUJULklRX0xUTS4yMDIyLTA3LTEzAQAAAJ1zDQACAAAABDYxMzUBCAAAAAUAAAABMQEAAAALLTIwODk3ODQ0NjADAAAAAjc5AgAAAAQ0MTczBAAAAAEwBwAAAAk3LzEzLzIwMjIIAAAACTMvMzEvMjAyMgkAAAABMKO4mecpZdoINqnp9yll2ggpQ0lRLlRTRTo3ODEzLklRX1JFVkVOVUUuSVFfTFRNLjIwMjItMDctMTMBAAAAFP8dAwIAAAAENjY5MAEIAAAABQAAAAExAQAAAAstMjA5NTMyMzA5MAMAAAACNzkCAAAAAzExMgQAAAABMAcAAAAJNy8xMy8yMDIyCAAAAAkzLzMxLzIwMjIJAAAAATCjuJnnKWXaCDap6fcpZdoI | AO1: KUNJUS5OWVNFOkdWQS5JUV9MVF9ERUJULklRX0xUTS4yMDIyLTA3LTEzAQAAALo1BAACAAAABzI5MC41NDkBCAAAAAUAAAABMQEAAAALLTIwOTk3OTY5MzcDAAAAAzE2MAIAAAAEMTA0OQQAAAABMAcAAAAJNy8xMy8yMDIyCAAAAAkzLzMxLzIwMjIJAAAAATCm35nnKWXaCDG76vcpZdoINUNJUS5OQVNEQVFHUzpBTVNDLklRX0JBU0lDX0VQU19JTkNMLklRX05UTS4yMDIyLTA3LTEzAQAAAHWIAAADAAAAAACjuJnnKWXaCAZs6vcpZdoIMENJUS5LTFNFOkxLTC5JUV9CQVNJQ19FUFNfSU5DTC5JUV9MVE0uMjAyMi0wNy0xMwEAAABcWQITAgAAAAktMC4wNzMzMzMBCAAAAAUAAAABMQEAAAALLTIxMTM4ODkxMTcDAAAAAzExMQIAAAABOQQAAAABMAcAAAAJNy8xMy8yMDIyCAAAAAk5LzMwLzIwMjEJAAAAATCjuJnnKWXaCCH36fcpZdoIKENJUS5UV1NFOjQxMDYuSVFfQ0FQRVguSVFfTFRNLjIwMjItMDctMTMBAAAAKkI2AQIAAAAHLTQ2LjUyOAEIAAAABQAAAAExAQAAAAstMjA5MTU2MDA3OAMAAAADMTU2AgAAAAQyMDIxBAAAAAEwBwAAAAk3LzEzLzIwMjIIAAAACTMvMzEvMjAyMgkAAAABMKO4mecpZdoIKR/q9yll2ggrQ0lRLk5BU0RBUUdTOkFNU0MuSVFfRUJJVC5JUV9MVE0uMjAyMi0wNy0xMwEAAAB1iAAAAgAAAActMjUuNjU4AQgAAAAFAAAAATEBAAAACy0yMDkyNzU4NzgzAwAAAAMxNjACAAAAAzQw | AP1: MAQAAAABMAcAAAAJNy8xMy8yMDIyCAAAAAkzLzMxLzIwMjIJAAAAATCjuJnnKWXaCFZF6vcpZdoIMUNJUS5PTTpBUkpPIEIuSVFfQkFTSUNfRVBTX0lOQ0wuSVFfTFRNLjIwMjItMDctMTMBAAAAU5bxDgIAAAAIMi42OTExOTYBCAAAAAUAAAABMQEAAAALLTIxMDIyNjU2OTgDAAAAAzEzNwIAAAABOQQAAAABMAcAAAAJNy8xMy8yMDIyCAAAAAkzLzMxLzIwMjIJAAAAATCjuJnnKWXaCISD6fcpZdoIJ0NJUS5PTTpBUkpPIEIuSVFfRUJJVC5JUV9MVE0uMjAyMi0wNy0xMwEAAABTlvEOAgAAAAQxMTE5AQgAAAAFAAAAATEBAAAACy0yMTAyMjY1Njk4AwAAAAMxMzcCAAAAAzQwMAQAAAABMAcAAAAJNy8xMy8yMDIyCAAAAAkzLzMxLzIwMjIJAAAAATCjuJnnKWXaCEVb6fcpZdoILENJUS5OWVNFOkdWQS5JUV9UT1RBTF9ERUJULklRX0xUTS4yMDIyLTA3LTEzAQAAALo1BAACAAAABzMzMi40NzMBCAAAAAUAAAABMQEAAAALLTIwOTk3OTY5MzcDAAAAAzE2MAIAAAAENDE3MwQAAAABMAcAAAAJNy8xMy8yMDIyCAAAAAkzLzMxLzIwMjIJAAAAATCm35nnKWXaCDG76vcpZdoINUNJUS5OQVNEQVFHUzpBTVNDLklRX0JBU0lDX0VQU19JTkNMLklRX0xUTS4yMDIyLTA3LTEzAQAAAHWIAAACAAAACS0wLjcwNTU0NwEIAAAABQAAAAExAQAAAAstMjA5Mjc1ODc4MwMAAAADMTYwAgAAAAE5BAAAAAEwBwAAAAk3LzEzLzIw | AQ1: MjIIAAAACTMvMzEvMjAyMgkAAAABMKO4mecpZdoIVkXq9yll2ggpQ0lRLktMU0U6TEtMLklRX1NUX0RFQlQuSVFfTFRNLjIwMjItMDctMTMBAAAAXFkCEwIAAAAIMC4yMzc2ODEBCAAAAAUAAAABMQEAAAALLTIxMTM4ODkxMTcDAAAAAzExMQIAAAAEMTA0NgQAAAABMAcAAAAJNy8xMy8yMDIyCAAAAAk5LzMwLzIwMjEJAAAAATCjuJnnKWXaCCH36fcpZdoIKENJUS5UU1g6U0lTLklRX1JFVkVOVUUuSVFfTFRNLjIwMjItMDctMTMBAAAASIAwAAIAAAAHNzMyLjQ0NAEIAAAABQAAAAExAQAAAAstMjA5NzM2NDMzNwMAAAACMjcCAAAAAzExMgQAAAABMAcAAAAJNy8xMy8yMDIyCAAAAAkzLzMxLzIwMjIJAAAAATCjuJnnKWXaCAZs6vcpZdoIJkNJUS5OWVNFOkZMUi5JUV9FQklULklRX0xUTS4yMDIyLTA3LTEzAQAAACsBCgACAAAABzI0NS4xNDQBCAAAAAUAAAABMQEAAAALLTIwOTg0NDU4OTUDAAAAAzE2MAIAAAADNDAwBAAAAAEwBwAAAAk3LzEzLzIwMjIIAAAACTMvMzEvMjAyMgkAAAABMKO4mecpZdoIO5Tq9yll2ggwQ0lRLk5ZU0U6RkxSLklRX0JBU0lDX0VQU19JTkNMLklRX05UTS4yMDIyLTA3LTEzAQAAACsBCgADAAAAAACm35nnKWXaCDuU6vcpZdoILkNJUS5OQVNEQVFHUzpBTVNDLklRX1NUX0RFQlQuSVFfTFRNLjIwMjItMDctMTMBAAAAdYgAAAMAAAAAAKO4mecpZdoIVkXq9yll2ggoQ0lRLlRT | AR1: RTo3ODEzLklRX0VCSVREQS5JUV9MVE0uMjAyMi0wNy0xMwEAAAAU/x0DAgAAAAMyODkBCAAAAAUAAAABMQEAAAALLTIwOTUzMjMwOTADAAAAAjc5AgAAAAQ0MDUxBAAAAAEwBwAAAAk3LzEzLzIwMjIIAAAACTMvMzEvMjAyMgkAAAABMKO4mecpZdoINqnp9yll2ggpQ0lRLktMU0U6TEtMLklRX0xUX0RFQlQuSVFfTFRNLjIwMjItMDctMTMBAAAAXFkCEwIAAAAINC44ODg3MzcBCAAAAAUAAAABMQEAAAALLTIxMTM4ODkxMTcDAAAAAzExMQIAAAAEMTA0OQQAAAABMAcAAAAJNy8xMy8yMDIyCAAAAAk5LzMwLzIwMjEJAAAAATCjuJnnKWXaCCH36fcpZdoILUNJUS5PTTpBUkpPIEIuSVFfVE9UQUxfREVCVC5JUV9MVE0uMjAyMi0wNy0xMwEAAABTlvEOAgAAAAQ1ODUwAQgAAAAFAAAAATEBAAAACy0yMTAyMjY1Njk4AwAAAAMxMzcCAAAABDQxNzMEAAAAATAHAAAACTcvMTMvMjAyMggAAAAJMy8zMS8yMDIyCQAAAAEwo7iZ5yll2giEg+n3KWXaCDBDSVEuTllTRTpGTFIuSVFfQkFTSUNfRVBTX0lOQ0wuSVFfTFRNLjIwMjItMDctMTMBAAAAKwEKAAIAAAAJLTIuMzk5MTg3AQgAAAAFAAAAATEBAAAACy0yMDk4NDQ1ODk1AwAAAAMxNjACAAAAATkEAAAAATAHAAAACTcvMTMvMjAyMggAAAAJMy8zMS8yMDIyCQAAAAEwpt+Z5yll2gg7lOr3KWXaCCpDSVEuVFdTRTo0MTA2LklRX1JFVkVOVUUuSVFfTFRNLjIwMjIt | AS1: MDctMTMBAAAAKkI2AQIAAAAIMjM4OC41ODIBCAAAAAUAAAABMQEAAAALLTIwOTE1NjAwNzgDAAAAAzE1NgIAAAADMTEyBAAAAAEwBwAAAAk3LzEzLzIwMjIIAAAACTMvMzEvMjAyMgkAAAABMKO4mecpZdoIIffp9yll2gguQ0lRLk5BU0RBUUdTOkFNU0MuSVFfTFRfREVCVC5JUV9MVE0uMjAyMi0wNy0xMwEAAAB1iAAAAgAAAAUwLjA4OQEIAAAABQAAAAExAQAAAAstMjA5Mjc1ODc4MwMAAAADMTYwAgAAAAQxMDQ5BAAAAAEwBwAAAAk3LzEzLzIwMjIIAAAACTMvMzEvMjAyMgkAAAABMKO4mecpZdoIVkXq9yll2ggsQ0lRLktMU0U6TEtMLklRX1RPVEFMX0RFQlQuSVFfTFRNLjIwMjItMDctMTMBAAAAXFkCEwIAAAAIOC4yMzI3MTgBCAAAAAUAAAABMQEAAAALLTIxMTM4ODkxMTcDAAAAAzExMQIAAAAENDE3MwQAAAABMAcAAAAJNy8xMy8yMDIyCAAAAAk5LzMwLzIwMjEJAAAAATCjuJnnKWXaCCH36fcpZdoIJ0NJUS5OWVNFOkdWQS5JUV9DQVBFWC5JUV9MVE0uMjAyMi0wNy0xMwEAAAC6NQQAAgAAAAgtMTA3LjMwMgEIAAAABQAAAAExAQAAAAstMjA5OTc5NjkzNwMAAAADMTYwAgAAAAQyMDIxBAAAAAEwBwAAAAk3LzEzLzIwMjIIAAAACTMvMzEvMjAyMgkAAAABMKbfmecpZdoIMbvq9yll2ggqQ0lRLk9NOkFSSk8gQi5JUV9TVF9ERUJULklRX0xUTS4yMDIyLTA3LTEzAQAAAFOW8Q4DAAAAAACjuJnnKWXa | AT1: CISD6fcpZdoIKUNJUS5OWVNFOkZMUi5JUV9TVF9ERUJULklRX0xUTS4yMDIyLTA3LTEzAQAAACsBCgADAAAAAACm35nnKWXaCDG76vcpZdoIMUNJUS5OQVNEQVFHUzpBTVNDLklRX1RPVEFMX0RFQlQuSVFfTFRNLjIwMjItMDctMTMBAAAAdYgAAAIAAAAFMy44MDIBCAAAAAUAAAABMQEAAAALLTIwOTI3NTg3ODMDAAAAAzE2MAIAAAAENDE3MwQAAAABMAcAAAAJNy8xMy8yMDIyCAAAAAkzLzMxLzIwMjIJAAAAATCjuJnnKWXaCFZF6vcpZdoIIkNJUS5LTFNFOkxLTC5JUV9DQVBFWF9FU1QuSVFfRlkrMS4BAAAAXFkCEwMAAAAAACySmv0KZdoILR4C6Cll2gggQ0lRLlRTRTo3ODEzLklRX0VCSVRfRVNULklRX05UTS4BAAAAFP8dAwMAAAAAACySmv0KZdoI+ZIC6Cll2gghQ0lRLktMU0U6TEtMLklRX0NBUEVYX0VTVC5JUV9OVE0uAQAAAFxZAhMDAAAAAAAskpr9CmXaCC0eAugpZdoIJENJUS5UV1NFOjQxMDYuSVFfRUJJVERBX0VTVC5JUV9GWSsxLgEAAAAqQjYBAwAAAAAALJKa/Qpl2gjO+AHoKWXaCCFDSVEuVFNYOlNJUy5JUV9FQklUREFfRVNULklRX05UTS4BAAAASIAwAAIAAAAIMTI1LjE2MjUBDgAAAAUAAAACMTEBAAAAATACAAAABzM2NTkzOTgDAAAABjEwMDE4NwQAAAABMwYAAAABMAcAAAACMjcIAAAAATAJAAAAATEKAAAAATALAAAACzEyODc2MDI2NjE3DAAAAAIxMg0AAAAJNy8xNC8yMDIyEAAA | AU1: AAk3LzEzLzIwMjIskpr9CmXaCH80AegpZdoIJENJUS5UU0U6NzgxNy5JUV9SRVZFTlVFX0VTVC5JUV9GWSsxLgEAAACdcw0AAgAAAAU5MzcwMAEOAAAABQAAAAEzAQAAAAEwAgAAAAoxMDA0MTExMTgyAwAAAAYxMDAxODAEAAAAAjU2BgAAAAEwBwAAAAI3OQgAAAABMAkAAAABMQoAAAABMAsAAAALMTI5MDkzNTUxMjYMAAAAATENAAAACTcvMTQvMjAyMhAAAAAJNy8xMy8yMDIyLJKa/Qpl2gjnuQLoKWXaCCFDSVEuVFNFOjc4MTMuSVFfRUJJVF9FU1QuSVFfRlkrMS4BAAAAFP8dAwMAAAAAACySmv0KZdoI+ZIC6Cll2ggiQ0lRLlRTWDpTSVMuSVFfRUJJVERBX0VTVC5JUV9GWSsxLgEAAABIgDAAAgAAAAgxMjIuNDg3NQEOAAAABQAAAAEzAQAAAAEwAgAAAAoxMDAzNTYzODk3AwAAAAYxMDAxODcEAAAAATMGAAAAATAHAAAAAjI3CAAAAAEwCQAAAAExCgAAAAEwCwAAAAsxMjg3NDcwMTMxNwwAAAABMQ0AAAAJNy8xNC8yMDIyEAAAAAk3LzEzLzIwMjIskpr9CmXaCIANAegpZdoIIUNJUS5OWVNFOkdWQS5JUV9DQVBFWF9FU1QuSVFfTlRNLgEAAAC6NQQAAgAAAAktMTE4LjE3MjUBDgAAAAUAAAACMTEBAAAAATACAAAACTcwMTM2MDM2MwMAAAAGMTA0MDkwBAAAAAEyBgAAAAEwBwAAAAMxNjAIAAAAATAJAAAAATEKAAAAATALAAAACzEyODgwMDI4OTIyDAAAAAIxMg0AAAAJNy8xNC8yMDIyEAAAAAk3LzEzLzIw | AV1: MjIskpr9CmXaCEaI/+cpZdoIJENJUS5UV1NFOjQxMDYuSVFfUkVWRU5VRV9FU1QuSVFfTlRNLgEAAAAqQjYBAwAAAAAALJKa/Qpl2ghn0QHoKWXaCCJDSVEuVFNFOjc4MTMuSVFfRUJJVERBX0VTVC5JUV9OVE0uAQAAABT/HQMDAAAAAAAskpr9CmXaCAdsAugpZdoII0NJUS5UV1NFOjQxMDYuSVFfRUJJVERBX0VTVC5JUV9OVE0uAQAAACpCNgEDAAAAAAAskpr9CmXaCM74AegpZdoIIkNJUS5OWVNFOkdWQS5JUV9DQVBFWF9FU1QuSVFfRlkrMS4BAAAAujUEAAIAAAAILTExOC4xNzUBDgAAAAUAAAABMwEAAAABMAIAAAAKMTAwMjYxMjU2NgMAAAAGMTA0MDkwBAAAAAEyBgAAAAEwBwAAAAMxNjAIAAAAATAJAAAAATEKAAAAATALAAAACzEyODgwMDI3MTI0DAAAAAExDQAAAAk3LzE0LzIwMjIQAAAACTcvMTMvMjAyMiySmv0KZdoIRoj/5yll2gglQ0lRLlRXU0U6NDEwNi5JUV9SRVZFTlVFX0VTVC5JUV9GWSsxLgEAAAAqQjYBAwAAAAAALJKa/Qpl2ghn0QHoKWXaCCJDSVEuVFNYOlNJUy5JUV9SRVZFTlVFX0VTVC5JUV9OVE0uAQAAAEiAMAACAAAACDc5My45NzE0AQ4AAAAFAAAAAjExAQAAAAEwAgAAAAczNjU5Mzk4AwAAAAYxMDAxODAEAAAAATMGAAAAATAHAAAAAjI3CAAAAAEwCQAAAAExCgAAAAEwCwAAAAsxMjg3NjI4MDM0NwwAAAACMTINAAAACTcvMTQvMjAyMhAAAAAJNy8xMy8yMDIyLJKa/Qpl2giA | AW1: DQHoKWXaCCBDSVEuTllTRTpGTFIuSVFfRUJJVF9FU1QuSVFfTlRNLgEAAAArAQoAAgAAAAgzNjMuMDIyNwEOAAAABQAAAAIxMQEAAAABMAIAAAAHMzk3MzQ4MwMAAAAGMTAwMjE1BAAAAAEyBgAAAAEwBwAAAAMxNjAIAAAAATAJAAAAATEKAAAAATALAAAACzEyOTE5ODAzNjg4DAAAAAIxMg0AAAAJNy8xNC8yMDIyEAAAAAk3LzEzLzIwMjIskpr9CmXaCHy/AOgpZdoIIUNJUS5PTTpBUkpPIEIuSVFfRUJJVF9FU1QuSVFfTlRNLgEAAABTlvEOAgAAAAkxMzA2Ljk3MTgBDgAAAAUAAAACMTEBAAAAATACAAAABzQyNTYzMDQDAAAABjEwMDIxNQQAAAABMwYAAAABMAcAAAADMTM3CAAAAAEwCQAAAAExCgAAAAEwCwAAAAsxMjkzMTMzNTAxNQwAAAACMTINAAAACTcvMTQvMjAyMhAAAAAJNy8xMy8yMDIyLJKa/Qpl2gjb4ALoKWXaCCNDSVEuVFNFOjc4MTMuSVFfRUJJVERBX0VTVC5JUV9GWSsxLgEAAAAU/x0DAwAAAAAALJKa/Qpl2ggHbALoKWXaCCJDSVEuVFNFOjc4MTcuSVFfQ0FQRVhfRVNULklRX0ZZKzEuAQAAAJ1zDQACAAAABS0yOTAwAQ4AAAAFAAAAATMBAAAAATACAAAACjEwMDQxMTExODIDAAAABjEwNDA5MAQAAAACNTYGAAAAATAHAAAAAjc5CAAAAAEwCQAAAAExCgAAAAEwCwAAAAsxMjcwODQxODUxMAwAAAABMQ0AAAAJNy8xNC8yMDIyEAAAAAk3LzEzLzIwMjIskpr9CmXaCPmSAugpZdoIIUNJUS5O | AX1: WVNFOkZMUi5JUV9FQklUX0VTVC5JUV9GWSsxLgEAAAArAQoAAgAAAAkzNDQuMDE2MTMBDgAAAAUAAAABMwEAAAABMAIAAAAKMTAwMzcwODc5NQMAAAAGMTAwMjE1BAAAAAEyBgAAAAEwBwAAAAMxNjAIAAAAATAJAAAAATEKAAAAATALAAAACzEyOTE5Nzg5NTg3DAAAAAExDQAAAAk3LzE0LzIwMjIQAAAACTcvMTMvMjAyMiySmv0KZdoIiOYA6Cll2ggjQ0lRLlRTWDpTSVMuSVFfUkVWRU5VRV9FU1QuSVFfRlkrMS4BAAAASIAwAAIAAAAHNzgwLjc3NQEOAAAABQAAAAEzAQAAAAEwAgAAAAoxMDAzNTYzODk3AwAAAAYxMDAxODAEAAAAATMGAAAAATAHAAAAAjI3CAAAAAEwCQAAAAExCgAAAAEwCwAAAAsxMjg3NjI3NjY4MwwAAAABMQ0AAAAJNy8xNC8yMDIyEAAAAAk3LzEzLzIwMjIskpr9CmXaCIANAegpZdoIIkNJUS5PTTpBUkpPIEIuSVFfRUJJVF9FU1QuSVFfRlkrMS4BAAAAU5bxDgIAAAAKMTE4OC44NDU0NgEOAAAABQAAAAEzAQAAAAEwAgAAAAoxMDA0MDY2OTU0AwAAAAYxMDAyMTUEAAAAATMGAAAAATAHAAAAAzEzNwgAAAABMAkAAAABMQoAAAABMAsAAAALMTI5MzEzMTQzMDEMAAAAATENAAAACTcvMTQvMjAyMhAAAAAJNy8xMy8yMDIyLJKa/Qpl2gjb4ALoKWXaCCJDSVEuVFdTRTo0MTA2LklRX0NBUEVYX0VTVC5JUV9OVE0uAQAAACpCNgEDAAAAAAAskpr9CmXaCGfRAegpZdoIJUNJUS5OQVNEQVFH | AY1: UzpBTVNDLklRX0VCSVRfRVNULklRX05UTS4BAAAAdYgAAAIAAAAILTI2LjYwNzUBDgAAAAUAAAACMTEBAAAAATACAAAACjEwMDMyODMzOTIDAAAABjEwMDIxNQQAAAABMgYAAAABMAcAAAADMTYwCAAAAAEwCQAAAAExCgAAAAEwCwAAAAsxMjg5OTY5NzI2NQwAAAACMTINAAAACTcvMTQvMjAyMhAAAAAJNy8xMy8yMDIyLJKa/Qpl2gjOgwHoKWXaCCFDSVEuVFNFOjc4MTcuSVFfQ0FQRVhfRVNULklRX05UTS4BAAAAnXMNAAIAAAAFLTI5MDABDgAAAAUAAAACMTEBAAAAATACAAAACjEwMDQxMTExODIDAAAABjEwNDA5MAQAAAACNTYGAAAAATAHAAAAAjc5CAAAAAEwCQAAAAExCgAAAAEwCwAAAAsxMjcwODQxODUxMAwAAAACMTINAAAACTcvMTQvMjAyMhAAAAAJNy8xMy8yMDIyLJKa/Qpl2gj5kgLoKWXaCCNDSVEuVFNFOjc4MTcuSVFfUkVWRU5VRV9FU1QuSVFfTlRNLgEAAACdcw0AAgAAAAU5MzcwMAEOAAAABQAAAAIxMQEAAAABMAIAAAAKMTAwNDExMTE4MgMAAAAGMTAwMTgwBAAAAAI1NgYAAAABMAcAAAACNzkIAAAAATAJAAAAATEKAAAAATALAAAACzEyOTA5MzU1MTI2DAAAAAIxMg0AAAAJNy8xNC8yMDIyEAAAAAk3LzEzLzIwMjIskpr9CmXaCOe5AugpZdoII0NJUS5UV1NFOjQxMDYuSVFfQ0FQRVhfRVNULklRX0ZZKzEuAQAAACpCNgEDAAAAAAAskpr9CmXaCM74AegpZdoIIENJUS5LTFNFOkxLTC5J | AZ1: UV9FQklUX0VTVC5JUV9OVE0uAQAAAFxZAhMDAAAAAAAskpr9CmXaCE1GAugpZdoII0NJUS5UU0U6NzgxMy5JUV9SRVZFTlVFX0VTVC5JUV9OVE0uAQAAABT/HQMDAAAAAAAskpr9CmXaCAdsAugpZdoIIkNJUS5OWVNFOkZMUi5JUV9FQklUREFfRVNULklRX05UTS4BAAAAKwEKAAIAAAAINDkzLjMyNTUBDgAAAAUAAAACMTEBAAAAATACAAAABzM5NzM0ODMDAAAABjEwMDE4NwQAAAABMgYAAAABMAcAAAADMTYwCAAAAAEwCQAAAAExCgAAAAEwCwAAAAsxMjg4OTc0MTg5NwwAAAACMTINAAAACTcvMTQvMjAyMhAAAAAJNy8xMy8yMDIyLJKa/Qpl2gi5mADoKWXaCCBDSVEuVFNYOlNJUy5JUV9DQVBFWF9FU1QuSVFfTlRNLgEAAABIgDAAAgAAAAYtMTguMjUBDgAAAAUAAAACMTEBAAAAATACAAAABzM2NTkzOTgDAAAABjEwNDA5MAQAAAABMwYAAAABMAcAAAACMjcIAAAAATAJAAAAATEKAAAAATALAAAACzEyODc0MDk2ODA0DAAAAAIxMg0AAAAJNy8xNC8yMDIyEAAAAAk3LzEzLzIwMjIskpr9CmXaCIjmAOgpZdoIJkNJUS5OQVNEQVFHUzpBTVNDLklRX0VCSVRfRVNULklRX0ZZKzEuAQAAAHWIAAACAAAACC0yNi42MDc1AQ4AAAAFAAAAATMBAAAAATACAAAACjEwMDMyODMzOTIDAAAABjEwMDIxNQQAAAABMgYAAAABMAcAAAADMTYwCAAAAAEwCQAAAAExCgAAAAEwCwAAAAsxMjg5OTY5NzI2NQwAAAABMQ0AAAAJ | BA1: Ny8xNC8yMDIyEAAAAAk3LzEzLzIwMjIskpr9CmXaCEqpAegpZdoIIUNJUS5LTFNFOkxLTC5JUV9FQklUX0VTVC5JUV9GWSsxLgEAAABcWQITAwAAAAAALJKa/Qpl2ghNRgLoKWXaCCNDSVEuTllTRTpGTFIuSVFfRUJJVERBX0VTVC5JUV9GWSsxLgEAAAArAQoAAgAAAAk0MTkuNzM2NjIBDgAAAAUAAAABMwEAAAABMAIAAAAKMTAwMzcwODc5NQMAAAAGMTAwMTg3BAAAAAEyBgAAAAEwBwAAAAMxNjAIAAAAATAJAAAAATEKAAAAATALAAAACzEyODg5NzM0Nzk3DAAAAAExDQAAAAk3LzE0LzIwMjIQAAAACTcvMTMvMjAyMiySmv0KZdoIuZgA6Cll2gghQ0lRLlRTWDpTSVMuSVFfQ0FQRVhfRVNULklRX0ZZKzEuAQAAAEiAMAACAAAAAy0xOAEOAAAABQAAAAEzAQAAAAEwAgAAAAoxMDAzNTYzODk3AwAAAAYxMDQwOTAEAAAAATMGAAAAATAHAAAAAjI3CAAAAAEwCQAAAAExCgAAAAEwCwAAAAsxMjg3NDA5NDMyOQwAAAABMQ0AAAAJNy8xNC8yMDIyEAAAAAk3LzEzLzIwMjIskpr9CmXaCIjmAOgpZdoII0NJUS5PTTpBUkpPIEIuSVFfRUJJVERBX0VTVC5JUV9OVE0uAQAAAFOW8Q4CAAAACTIyNjYuMDkwMQEOAAAABQAAAAIxMQEAAAABMAIAAAAHNDI1NjMwNAMAAAAGMTAwMTg3BAAAAAEzBgAAAAEwBwAAAAMxMzcIAAAAATAJAAAAATEKAAAAATALAAAACzEyOTMxMzM1MDExDAAAAAIxMg0AAAAJNy8xNC8yMDIyEAAA | BB1: AAk3LzEzLzIwMjIskpr9CmXaCNvgAugpZdoIJENJUS5PTTpBUkpPIEIuSVFfRUJJVERBX0VTVC5JUV9GWSsxLgEAAABTlvEOAgAAAAoyMTg1Ljc1Njc0AQ4AAAAFAAAAATMBAAAAATACAAAACjEwMDQwNjY5NTQDAAAABjEwMDE4NwQAAAABMwYAAAABMAcAAAADMTM3CAAAAAEwCQAAAAExCgAAAAEwCwAAAAsxMjkzMTMxNDE4OQwAAAABMQ0AAAAJNy8xNC8yMDIyEAAAAAk3LzEzLzIwMjIskpr9CmXaCNAHA+gpZdoIJENJUS5UU0U6NzgxMy5JUV9SRVZFTlVFX0VTVC5JUV9GWSsxLgEAAAAU/x0DAwAAAAAALJKa/Qpl2ggHbALoKWXaCCdDSVEuTkFTREFRR1M6QU1TQy5JUV9FQklUREFfRVNULklRX05UTS4BAAAAdYgAAAIAAAAJLTE5LjgzMzMzAQ4AAAAFAAAAAjExAQAAAAEwAgAAAAoxMDAzMjgzMzkyAwAAAAYxMDAxODcEAAAAATIGAAAAATAHAAAAAzE2MAgAAAABMAkAAAABMQoAAAABMAsAAAALMTI4OTk2OTcyNTkMAAAAAjEyDQAAAAk3LzE0LzIwMjIQAAAACTcvMTMvMjAyMiySmv0KZdoISqkB6Cll2gggQ0lRLk5ZU0U6R1ZBLklRX0VCSVRfRVNULklRX05UTS4BAAAAujUEAAIAAAAIMTA4LjIyNjgBDgAAAAUAAAACMTEBAAAAATACAAAACTcwMTM2MDM2MwMAAAAGMTAwMjE1BAAAAAEyBgAAAAEwBwAAAAMxNjAIAAAAATAJAAAAATEKAAAAATALAAAACzEyODgyNjE5NjUzDAAAAAIxMg0AAAAJNy8xNC8y | BC1: MDIyEAAAAAk3LzEzLzIwMjIskpr9CmXaCNVKAOgpZdoIIkNJUS5LTFNFOkxLTC5JUV9FQklUREFfRVNULklRX05UTS4BAAAAXFkCEwMAAAAAACySmv0KZdoILR4C6Cll2ggoQ0lRLk5BU0RBUUdTOkFNU0MuSVFfRUJJVERBX0VTVC5JUV9GWSsxLgEAAAB1iAAAAgAAAAktMTkuODMzMzMBDgAAAAUAAAABMwEAAAABMAIAAAAKMTAwMzI4MzM5MgMAAAAGMTAwMTg3BAAAAAEyBgAAAAEwBwAAAAMxNjAIAAAAATAJAAAAATEKAAAAATALAAAACzEyODk5Njk3MjU5DAAAAAExDQAAAAk3LzE0LzIwMjIQAAAACTcvMTMvMjAyMiySmv0KZdoISqkB6Cll2gghQ0lRLk5ZU0U6R1ZBLklRX0VCSVRfRVNULklRX0ZZKzEuAQAAALo1BAACAAAABzEwOS41NzQBDgAAAAUAAAABMwEAAAABMAIAAAAKMTAwMjYxMjU2NgMAAAAGMTAwMjE1BAAAAAEyBgAAAAEwBwAAAAMxNjAIAAAAATAJAAAAATEKAAAAATALAAAACzEyODgyNjE4ODkzDAAAAAExDQAAAAk3LzE0LzIwMjIQAAAACTcvMTMvMjAyMiySmv0KZdoI1UoA6Cll2ggjQ0lRLk5ZU0U6RkxSLklRX1JFVkVOVUVfRVNULklRX05UTS4BAAAAKwEKAAIAAAAKMTQxNjYuNjYwNgEOAAAABQAAAAIxMQEAAAABMAIAAAAHMzk3MzQ4MwMAAAAGMTAwMTgwBAAAAAEyBgAAAAEwBwAAAAMxNjAIAAAAATAJAAAAATEKAAAAATALAAAACzEyODg5NzQxODkzDAAAAAIxMg0AAAAJNy8xNC8y | BD1: MDIyEAAAAAk3LzEzLzIwMjIskpr9CmXaCHy/AOgpZdoIJENJUS5OWVNFOkdWQS5JUV9SRVZFTlVFX0VTVC5JUV9GWSsxLgEAAAC6NQQAAgAAAAkzMDU2LjM5MzUBDgAAAAUAAAABMwEAAAABMAIAAAAKMTAwMjYxMjU2NgMAAAAGMTAwMTgwBAAAAAEyBgAAAAEwBwAAAAMxNjAIAAAAATAJAAAAATEKAAAAATALAAAACzEyOTIxOTUxMzk4DAAAAAExDQAAAAk3LzE0LzIwMjIQAAAACTcvMTMvMjAyMiySmv0KZdoIRoj/5yll2ggiQ0lRLlRTRTo3ODEzLklRX0NBUEVYX0VTVC5JUV9GWSsxLgEAAAAU/x0DAwAAAAAALJKa/Qpl2ggHbALoKWXaCCBDSVEuVFNFOjc4MTcuSVFfRUJJVF9FU1QuSVFfTlRNLgEAAACdcw0AAgAAAAUxMjkwMAEOAAAABQAAAAIxMQEAAAABMAIAAAAKMTAwNDExMTE4MgMAAAAGMTAwMjE1BAAAAAI1NgYAAAABMAcAAAACNzkIAAAAATAJAAAAATEKAAAAATALAAAACzEyODc0ODA4NTMzDAAAAAIxMg0AAAAJNy8xNC8yMDIyEAAAAAk3LzEzLzIwMjIskpr9CmXaCOe5AugpZdoIJENJUS5PTTpBUkpPIEIuSVFfUkVWRU5VRV9FU1QuSVFfTlRNLgEAAABTlvEOAgAAAAoxMDE4OC42OTg0AQ4AAAAFAAAAAjExAQAAAAEwAgAAAAc0MjU2MzA0AwAAAAYxMDAxODAEAAAAATMGAAAAATAHAAAAAzEzNwgAAAABMAkAAAABMQoAAAABMAsAAAALMTI5MzEzMjcwMzMMAAAAAjEyDQAAAAk3LzE0LzIwMjIQ | BE1: AAAACTcvMTMvMjAyMiySmv0KZdoI2+AC6Cll2ggjQ0lRLktMU0U6TEtMLklRX0VCSVREQV9FU1QuSVFfRlkrMS4BAAAAXFkCEwMAAAAAACySmv0KZdoITUYC6Cll2ggkQ0lRLk5ZU0U6RkxSLklRX1JFVkVOVUVfRVNULklRX0ZZKzEuAQAAACsBCgACAAAACzE0MDE0LjAxMDkyAQ4AAAAFAAAAATMBAAAAATACAAAACjEwMDM3MDg3OTUDAAAABjEwMDE4MAQAAAABMgYAAAABMAcAAAADMTYwCAAAAAEwCQAAAAExCgAAAAEwCwAAAAsxMjg4OTc0MDg3NwwAAAABMQ0AAAAJNy8xNC8yMDIyEAAAAAk3LzEzLzIwMjIskpr9CmXaCHy/AOgpZdoIIUNJUS5UU0U6NzgxNy5JUV9FQklUX0VTVC5JUV9GWSsxLgEAAACdcw0AAgAAAAUxMjkwMAEOAAAABQAAAAEzAQAAAAEwAgAAAAoxMDA0MTExMTgyAwAAAAYxMDAyMTUEAAAAAjU2BgAAAAEwBwAAAAI3OQgAAAABMAkAAAABMQoAAAABMAsAAAALMTI4NzQ4MDg1MzMMAAAAATENAAAACTcvMTQvMjAyMhAAAAAJNy8xMy8yMDIyLJKa/Qpl2gjnuQLoKWXaCChDSVEuTkFTREFRR1M6QU1TQy5JUV9SRVZFTlVFX0VTVC5JUV9OVE0uAQAAAHWIAAACAAAACDExNC40MzI1AQ4AAAAFAAAAAjExAQAAAAEwAgAAAAoxMDAzMjgzMzkyAwAAAAYxMDAxODAEAAAAATIGAAAAATAHAAAAAzE2MAgAAAABMAkAAAABMQoAAAABMAsAAAALMTI4OTk2OTczNDkMAAAAAjEyDQAAAAk3LzE0LzIw | BF1: MjIQAAAACTcvMTMvMjAyMiySmv0KZdoIr1sB6Cll2ggiQ0lRLk5ZU0U6R1ZBLklRX0VCSVREQV9FU1QuSVFfTlRNLgEAAAC6NQQAAgAAAAYyMjcuNzIBDgAAAAUAAAACMTEBAAAAATACAAAACTcwMTM2MDM2MwMAAAAGMTAwMTg3BAAAAAEyBgAAAAEwBwAAAAMxNjAIAAAAATAJAAAAATEKAAAAATALAAAACzEyODgwMDI4ODk0DAAAAAIxMg0AAAAJNy8xNC8yMDIyEAAAAAk3LzEzLzIwMjIskpr9CmXaCDvW/+cpZdoII0NJUS5LTFNFOkxLTC5JUV9SRVZFTlVFX0VTVC5JUV9OVE0uAQAAAFxZAhMDAAAAAAAskpr9CmXaCE1GAugpZdoIKUNJUS5OQVNEQVFHUzpBTVNDLklRX1JFVkVOVUVfRVNULklRX0ZZKzEuAQAAAHWIAAACAAAACDExNC40MzI1AQ4AAAAFAAAAATMBAAAAATACAAAACjEwMDMyODMzOTIDAAAABjEwMDE4MAQAAAABMgYAAAABMAcAAAADMTYwCAAAAAEwCQAAAAExCgAAAAEwCwAAAAsxMjg5OTY5NzM0OQwAAAABMQ0AAAAJNy8xNC8yMDIyEAAAAAk3LzEzLzIwMjIskpr9CmXaCM6DAegpZdoIIUNJUS5UV1NFOjQxMDYuSVFfRUJJVF9FU1QuSVFfTlRNLgEAAAAqQjYBAwAAAAAALJKa/Qpl2ggtHgLoKWXaCCNDSVEuTllTRTpHVkEuSVFfRUJJVERBX0VTVC5JUV9GWSsxLgEAAAC6NQQAAgAAAAkyMTUuMDQwNzUBDgAAAAUAAAABMwEAAAABMAIAAAAKMTAwMjYxMjU2NgMAAAAGMTAwMTg3BAAAAAEy | BG1: BgAAAAEwBwAAAAMxNjAIAAAAATAJAAAAATEKAAAAATALAAAACzEyOTIxOTUxNDEwDAAAAAExDQAAAAk3LzE0LzIwMjIQAAAACTcvMTMvMjAyMiySmv0KZdoIO9b/5yll2gghQ0lRLk5ZU0U6RkxSLklRX0NBUEVYX0VTVC5JUV9OVE0uAQAAACsBCgACAAAACC03Ny41NDIzAQ4AAAAFAAAAAjExAQAAAAEwAgAAAAczOTczNDgzAwAAAAYxMDQwOTAEAAAAATIGAAAAATAHAAAAAzE2MAgAAAABMAkAAAABMQoAAAABMAsAAAALMTI4NjYyMDI5NzYMAAAAAjEyDQAAAAk3LzE0LzIwMjIQAAAACTcvMTMvMjAyMiySmv0KZdoIuZgA6Cll2gghQ0lRLlRTRTo3ODEzLklRX0NBUEVYX0VTVC5JUV9OVE0uAQAAABT/HQMDAAAAAAAskpr9CmXaCAdsAugpZdoIJ0NJUS5OQVNEQVFHUzpBTVNDLklRX0NBUEVYX0VTVC5JUV9GWSsxLgEAAAB1iAAAAgAAAAgtMS41MzMzMwEOAAAABQAAAAEzAQAAAAEwAgAAAAoxMDAzMjgzMzkyAwAAAAYxMDQwOTAEAAAAATIGAAAAATAHAAAAAzE2MAgAAAABMAkAAAABMQoAAAABMAsAAAALMTI4OTk3MjMxNjMMAAAAATENAAAACTcvMTQvMjAyMhAAAAAJNy8xMy8yMDIyLJKa/Qpl2gh/NAHoKWXaCCJDSVEuVFNFOjc4MTcuSVFfRUJJVERBX0VTVC5JUV9OVE0uAQAAAJ1zDQACAAAABTIxMTI2AQ4AAAAFAAAAAjExAQAAAAEwAgAAAAoxMDA0MTExMTgyAwAAAAYxMDAxODcEAAAAAjU2BgAAAAEw | BH1: BwAAAAI3OQgAAAABMAkAAAABMQoAAAABMAsAAAALMTI3ODUzMjU5NzMMAAAAAjEyDQAAAAk3LzE0LzIwMjIQAAAACTcvMTMvMjAyMiySmv0KZdoI57kC6Cll2ggiQ0lRLk9NOkFSSk8gQi5JUV9DQVBFWF9FU1QuSVFfTlRNLgEAAABTlvEOAgAAAAktNzQ0LjEwOTkBDgAAAAUAAAACMTEBAAAAATACAAAABzQyNTYzMDQDAAAABjEwNDA5MAQAAAABMwYAAAABMAcAAAADMTM3CAAAAAEwCQAAAAExCgAAAAEwCwAAAAsxMjkyNDUwNTcxNgwAAAACMTINAAAACTcvMTQvMjAyMhAAAAAJNy8xMy8yMDIyLJKa/Qpl2gjb4ALoKWXaCCRDSVEuS0xTRTpMS0wuSVFfUkVWRU5VRV9FU1QuSVFfRlkrMS4BAAAAXFkCEwMAAAAAACySmv0KZdoILR4C6Cll2ggfQ0lRLlRTWDpTSVMuSVFfRUJJVF9FU1QuSVFfTlRNLgEAAABIgDAAAgAAAAY3NS44MjUBDgAAAAUAAAACMTEBAAAAATACAAAABzM2NTkzOTgDAAAABjEwMDIxNQQAAAABMwYAAAABMAcAAAACMjcIAAAAATAJAAAAATEKAAAAATALAAAACzEyODczMTU5ODUyDAAAAAIxMg0AAAAJNy8xNC8yMDIyEAAAAAk3LzEzLzIwMjIskpr9CmXaCIANAegpZdoIIkNJUS5UV1NFOjQxMDYuSVFfRUJJVF9FU1QuSVFfRlkrMS4BAAAAKkI2AQMAAAAAACySmv0KZdoIzvgB6Cll2ggiQ0lRLk5ZU0U6RkxSLklRX0NBUEVYX0VTVC5JUV9GWSsxLgEAAAArAQoAAgAAAAYtNzYuMjUBDgAA | BI1: AAUAAAABMwEAAAABMAIAAAAKMTAwMzcwODc5NQMAAAAGMTA0MDkwBAAAAAEyBgAAAAEwBwAAAAMxNjAIAAAAATAJAAAAATEKAAAAATALAAAACzEyODg2MTQ4NDY5DAAAAAExDQAAAAk3LzE0LzIwMjIQAAAACTcvMTMvMjAyMiySmv0KZdoIuZgA6Cll2ggjQ0lRLlRTRTo3ODE3LklRX0VCSVREQV9FU1QuSVFfRlkrMS4BAAAAnXMNAAIAAAAFMjExMjYBDgAAAAUAAAABMwEAAAABMAIAAAAKMTAwNDExMTE4MgMAAAAGMTAwMTg3BAAAAAI1NgYAAAABMAcAAAACNzkIAAAAATAJAAAAATEKAAAAATALAAAACzEyNzg1MzI1OTczDAAAAAExDQAAAAk3LzE0LzIwMjIQAAAACTcvMTMvMjAyMiySmv0KZdoI+ZIC6Cll2ggjQ0lRLk9NOkFSSk8gQi5JUV9DQVBFWF9FU1QuSVFfRlkrMS4BAAAAU5bxDgIAAAAJLTc0MS40Mzc1AQ4AAAAFAAAAATMBAAAAATACAAAACjEwMDQwNjY5NTQDAAAABjEwNDA5MAQAAAABMwYAAAABMAcAAAADMTM3CAAAAAEwCQAAAAExCgAAAAEwCwAAAAsxMjkyNDQ5NjM0MgwAAAABMQ0AAAAJNy8xNC8yMDIyEAAAAAk3LzEzLzIwMjIskpr9CmXaCNvgAugpZdoIJUNJUS5PTTpBUkpPIEIuSVFfUkVWRU5VRV9FU1QuSVFfRlkrMS4BAAAAU5bxDgIAAAALMTAwMjguNjA0NDIBDgAAAAUAAAABMwEAAAABMAIAAAAKMTAwNDA2Njk1NAMAAAAGMTAwMTgwBAAAAAEzBgAAAAEwBwAAAAMxMzcIAAAAATAJ | BJ1: AAAAATEKAAAAATALAAAACzEyOTMxMzE0ODY4DAAAAAExDQAAAAk3LzE0LzIwMjIQAAAACTcvMTMvMjAyMiySmv0KZdoI2+AC6Cll2gggQ0lRLlRTWDpTSVMuSVFfRUJJVF9FU1QuSVFfRlkrMS4BAAAASIAwAAIAAAAENzEuNwEOAAAABQAAAAEzAQAAAAEwAgAAAAoxMDAzNTYzODk3AwAAAAYxMDAyMTUEAAAAATMGAAAAATAHAAAAAjI3CAAAAAEwCQAAAAExCgAAAAEwCwAAAAsxMjg3MzE1Njk1OAwAAAABMQ0AAAAJNy8xNC8yMDIyEAAAAAk3LzEzLzIwMjIskpr9CmXaCH80AegpZdoIJkNJUS5OQVNEQVFHUzpBTVNDLklRX0NBUEVYX0VTVC5JUV9OVE0uAQAAAHWIAAACAAAACC0xLjUzMzMzAQ4AAAAFAAAAAjExAQAAAAEwAgAAAAoxMDAzMjgzMzkyAwAAAAYxMDQwOTAEAAAAATIGAAAAATAHAAAAAzE2MAgAAAABMAkAAAABMQoAAAABMAsAAAALMTI4OTk3MjMxNjMMAAAAAjEyDQAAAAk3LzE0LzIwMjIQAAAACTcvMTMvMjAyMiySmv0KZdoIzoMB6Cll2ggjQ0lRLk5ZU0U6R1ZBLklRX1JFVkVOVUVfRVNULklRX05UTS4BAAAAujUEAAIAAAAJMzA2NC45Nzc1AQ4AAAAFAAAAAjExAQAAAAEwAgAAAAk3MDEzNjAzNjMDAAAABjEwMDE4MAQAAAABMgYAAAABMAcAAAADMTYwCAAAAAEwCQAAAAExCgAAAAEwCwAAAAsxMjkyMTk1Mjg2MwwAAAACMTINAAAACTcvMTQvMjAyMhAAAAAJNy8xMy8yMDIyLJKa/Qpl2ggw | BK1: /f/nKWXaCC1DSVEuTllTRTpHVkEuSVFfUkVWRU5VRV9FU1QuSVFfTlRNLjIwMjItMDctMTMBAAAAujUEAAIAAAAJMzA2NC45Nzc1AQ4AAAAFAAAAAjExAQAAAAEwAgAAAAk3MDEzNjAzNjMDAAAABjEwMDE4MAQAAAABMgYAAAABMAcAAAADMTYwCAAAAAEwCQAAAAExCgAAAAEwCwAAAAsxMjkyMTk1Mjg2MwwAAAACMTINAAAACTcvMTQvMjAyMhAAAAAJNy8xMy8yMDIypt+Z5yll2ggxu+r3KWXaCDBDSVEuTkFTREFRR1M6QU1TQy5JUV9DQVBFWF9FU1QuSVFfTlRNLjIwMjItMDctMTMBAAAAdYgAAAIAAAAILTEuNTMzMzMBDgAAAAUAAAACMTEBAAAAATACAAAACjEwMDMyODMzOTIDAAAABjEwNDA5MAQAAAABMgYAAAABMAcAAAADMTYwCAAAAAEwCQAAAAExCgAAAAEwCwAAAAsxMjg5OTcyMzE2MwwAAAACMTINAAAACTcvMTQvMjAyMhAAAAAJNy8xMy8yMDIypt+Z5yll2ghWRer3KWXaCCpDSVEuVFNYOlNJUy5JUV9FQklUX0VTVC5JUV9GWSsxLjIwMjItMDctMTMBAAAASIAwAAIAAAAENzEuNwEOAAAABQAAAAEzAQAAAAEwAgAAAAoxMDAzNTYzODk3AwAAAAYxMDAyMTUEAAAAATMGAAAAATAHAAAAAjI3CAAAAAEwCQAAAAExCgAAAAEwCwAAAAsxMjg3MzE1Njk1OAwAAAABMQ0AAAAJNy8xNC8yMDIyEAAAAAk3LzEzLzIwMjKm35nnKWXaCAZs6vcpZdoIL0NJUS5PTTpBUkpPIEIuSVFfUkVWRU5VRV9FU1QuSVFf | BL1: RlkrMS4yMDIyLTA3LTEzAQAAAFOW8Q4CAAAACzEwMDI4LjYwNDQyAQ4AAAAFAAAAATMBAAAAATACAAAACjEwMDQwNjY5NTQDAAAABjEwMDE4MAQAAAABMwYAAAABMAcAAAADMTM3CAAAAAEwCQAAAAExCgAAAAEwCwAAAAsxMjkzMTMxNDg2OAwAAAABMQ0AAAAJNy8xNC8yMDIyEAAAAAk3LzEzLzIwMjKm35nnKWXaCISD6fcpZdoILUNJUS5PTTpBUkpPIEIuSVFfQ0FQRVhfRVNULklRX0ZZKzEuMjAyMi0wNy0xMwEAAABTlvEOAgAAAAktNzQxLjQzNzUBDgAAAAUAAAABMwEAAAABMAIAAAAKMTAwNDA2Njk1NAMAAAAGMTA0MDkwBAAAAAEzBgAAAAEwBwAAAAMxMzcIAAAAATAJAAAAATEKAAAAATALAAAACzEyOTI0NDk2MzQyDAAAAAExDQAAAAk3LzE0LzIwMjIQAAAACTcvMTMvMjAyMqbfmecpZdoIhIPp9yll2ggtQ0lRLlRTRTo3ODE3LklRX0VCSVREQV9FU1QuSVFfRlkrMS4yMDIyLTA3LTEzAQAAAJ1zDQACAAAABTIxMTI2AQ4AAAAFAAAAATMBAAAAATACAAAACjEwMDQxMTExODIDAAAABjEwMDE4NwQAAAACNTYGAAAAATAHAAAAAjc5CAAAAAEwCQAAAAExCgAAAAEwCwAAAAsxMjc4NTMyNTk3MwwAAAABMQ0AAAAJNy8xNC8yMDIyEAAAAAk3LzEzLzIwMjKm35nnKWXaCDap6fcpZdoILENJUS5OWVNFOkZMUi5JUV9DQVBFWF9FU1QuSVFfRlkrMS4yMDIyLTA3LTEzAQAAACsBCgACAAAABi03Ni4yNQEOAAAA | BM1: BQAAAAEzAQAAAAEwAgAAAAoxMDAzNzA4Nzk1AwAAAAYxMDQwOTAEAAAAATIGAAAAATAHAAAAAzE2MAgAAAABMAkAAAABMQoAAAABMAsAAAALMTI4ODYxNDg0NjkMAAAAATENAAAACTcvMTQvMjAyMhAAAAAJNy8xMy8yMDIypt+Z5yll2gg7lOr3KWXaCCxDSVEuVFdTRTo0MTA2LklRX0VCSVRfRVNULklRX0ZZKzEuMjAyMi0wNy0xMwEAAAAqQjYBAwAAAAAApt+Z5yll2ggpH+r3KWXaCClDSVEuVFNYOlNJUy5JUV9FQklUX0VTVC5JUV9OVE0uMjAyMi0wNy0xMwEAAABIgDAAAgAAAAY3NS44MjUBDgAAAAUAAAACMTEBAAAAATACAAAABzM2NTkzOTgDAAAABjEwMDIxNQQAAAABMwYAAAABMAcAAAACMjcIAAAAATAJAAAAATEKAAAAATALAAAACzEyODczMTU5ODUyDAAAAAIxMg0AAAAJNy8xNC8yMDIyEAAAAAk3LzEzLzIwMjKm35nnKWXaCAZs6vcpZdoILkNJUS5LTFNFOkxLTC5JUV9SRVZFTlVFX0VTVC5JUV9GWSsxLjIwMjItMDctMTMBAAAAXFkCEwMAAAAAAKbfmecpZdoIIffp9yll2ggsQ0lRLk9NOkFSSk8gQi5JUV9DQVBFWF9FU1QuSVFfTlRNLjIwMjItMDctMTMBAAAAU5bxDgIAAAAJLTc0NC4xMDk5AQ4AAAAFAAAAAjExAQAAAAEwAgAAAAc0MjU2MzA0AwAAAAYxMDQwOTAEAAAAATMGAAAAATAHAAAAAzEzNwgAAAABMAkAAAABMQoAAAABMAsAAAALMTI5MjQ1MDU3MTYMAAAAAjEyDQAAAAk3LzE0LzIw | BN1: MjIQAAAACTcvMTMvMjAyMqbfmecpZdoIRVvp9yll2ggsQ0lRLlRTRTo3ODE3LklRX0VCSVREQV9FU1QuSVFfTlRNLjIwMjItMDctMTMBAAAAnXMNAAIAAAAFMjExMjYBDgAAAAUAAAACMTEBAAAAATACAAAACjEwMDQxMTExODIDAAAABjEwMDE4NwQAAAACNTYGAAAAATAHAAAAAjc5CAAAAAEwCQAAAAExCgAAAAEwCwAAAAsxMjc4NTMyNTk3MwwAAAACMTINAAAACTcvMTQvMjAyMhAAAAAJNy8xMy8yMDIypt+Z5yll2giEg+n3KWXaCDFDSVEuTkFTREFRR1M6QU1TQy5JUV9DQVBFWF9FU1QuSVFfRlkrMS4yMDIyLTA3LTEzAQAAAHWIAAACAAAACC0xLjUzMzMzAQ4AAAAFAAAAATMBAAAAATACAAAACjEwMDMyODMzOTIDAAAABjEwNDA5MAQAAAABMgYAAAABMAcAAAADMTYwCAAAAAEwCQAAAAExCgAAAAEwCwAAAAsxMjg5OTcyMzE2MwwAAAABMQ0AAAAJNy8xNC8yMDIyEAAAAAk3LzEzLzIwMjKm35nnKWXaCAZs6vcpZdoIK0NJUS5UU0U6NzgxMy5JUV9DQVBFWF9FU1QuSVFfTlRNLjIwMjItMDctMTMBAAAAFP8dAwMAAAAAAKbfmecpZdoI59Hp9yll2ggrQ0lRLk5ZU0U6RkxSLklRX0NBUEVYX0VTVC5JUV9OVE0uMjAyMi0wNy0xMwEAAAArAQoAAgAAAAgtNzcuNTQyMwEOAAAABQAAAAIxMQEAAAABMAIAAAAHMzk3MzQ4MwMAAAAGMTA0MDkwBAAAAAEyBgAAAAEwBwAAAAMxNjAIAAAAATAJAAAAATEKAAAAATAL | BO1: AAAACzEyODY2MjAyOTc2DAAAAAIxMg0AAAAJNy8xNC8yMDIyEAAAAAk3LzEzLzIwMjKm35nnKWXaCDuU6vcpZdoILUNJUS5OWVNFOkdWQS5JUV9FQklUREFfRVNULklRX0ZZKzEuMjAyMi0wNy0xMwEAAAC6NQQAAgAAAAkyMTUuMDQwNzUBDgAAAAUAAAABMwEAAAABMAIAAAAKMTAwMjYxMjU2NgMAAAAGMTAwMTg3BAAAAAEyBgAAAAEwBwAAAAMxNjAIAAAAATAJAAAAATEKAAAAATALAAAACzEyOTIxOTUxNDEwDAAAAAExDQAAAAk3LzE0LzIwMjIQAAAACTcvMTMvMjAyMqbfmecpZdoIMbvq9yll2ggrQ0lRLlRXU0U6NDEwNi5JUV9FQklUX0VTVC5JUV9OVE0uMjAyMi0wNy0xMwEAAAAqQjYBAwAAAAAApt+Z5yll2ggh9+n3KWXaCDNDSVEuTkFTREFRR1M6QU1TQy5JUV9SRVZFTlVFX0VTVC5JUV9GWSsxLjIwMjItMDctMTMBAAAAdYgAAAIAAAAIMTE0LjQzMjUBDgAAAAUAAAABMwEAAAABMAIAAAAKMTAwMzI4MzM5MgMAAAAGMTAwMTgwBAAAAAEyBgAAAAEwBwAAAAMxNjAIAAAAATAJAAAAATEKAAAAATALAAAACzEyODk5Njk3MzQ5DAAAAAExDQAAAAk3LzE0LzIwMjIQAAAACTcvMTMvMjAyMqbfmecpZdoIVkXq9yll2ggtQ0lRLktMU0U6TEtMLklRX1JFVkVOVUVfRVNULklRX05UTS4yMDIyLTA3LTEzAQAAAFxZAhMDAAAAAACm35nnKWXaCCH36fcpZdoILENJUS5OWVNFOkdWQS5JUV9FQklUREFfRVNULklR | BP1: X05UTS4yMDIyLTA3LTEzAQAAALo1BAACAAAABjIyNy43MgEOAAAABQAAAAIxMQEAAAABMAIAAAAJNzAxMzYwMzYzAwAAAAYxMDAxODcEAAAAATIGAAAAATAHAAAAAzE2MAgAAAABMAkAAAABMQoAAAABMAsAAAALMTI4ODAwMjg4OTQMAAAAAjEyDQAAAAk3LzE0LzIwMjIQAAAACTcvMTMvMjAyMqbfmecpZdoIMbvq9yll2ggyQ0lRLk5BU0RBUUdTOkFNU0MuSVFfUkVWRU5VRV9FU1QuSVFfTlRNLjIwMjItMDctMTMBAAAAdYgAAAIAAAAIMTE0LjQzMjUBDgAAAAUAAAACMTEBAAAAATACAAAACjEwMDMyODMzOTIDAAAABjEwMDE4MAQAAAABMgYAAAABMAcAAAADMTYwCAAAAAEwCQAAAAExCgAAAAEwCwAAAAsxMjg5OTY5NzM0OQwAAAACMTINAAAACTcvMTQvMjAyMhAAAAAJNy8xMy8yMDIypt+Z5yll2ghWRer3KWXaCCtDSVEuVFNFOjc4MTcuSVFfRUJJVF9FU1QuSVFfRlkrMS4yMDIyLTA3LTEzAQAAAJ1zDQACAAAABTEyOTAwAQ4AAAAFAAAAATMBAAAAATACAAAACjEwMDQxMTExODIDAAAABjEwMDIxNQQAAAACNTYGAAAAATAHAAAAAjc5CAAAAAEwCQAAAAExCgAAAAEwCwAAAAsxMjg3NDgwODUzMwwAAAABMQ0AAAAJNy8xNC8yMDIyEAAAAAk3LzEzLzIwMjKm35nnKWXaCISD6fcpZdoILkNJUS5OWVNFOkZMUi5JUV9SRVZFTlVFX0VTVC5JUV9GWSsxLjIwMjItMDctMTMBAAAAKwEKAAIAAAALMTQwMTQuMDEw | BQ1: OTIBDgAAAAUAAAABMwEAAAABMAIAAAAKMTAwMzcwODc5NQMAAAAGMTAwMTgwBAAAAAEyBgAAAAEwBwAAAAMxNjAIAAAAATAJAAAAATEKAAAAATALAAAACzEyODg5NzQwODc3DAAAAAExDQAAAAk3LzE0LzIwMjIQAAAACTcvMTMvMjAyMqbfmecpZdoIO5Tq9yll2ggtQ0lRLktMU0U6TEtMLklRX0VCSVREQV9FU1QuSVFfRlkrMS4yMDIyLTA3LTEzAQAAAFxZAhMDAAAAAACm35nnKWXaCCH36fcpZdoILkNJUS5PTTpBUkpPIEIuSVFfUkVWRU5VRV9FU1QuSVFfTlRNLjIwMjItMDctMTMBAAAAU5bxDgIAAAAKMTAxODguNjk4NAEOAAAABQAAAAIxMQEAAAABMAIAAAAHNDI1NjMwNAMAAAAGMTAwMTgwBAAAAAEzBgAAAAEwBwAAAAMxMzcIAAAAATAJAAAAATEKAAAAATALAAAACzEyOTMxMzI3MDMzDAAAAAIxMg0AAAAJNy8xNC8yMDIyEAAAAAk3LzEzLzIwMjKm35nnKWXaCISD6fcpZdoIKkNJUS5UU0U6NzgxNy5JUV9FQklUX0VTVC5JUV9OVE0uMjAyMi0wNy0xMwEAAACdcw0AAgAAAAUxMjkwMAEOAAAABQAAAAIxMQEAAAABMAIAAAAKMTAwNDExMTE4MgMAAAAGMTAwMjE1BAAAAAI1NgYAAAABMAcAAAACNzkIAAAAATAJAAAAATEKAAAAATALAAAACzEyODc0ODA4NTMzDAAAAAIxMg0AAAAJNy8xNC8yMDIyEAAAAAk3LzEzLzIwMjKm35nnKWXaCISD6fcpZdoILENJUS5UU0U6NzgxMy5JUV9DQVBFWF9FU1QuSVFf | BR1: RlkrMS4yMDIyLTA3LTEzAQAAABT/HQMDAAAAAACm35nnKWXaCOfR6fcpZdoILkNJUS5OWVNFOkdWQS5JUV9SRVZFTlVFX0VTVC5JUV9GWSsxLjIwMjItMDctMTMBAAAAujUEAAIAAAAJMzA1Ni4zOTM1AQ4AAAAFAAAAATMBAAAAATACAAAACjEwMDI2MTI1NjYDAAAABjEwMDE4MAQAAAABMgYAAAABMAcAAAADMTYwCAAAAAEwCQAAAAExCgAAAAEwCwAAAAsxMjkyMTk1MTM5OAwAAAABMQ0AAAAJNy8xNC8yMDIyEAAAAAk3LzEzLzIwMjKm35nnKWXaCDG76vcpZdoILUNJUS5OWVNFOkZMUi5JUV9SRVZFTlVFX0VTVC5JUV9OVE0uMjAyMi0wNy0xMwEAAAArAQoAAgAAAAoxNDE2Ni42NjA2AQ4AAAAFAAAAAjExAQAAAAEwAgAAAAczOTczNDgzAwAAAAYxMDAxODAEAAAAATIGAAAAATAHAAAAAzE2MAgAAAABMAkAAAABMQoAAAABMAsAAAALMTI4ODk3NDE4OTMMAAAAAjEyDQAAAAk3LzE0LzIwMjIQAAAACTcvMTMvMjAyMqbfmecpZdoIO5Tq9yll2ggrQ0lRLk5ZU0U6R1ZBLklRX0VCSVRfRVNULklRX0ZZKzEuMjAyMi0wNy0xMwEAAAC6NQQAAgAAAAcxMDkuNTc0AQ4AAAAFAAAAATMBAAAAATACAAAACjEwMDI2MTI1NjYDAAAABjEwMDIxNQQAAAABMgYAAAABMAcAAAADMTYwCAAAAAEwCQAAAAExCgAAAAEwCwAAAAsxMjg4MjYxODg5MwwAAAABMQ0AAAAJNy8xNC8yMDIyEAAAAAk3LzEzLzIwMjKm35nnKWXaCDG7 | BS1: 6vcpZdoIMkNJUS5OQVNEQVFHUzpBTVNDLklRX0VCSVREQV9FU1QuSVFfRlkrMS4yMDIyLTA3LTEzAQAAAHWIAAACAAAACS0xOS44MzMzMwEOAAAABQAAAAEzAQAAAAEwAgAAAAoxMDAzMjgzMzkyAwAAAAYxMDAxODcEAAAAATIGAAAAATAHAAAAAzE2MAgAAAABMAkAAAABMQoAAAABMAsAAAALMTI4OTk2OTcyNTkMAAAAATENAAAACTcvMTQvMjAyMhAAAAAJNy8xMy8yMDIypt+Z5yll2ghWRer3KWXaCCxDSVEuS0xTRTpMS0wuSVFfRUJJVERBX0VTVC5JUV9OVE0uMjAyMi0wNy0xMwEAAABcWQITAwAAAAAApt+Z5yll2ggh9+n3KWXaCCpDSVEuTllTRTpHVkEuSVFfRUJJVF9FU1QuSVFfTlRNLjIwMjItMDctMTMBAAAAujUEAAIAAAAIMTA4LjIyNjgBDgAAAAUAAAACMTEBAAAAATACAAAACTcwMTM2MDM2MwMAAAAGMTAwMjE1BAAAAAEyBgAAAAEwBwAAAAMxNjAIAAAAATAJAAAAATEKAAAAATALAAAACzEyODgyNjE5NjUzDAAAAAIxMg0AAAAJNy8xNC8yMDIyEAAAAAk3LzEzLzIwMjKm35nnKWXaCDG76vcpZdoIMUNJUS5OQVNEQVFHUzpBTVNDLklRX0VCSVREQV9FU1QuSVFfTlRNLjIwMjItMDctMTMBAAAAdYgAAAIAAAAJLTE5LjgzMzMzAQ4AAAAFAAAAAjExAQAAAAEwAgAAAAoxMDAzMjgzMzkyAwAAAAYxMDAxODcEAAAAATIGAAAAATAHAAAAAzE2MAgAAAABMAkAAAABMQoAAAABMAsAAAALMTI4OTk2OTcy | BT1: NTkMAAAAAjEyDQAAAAk3LzE0LzIwMjIQAAAACTcvMTMvMjAyMqbfmecpZdoIVkXq9yll2gguQ0lRLlRTRTo3ODEzLklRX1JFVkVOVUVfRVNULklRX0ZZKzEuMjAyMi0wNy0xMwEAAAAU/x0DAwAAAAAApt+Z5yll2gg2qen3KWXaCC5DSVEuT006QVJKTyBCLklRX0VCSVREQV9FU1QuSVFfRlkrMS4yMDIyLTA3LTEzAQAAAFOW8Q4CAAAACjIxODUuNzU2NzQBDgAAAAUAAAABMwEAAAABMAIAAAAKMTAwNDA2Njk1NAMAAAAGMTAwMTg3BAAAAAEzBgAAAAEwBwAAAAMxMzcIAAAAATAJAAAAATEKAAAAATALAAAACzEyOTMxMzE0MTg5DAAAAAExDQAAAAk3LzE0LzIwMjIQAAAACTcvMTMvMjAyMqbfmecpZdoIRVvp9yll2ggtQ0lRLk9NOkFSSk8gQi5JUV9FQklUREFfRVNULklRX05UTS4yMDIyLTA3LTEzAQAAAFOW8Q4CAAAACTIyNjYuMDkwMQEOAAAABQAAAAIxMQEAAAABMAIAAAAHNDI1NjMwNAMAAAAGMTAwMTg3BAAAAAEzBgAAAAEwBwAAAAMxMzcIAAAAATAJAAAAATEKAAAAATALAAAACzEyOTMxMzM1MDExDAAAAAIxMg0AAAAJNy8xNC8yMDIyEAAAAAk3LzEzLzIwMjKm35nnKWXaCEVb6fcpZdoIK0NJUS5UU1g6U0lTLklRX0NBUEVYX0VTVC5JUV9GWSsxLjIwMjItMDctMTMBAAAASIAwAAIAAAADLTE4AQ4AAAAFAAAAATMBAAAAATACAAAACjEwMDM1NjM4OTcDAAAABjEwNDA5MAQAAAABMwYAAAABMAcAAAAC | BU1: MjcIAAAAATAJAAAAATEKAAAAATALAAAACzEyODc0MDk0MzI5DAAAAAExDQAAAAk3LzE0LzIwMjIQAAAACTcvMTMvMjAyMqbfmecpZdoIBmzq9yll2ggtQ0lRLk5ZU0U6RkxSLklRX0VCSVREQV9FU1QuSVFfRlkrMS4yMDIyLTA3LTEzAQAAACsBCgACAAAACTQxOS43MzY2MgEOAAAABQAAAAEzAQAAAAEwAgAAAAoxMDAzNzA4Nzk1AwAAAAYxMDAxODcEAAAAATIGAAAAATAHAAAAAzE2MAgAAAABMAkAAAABMQoAAAABMAsAAAALMTI4ODk3MzQ3OTcMAAAAATENAAAACTcvMTQvMjAyMhAAAAAJNy8xMy8yMDIypt+Z5yll2gg7lOr3KWXaCCtDSVEuS0xTRTpMS0wuSVFfRUJJVF9FU1QuSVFfRlkrMS4yMDIyLTA3LTEzAQAAAFxZAhMDAAAAAACm35nnKWXaCOfR6fcpZdoIMENJUS5OQVNEQVFHUzpBTVNDLklRX0VCSVRfRVNULklRX0ZZKzEuMjAyMi0wNy0xMwEAAAB1iAAAAgAAAAgtMjYuNjA3NQEOAAAABQAAAAEzAQAAAAEwAgAAAAoxMDAzMjgzMzkyAwAAAAYxMDAyMTUEAAAAATIGAAAAATAHAAAAAzE2MAgAAAABMAkAAAABMQoAAAABMAsAAAALMTI4OTk2OTcyNjUMAAAAATENAAAACTcvMTQvMjAyMhAAAAAJNy8xMy8yMDIypt+Z5yll2ghWRer3KWXaCCpDSVEuVFNYOlNJUy5JUV9DQVBFWF9FU1QuSVFfTlRNLjIwMjItMDctMTMBAAAASIAwAAIAAAAGLTE4LjI1AQ4AAAAFAAAAAjExAQAAAAEwAgAAAAczNjU5 | BV1: Mzk4AwAAAAYxMDQwOTAEAAAAATMGAAAAATAHAAAAAjI3CAAAAAEwCQAAAAExCgAAAAEwCwAAAAsxMjg3NDA5NjgwNAwAAAACMTINAAAACTcvMTQvMjAyMhAAAAAJNy8xMy8yMDIypt+Z5yll2ggGbOr3KWXaCCxDSVEuTllTRTpGTFIuSVFfRUJJVERBX0VTVC5JUV9OVE0uMjAyMi0wNy0xMwEAAAArAQoAAgAAAAg0OTMuMzI1NQEOAAAABQAAAAIxMQEAAAABMAIAAAAHMzk3MzQ4MwMAAAAGMTAwMTg3BAAAAAEyBgAAAAEwBwAAAAMxNjAIAAAAATAJAAAAATEKAAAAATALAAAACzEyODg5NzQxODk3DAAAAAIxMg0AAAAJNy8xNC8yMDIyEAAAAAk3LzEzLzIwMjKm35nnKWXaCDuU6vcpZdoILUNJUS5UU0U6NzgxMy5JUV9SRVZFTlVFX0VTVC5JUV9OVE0uMjAyMi0wNy0xMwEAAAAU/x0DAwAAAAAApt+Z5yll2gg2qen3KWXaCCpDSVEuS0xTRTpMS0wuSVFfRUJJVF9FU1QuSVFfTlRNLjIwMjItMDctMTMBAAAAXFkCEwMAAAAAAKbfmecpZdoIIffp9yll2ggtQ0lRLlRXU0U6NDEwNi5JUV9DQVBFWF9FU1QuSVFfRlkrMS4yMDIyLTA3LTEzAQAAACpCNgEDAAAAAACm35nnKWXaCCkf6vcpZdoILUNJUS5UU0U6NzgxNy5JUV9SRVZFTlVFX0VTVC5JUV9OVE0uMjAyMi0wNy0xMwEAAACdcw0AAgAAAAU5MzcwMAEOAAAABQAAAAIxMQEAAAABMAIAAAAKMTAwNDExMTE4MgMAAAAGMTAwMTgwBAAAAAI1NgYAAAABMAcAAAAC | BW1: NzkIAAAAATAJAAAAATEKAAAAATALAAAACzEyOTA5MzU1MTI2DAAAAAIxMg0AAAAJNy8xNC8yMDIyEAAAAAk3LzEzLzIwMjKm35nnKWXaCISD6fcpZdoIK0NJUS5UU0U6NzgxNy5JUV9DQVBFWF9FU1QuSVFfTlRNLjIwMjItMDctMTMBAAAAnXMNAAIAAAAFLTI5MDABDgAAAAUAAAACMTEBAAAAATACAAAACjEwMDQxMTExODIDAAAABjEwNDA5MAQAAAACNTYGAAAAATAHAAAAAjc5CAAAAAEwCQAAAAExCgAAAAEwCwAAAAsxMjcwODQxODUxMAwAAAACMTINAAAACTcvMTQvMjAyMhAAAAAJNy8xMy8yMDIypt+Z5yll2gg2qen3KWXaCC9DSVEuTkFTREFRR1M6QU1TQy5JUV9FQklUX0VTVC5JUV9OVE0uMjAyMi0wNy0xMwEAAAB1iAAAAgAAAAgtMjYuNjA3NQEOAAAABQAAAAIxMQEAAAABMAIAAAAKMTAwMzI4MzM5MgMAAAAGMTAwMjE1BAAAAAEyBgAAAAEwBwAAAAMxNjAIAAAAATAJAAAAATEKAAAAATALAAAACzEyODk5Njk3MjY1DAAAAAIxMg0AAAAJNy8xNC8yMDIyEAAAAAk3LzEzLzIwMjKm35nnKWXaCFZF6vcpZdoILENJUS5UV1NFOjQxMDYuSVFfQ0FQRVhfRVNULklRX05UTS4yMDIyLTA3LTEzAQAAACpCNgEDAAAAAACm35nnKWXaCCkf6vcpZdoILENJUS5PTTpBUkpPIEIuSVFfRUJJVF9FU1QuSVFfRlkrMS4yMDIyLTA3LTEzAQAAAFOW8Q4CAAAACjExODguODQ1NDYBDgAAAAUAAAABMwEAAAABMAIAAAAK | BX1: MTAwNDA2Njk1NAMAAAAGMTAwMjE1BAAAAAEzBgAAAAEwBwAAAAMxMzcIAAAAATAJAAAAATEKAAAAATALAAAACzEyOTMxMzE0MzAxDAAAAAExDQAAAAk3LzE0LzIwMjIQAAAACTcvMTMvMjAyMqbfmecpZdoIRVvp9yll2ggtQ0lRLlRTWDpTSVMuSVFfUkVWRU5VRV9FU1QuSVFfRlkrMS4yMDIyLTA3LTEzAQAAAEiAMAACAAAABzc4MC43NzUBDgAAAAUAAAABMwEAAAABMAIAAAAKMTAwMzU2Mzg5NwMAAAAGMTAwMTgwBAAAAAEzBgAAAAEwBwAAAAIyNwgAAAABMAkAAAABMQoAAAABMAsAAAALMTI4NzYyNzY2ODMMAAAAATENAAAACTcvMTQvMjAyMhAAAAAJNy8xMy8yMDIypt+Z5yll2ggGbOr3KWXaCCtDSVEuTllTRTpGTFIuSVFfRUJJVF9FU1QuSVFfRlkrMS4yMDIyLTA3LTEzAQAAACsBCgACAAAACTM0NC4wMTYxMwEOAAAABQAAAAEzAQAAAAEwAgAAAAoxMDAzNzA4Nzk1AwAAAAYxMDAyMTUEAAAAATIGAAAAATAHAAAAAzE2MAgAAAABMAkAAAABMQoAAAABMAsAAAALMTI5MTk3ODk1ODcMAAAAATENAAAACTcvMTQvMjAyMhAAAAAJNy8xMy8yMDIypt+Z5yll2gg7lOr3KWXaCCxDSVEuVFNFOjc4MTcuSVFfQ0FQRVhfRVNULklRX0ZZKzEuMjAyMi0wNy0xMwEAAACdcw0AAgAAAAUtMjkwMAEOAAAABQAAAAEzAQAAAAEwAgAAAAoxMDA0MTExMTgyAwAAAAYxMDQwOTAEAAAAAjU2BgAAAAEwBwAAAAI3OQgAAAAB | BY1: MAkAAAABMQoAAAABMAsAAAALMTI3MDg0MTg1MTAMAAAAATENAAAACTcvMTQvMjAyMhAAAAAJNy8xMy8yMDIypt+Z5yll2gg2qen3KWXaCC1DSVEuVFNFOjc4MTMuSVFfRUJJVERBX0VTVC5JUV9GWSsxLjIwMjItMDctMTMBAAAAFP8dAwMAAAAAAKbfmecpZdoINqnp9yll2ggrQ0lRLk9NOkFSSk8gQi5JUV9FQklUX0VTVC5JUV9OVE0uMjAyMi0wNy0xMwEAAABTlvEOAgAAAAkxMzA2Ljk3MTgBDgAAAAUAAAACMTEBAAAAATACAAAABzQyNTYzMDQDAAAABjEwMDIxNQQAAAABMwYAAAABMAcAAAADMTM3CAAAAAEwCQAAAAExCgAAAAEwCwAAAAsxMjkzMTMzNTAxNQwAAAACMTINAAAACTcvMTQvMjAyMhAAAAAJNy8xMy8yMDIypt+Z5yll2ghFW+n3KWXaCCpDSVEuTllTRTpGTFIuSVFfRUJJVF9FU1QuSVFfTlRNLjIwMjItMDctMTMBAAAAKwEKAAIAAAAIMzYzLjAyMjcBDgAAAAUAAAACMTEBAAAAATACAAAABzM5NzM0ODMDAAAABjEwMDIxNQQAAAABMgYAAAABMAcAAAADMTYwCAAAAAEwCQAAAAExCgAAAAEwCwAAAAsxMjkxOTgwMzY4OAwAAAACMTINAAAACTcvMTQvMjAyMhAAAAAJNy8xMy8yMDIypt+Z5yll2gg7lOr3KWXaCCxDSVEuVFNYOlNJUy5JUV9SRVZFTlVFX0VTVC5JUV9OVE0uMjAyMi0wNy0xMwEAAABIgDAAAgAAAAg3OTMuOTcxNAEOAAAABQAAAAIxMQEAAAABMAIAAAAHMzY1OTM5OAMAAAAGMTAw | BZ1: MTgwBAAAAAEzBgAAAAEwBwAAAAIyNwgAAAABMAkAAAABMQoAAAABMAsAAAALMTI4NzYyODAzNDcMAAAAAjEyDQAAAAk3LzE0LzIwMjIQAAAACTcvMTMvMjAyMqbfmecpZdoIBmzq9yll2ggvQ0lRLlRXU0U6NDEwNi5JUV9SRVZFTlVFX0VTVC5JUV9GWSsxLjIwMjItMDctMTMBAAAAKkI2AQMAAAAAAKbfmecpZdoIKR/q9yll2ggsQ0lRLk5ZU0U6R1ZBLklRX0NBUEVYX0VTVC5JUV9GWSsxLjIwMjItMDctMTMBAAAAujUEAAIAAAAILTExOC4xNzUBDgAAAAUAAAABMwEAAAABMAIAAAAKMTAwMjYxMjU2NgMAAAAGMTA0MDkwBAAAAAEyBgAAAAEwBwAAAAMxNjAIAAAAATAJAAAAATEKAAAAATALAAAACzEyODgwMDI3MTI0DAAAAAExDQAAAAk3LzE0LzIwMjIQAAAACTcvMTMvMjAyMqbfmecpZdoIMbvq9yll2ggtQ0lRLlRXU0U6NDEwNi5JUV9FQklUREFfRVNULklRX05UTS4yMDIyLTA3LTEzAQAAACpCNgEDAAAAAACm35nnKWXaCCkf6vcpZdoILENJUS5UU0U6NzgxMy5JUV9FQklUREFfRVNULklRX05UTS4yMDIyLTA3LTEzAQAAABT/HQMDAAAAAACm35nnKWXaCOfR6fcpZdoILkNJUS5UV1NFOjQxMDYuSVFfUkVWRU5VRV9FU1QuSVFfTlRNLjIwMjItMDctMTMBAAAAKkI2AQMAAAAAAKbfmecpZdoIKR/q9yll2ggrQ0lRLk5ZU0U6R1ZBLklRX0NBUEVYX0VTVC5JUV9OVE0uMjAyMi0wNy0xMwEAAAC6NQQAAgAA | CA1: AAktMTE4LjE3MjUBDgAAAAUAAAACMTEBAAAAATACAAAACTcwMTM2MDM2MwMAAAAGMTA0MDkwBAAAAAEyBgAAAAEwBwAAAAMxNjAIAAAAATAJAAAAATEKAAAAATALAAAACzEyODgwMDI4OTIyDAAAAAIxMg0AAAAJNy8xNC8yMDIyEAAAAAk3LzEzLzIwMjKm35nnKWXaCDG76vcpZdoILENJUS5UU1g6U0lTLklRX0VCSVREQV9FU1QuSVFfRlkrMS4yMDIyLTA3LTEzAQAAAEiAMAACAAAACDEyMi40ODc1AQ4AAAAFAAAAATMBAAAAATACAAAACjEwMDM1NjM4OTcDAAAABjEwMDE4NwQAAAABMwYAAAABMAcAAAACMjcIAAAAATAJAAAAATEKAAAAATALAAAACzEyODc0NzAxMzE3DAAAAAExDQAAAAk3LzE0LzIwMjIQAAAACTcvMTMvMjAyMqbfmecpZdoIBmzq9yll2ggrQ0lRLlRTRTo3ODEzLklRX0VCSVRfRVNULklRX0ZZKzEuMjAyMi0wNy0xMwEAAAAU/x0DAwAAAAAApt+Z5yll2gg2qen3KWXaCC5DSVEuVFNFOjc4MTcuSVFfUkVWRU5VRV9FU1QuSVFfRlkrMS4yMDIyLTA3LTEzAQAAAJ1zDQACAAAABTkzNzAwAQ4AAAAFAAAAATMBAAAAATACAAAACjEwMDQxMTExODIDAAAABjEwMDE4MAQAAAACNTYGAAAAATAHAAAAAjc5CAAAAAEwCQAAAAExCgAAAAEwCwAAAAsxMjkwOTM1NTEyNgwAAAABMQ0AAAAJNy8xNC8yMDIyEAAAAAk3LzEzLzIwMjKm35nnKWXaCISD6fcpZdoIK0NJUS5UU1g6U0lTLklRX0VCSVREQV9F | CB1: U1QuSVFfTlRNLjIwMjItMDctMTMBAAAASIAwAAIAAAAIMTI1LjE2MjUBDgAAAAUAAAACMTEBAAAAATACAAAABzM2NTkzOTgDAAAABjEwMDE4NwQAAAABMwYAAAABMAcAAAACMjcIAAAAATAJAAAAATEKAAAAATALAAAACzEyODc2MDI2NjE3DAAAAAIxMg0AAAAJNy8xNC8yMDIyEAAAAAk3LzEzLzIwMjKm35nnKWXaCAZs6vcpZdoILkNJUS5UV1NFOjQxMDYuSVFfRUJJVERBX0VTVC5JUV9GWSsxLjIwMjItMDctMTMBAAAAKkI2AQMAAAAAAKbfmecpZdoIKR/q9yll2ggrQ0lRLktMU0U6TEtMLklRX0NBUEVYX0VTVC5JUV9OVE0uMjAyMi0wNy0xMwEAAABcWQITAwAAAAAApt+Z5yll2ggh9+n3KWXaCCpDSVEuVFNFOjc4MTMuSVFfRUJJVF9FU1QuSVFfTlRNLjIwMjItMDctMTMBAAAAFP8dAwMAAAAAAKbfmecpZdoINqnp9yll2ggsQ0lRLktMU0U6TEtMLklRX0NBUEVYX0VTVC5JUV9GWSsxLjIwMjItMDctMTMBAAAAXFkCEwMAAAAAAKbfmecpZdoIIffp9yll2gg=

Sheet BSM Model
C3: Method 1: Black-Scholes-Merton Model
C5: Input Assumptions | F5: Notes
C6: Ticker | E6: AAPL
C7: Option | E7: European-style vanilla call | I7: Call Option Price Sensitivity Analysis
C8: Valuation Date | E8: ='[1]Historical Prices'!B4 -> 46101 | K8: T
C9: Stock price at time0 | D9: S0 | E9: ='Historical Prices'!B9 -> 247.99 | F9: Bloomberg spot price | J9: =E25 -> 22.625253 | K9: 0.1 | L9: 0.2 | M9: 0.3 | N9: 0.4 | O9: 0.5 | P9: 0.6 | Q9: 0.7 | R9: 0.8 | S9: 0.9 | T9: 1
C10: Volatility: Choose source | E10: Implied volatility | I10: σ | J10: 0.1 | K10: 2.5798628 | L10: 4.249105 | M10: 5.6443719 | N10: 6.8953425 | O10: 8.0535159 | P10: 9.1455436 | Q10: 10.187314 | R10: 11.189187 | S10: 12.158356 | T10: 13.100048
C11: Implied volatility | E11: ='Option Monitor'!F7/100 -> 0.31072491 | F11: Bloomberg implied volatility | J11: 0.15 | K11: 4.1351594 | L11: 6.459424 | M11: 8.3451161 | N11: 10.000971 | O11: 11.508826 | P11: 12.910873 | Q11: 14.232255 | R11: 15.489381 | S11: 16.693666 | T11: 17.853427
C12: Historical volatility | E12: ='Historical Prices'!F9 -> 0.22560599 | F12: 180-day annualized historical | J12: 0.2 | K12: 5.6960176 | L12: 8.6692883 | M12: 11.044882 | N12: 13.107801 | O12: 14.969311 | P12: 16.686714 | Q12: 18.294145 | R12: 19.813895 | S12: 21.261475 | T12: 22.6482
C13: Active volatility | D13: σ | E13: =IF(E10="Implied volatility", E11, E12) -> 0.31072491 | J13: 0.25 | K13: 7.2588332 | L13: 10.878197 | M13: 13.742841 | N13: 16.212936 | O13: 18.428842 | P13: 20.462803 | Q13: 22.357859 | R13: 24.142118 | S13: 25.83515 | T13: 27.451233
C14: Strike price | D14: K | E14: ='Option Monitor'!H7 -> 250 | J14: 0.3 | K14: 8.8223351 | L14: 13.085801 | M14: 16.438379 | N14: 19.314898 | O14: 21.884653 | P14: 24.23477 | Q14: 26.417153 | R14: 28.465708 | S14: 30.404047 | T14: 32.2494
C15: Time until option expiration | D15: T | E15: 0.5 | J15: 0.35 | K15: 10.385922 | L15: 15.291792 | M15: 19.130948 | N15: 22.412612 | O15: 25.334952 | P15: 27.999944 | Q15: 30.46835 | R15: 32.779869 | S15: 34.962149 | T15: 37.035378
C16: Risk-free rate | D16: r | E16: ='Risk-Free Rate'!C2/100 -> 0.037438 | F16: USGG6M INDEX | J16: 0.4 | K16: 11.949245 | L16: 17.495881 | M16: 21.820024 | N16: 25.505162 | O16: 28.77831 | P16: 31.756298 | Q16: 34.508746 | R16: 37.081151 | S16: 39.505207 | T16: 41.804058
C17: Dividend yield | D17: q | E17: ='Dividend Yield'!B2 -> 0.0042 | F17: Indicated yield | J17: 0.45 | K17: 13.512066 | L17: 19.697784 | M17: 24.505095 | N17: 28.5917 | O17: 32.213469 | P17: 35.502098 | Q17: 38.53608 | R17: 41.366721 | S17: 44.029771 | T17: 46.551341
J18: 0.5 | K18: 15.074204 | L18: 21.897224 | M18: 27.185657 | N18: 31.671417 | O18: 35.639258 | P18: 39.235765 | Q18: 42.548323 | R18: 45.634066 | S18: 48.532814 | T18: 51.273659
C19: Calculation
D20: d1 | E20: =(LN(E9/E14) + (E16 - E17 + (E13^2)/2) * E15) / (E13 * SQRT(E15)) -> 0.14875586
D21: d2 | E21: =E20 -E13 * SQRT( E15) -> -0.070959826
D22: N(d1) | E22: =_xlfn.NORM.S.DIST(E20, TRUE) -> 0.55912686
D23: N(d2) | E23: =_xlfn.NORM.S.DIST(E21, TRUE) -> 0.47171486
C25: Call Option Price | E25: =E9 * EXP(-E17 * E15) * E22 - E14 * EXP(-E16 * E15) * E23 -> 22.625253
C27: Greeks
C28: Delta | D28: Δ | E28: =EXP(-E17*E15)*E22 -> 0.55795393 | F28: Option price change per $1 move in underlying stock
C29: Gamma | D29: Γ | E29: =(EXP(-E17*E15) * _xlfn.NORM.S.DIST(E20, FALSE)) / (E9 * E13 * SQRT(E15)) -> 0.0072259959 | F29: Rate of change in Δ per $1 move in underlying stock
C30: Vega | D30: ν | E30: =(E9 * EXP(-E17*E15) * SQRT(E15) * _xlfn.NORM.S.DIST(E20, FALSE)) / 100 -> 0.69041802 | F30: Option price change per 1% increase in implied volatility
C31: Theta | D31: Θ | E31: =(-(E9*E13*EXP(-E17*E15)*_xlfn.NORM.S.DIST(E20,FALSE))/(2*SQRT(E15)) + E17*E9*EXP(-E17*E15)*E22 - E16*E14*EXP(-E16*E15)*E23) / 365 -> -0.069054809 | F31: Daily loss in option value due to time decay
C32: Rho | D32: ρ | E32: =(E14 * E15 * EXP(-E16*E15) * E23) / 100 -> 0.57870871 | F32: Option price change per 1% increase in r

Sheet DCF
C3: Editure Limited | Discounted Cash Flow (DCF)
C5: =Cover!C5 -> 0
A7: x | C7: Overview
B9: x | C9: Key Company Assumptions
C11: Tax Rate | G11: =Tax -> #REF!
C12: WACC | G12: 0.052817989
C13: Terminal Growth Rate | G13: 0.019
C14: Exit Multiple | G14: 9.3
A16: x | C16: Discounted Cash Flow Valuation
B18: x | C18: Operating Model
C20: ($USD in thousands) | G20: =#REF! -> #REF! | H20: =#REF! -> #REF! | I20: =#REF! -> #REF! | J20: =#REF! -> #REF! | K20: =#REF! -> #REF! | L20: =#REF! -> #REF!
C21: Total Revenue | G21: =#REF! -> #REF! | H21: =#REF! -> #REF! | I21: =#REF! -> #REF! | J21: =#REF! -> #REF! | K21: =#REF! -> #REF! | L21: =#REF! -> #REF!
C22: % Growth | G22: =#REF! -> #REF! | H22: =#REF! -> #REF! | I22: =#REF! -> #REF! | J22: =#REF! -> #REF! | K22: =#REF! -> #REF! | L22: =#REF! -> #REF!
C23: Cost of Goods Sold (COGS) | G23: =#REF! -> #REF! | H23: =#REF! -> #REF! | I23: =#REF! -> #REF! | J23: =#REF! -> #REF! | K23: =#REF! -> #REF! | L23: =#REF! -> #REF!
C24: % Margin | G24: =G23/G21 -> #REF! | H24: =H23/H21 -> #REF! | I24: =I23/I21 -> #REF! | J24: =J23/J21 -> #REF! | K24: =K23/K21 -> #REF! | L24: =L23/L21 -> #REF!
C25: Gross Profit | G25: =G21-G23 -> #REF! | H25: =H21-H23 -> #REF! | I25: =I21-I23 -> #REF! | J25: =J21-J23 -> #REF! | K25: =K21-K23 -> #REF! | L25: =L21-L23 -> #REF!
C26: % Margin | G26: =G25/G21 -> #REF! | H26: =H25/H21 -> #REF! | I26: =I25/I21 -> #REF! | J26: =J25/J21 -> #REF! | K26: =K25/K21 -> #REF! | L26: =L25/L21 -> #REF!
C28: Total Operating Expenses | G28: =#REF! -> #REF! | H28: =#REF! -> #REF! | I28: =#REF! -> #REF! | J28: =#REF! -> #REF! | K28: =#REF! -> #REF! | L28: =#REF! -> #REF!
C29: % Margin | G29: =G28/G21 -> #REF! | H29: =H28/H21 -> #REF! | I29: =I28/I21 -> #REF! | J29: =J28/J21 -> #REF! | K29: =K28/K21 -> #REF! | L29: =L28/L21 -> #REF!
C30: EBIT | G30: =#REF! -> #REF! | H30: =#REF! -> #REF! | I30: =#REF! -> #REF! | J30: =#REF! -> #REF! | K30: =#REF! -> #REF! | L30: =#REF! -> #REF!
C31: % Margin | G31: =G30/G21 -> #REF! | H31: =H30/H21 -> #REF! | I31: =I30/I21 -> #REF! | J31: =J30/J21 -> #REF! | K31: =K30/K21 -> #REF! | L31: =L30/L21 -> #REF!
C32: Depreciation & Amortization | G32: =#REF! -> #REF! | H32: =#REF! -> #REF! | I32: =#REF! -> #REF! | J32: =#REF! -> #REF! | K32: =#REF! -> #REF! | L32: =#REF! -> #REF!
C33: % Margin | G33: =G32/G21 -> #REF! | H33: =H32/H21 -> #REF! | I33: =I32/I21 -> #REF! | J33: =J32/J21 -> #REF! | K33: =K32/K21 -> #REF! | L33: =L32/L21 -> #REF!
C34: EBITDA | G34: =G30+G32 -> #REF! | H34: =H30+H32 -> #REF! | I34: =I30+I32 -> #REF! | J34: =J30+J32 -> #REF! | K34: =K30+K32 -> #REF! | L34: =L30+L32 -> #REF!
C35: % Margin | G35: =G34/G21 -> #REF! | H35: =H34/H21 -> #REF! | I35: =I34/I21 -> #REF! | J35: =J34/J21 -> #REF! | K35: =K34/K21 -> #REF! | L35: =L34/L21 -> #REF!
B38: x | C38: Unlevered Free Cash Flow
C40: =C20 -> ($USD in thousands) | G40: =G20 -> #REF! | H40: =H20 -> #REF! | I40: =I20 -> #REF! | J40: =J20 -> #REF! | K40: =K20 -> #REF! | L40: =L20 -> #REF!
C41: EBIT | G41: =G30 -> #REF! | H41: =H30 -> #REF! | I41: =I30 -> #REF! | J41: =J30 -> #REF! | K41: =K30 -> #REF! | L41: =L30 -> #REF!
C42: % Tax Rate | G42: =Tax -> #REF! | H42: =Tax -> #REF! | I42: =Tax -> #REF! | J42: =Tax -> #REF! | K42: =Tax -> #REF! | L42: =Tax -> #REF!
C43: ( + ) NOPAT | G43: =G41*(1-G42) -> #REF! | H43: =H41*(1-H42) -> #REF! | I43: =I41*(1-I42) -> #REF! | J43: =J41*(1-J42) -> #REF! | K43: =K41*(1-K42) -> #REF! | L43: =L41*(1-L42) -> #REF!
C44: ( – ) CapEx | G44: =#REF! -> #REF! | H44: =#REF! -> #REF! | I44: =#REF! -> #REF! | J44: =#REF! -> #REF! | K44: =#REF! -> #REF! | L44: =#REF! -> #REF!
C45: ( – ) Increase in Net Working Capital (NWC) | G45: =#REF! -> #REF! | H45: =#REF! -> #REF! | I45: =#REF! -> #REF! | J45: =#REF! -> #REF! | K45: =#REF! -> #REF! | L45: =#REF! -> #REF!
C46: ( + ) D&A | G46: =#REF! -> #REF! | H46: =#REF! -> #REF! | I46: =#REF! -> #REF! | J46: =#REF! -> #REF! | K46: =#REF! -> #REF! | L46: =#REF! -> #REF!
C48: Unlevered Free Cash Flow | G48: =G43-G44-G45+G46 -> #REF! | H48: =H43-H44-H45+H46 -> #REF! | I48: =I43-I44-I45+I46 -> #REF! | J48: =J43-J44-J45+J46 -> #REF! | K48: =K43-K44-K45+K46 -> #REF! | L48: =L43-L44-L45+L46 -> #REF!
C49: % Margin | G49: =G48/G$21 -> #REF! | H49: =H48/H$21 -> #REF! | I49: =I48/I$21 -> #REF! | J49: =J48/J$21 -> #REF! | K49: =K48/K$21 -> #REF! | L49: =L48/L$21 -> #REF!
C51: Unlevered FCF (FCFF) | G51: =G48 -> #REF! | H51: =H48 -> #REF! | I51: =I48 -> #REF! | J51: =J48 -> #REF! | K51: =K48 -> #REF! | L51: =L48 -> #REF!
C52: Discount Period | D52: (Using mid-year convention) | G52: =0.25/2 -> 0.125 | H52: =0.5+0.25 -> 0.75 | I52: =H52+1 -> 1.75 | J52: =I52+1 -> 2.75 | K52: =J52+1 -> 3.75 | L52: =K52+1 -> 4.75
C53: Discount Factor | G53: =1/(1+$G$12)^G52 -> 0.99358686 | H53: =1/(1+$G$12)^H52 -> 0.96213282 | I53: =1/(1+$G$12)^I52 -> 0.91386434 | J53: =1/(1+$G$12)^J52 -> 0.86801741 | K53: =1/(1+$G$12)^K52 -> 0.82447053 | L53: =1/(1+$G$12)^L52 -> 0.78310832
C54: Discounted UFCFs | G54: =G51*G53 -> #REF! | H54: =H51*H53 -> #REF! | I54: =I51*I53 -> #REF! | J54: =J51*J53 -> #REF! | K54: =K51*K53 -> #REF! | L54: =L51*L53 -> #REF!
C56: PV of UFCFs | D56: =SUM(G54:L54) -> #REF!
B59: x | C59: Terminal Value
C61: Gordon Growth
C62: Final Year UFCF | E62: =L51 -> #REF!
C63: Growth Rate (g) | E63: =G13 -> 0.019
C64: WACC | E64: =G12 -> 0.052817989
C65: Terminal Value | E65: =(E62*(1+E63)/($G$12-E63)) -> #REF!
C67: PV of Terminal Value | D67: =E65/(1+$G$12)^5.25 -> #REF!
C69: Exit Multiple
C70: Final Year EBITDA | E70: =L30 -> #REF!
C71: Exit Multiple | E71: =G14 -> 9.3
C72: WACC | E72: =$G$12 -> 0.052817989
C73: Terminal Value | E73: =E70*E71 -> #REF!
C75: PV of Terminal Value | D75: =E73/(1+$G$12)^5.25 -> #REF!
B78: x | C78: Valuation (Gordon Growth Method)
C80: ( + ) Enterprise Value | E80: =(D67+D75)/2+D56 -> #REF!
C81: ( – ) Debt | E81: 414131
C82: ( + ) Cash | E82: 43903
C83: Equity Value | E83: =E80-E81+E82 -> #REF!
C85: Fully Diluted S.O. | E85: =7985700000/12.35 -> 6.4661538e+08
C86: Implied Share Price | E86: =E83/E85 -> #REF!
C88: EV / 2012E EBITDA | E88: =E80/F30 -> #REF!
C89: EV / 2013P EBITDA | E89: =E80/H30 -> #REF!
C90: EV / 2017P EBITDA | E90: =E80/L30 -> #REF!
C92: EV / 2012E Revenue | E92: =E80/F21 -> #REF!
C93: EV / 2013P Revenue | E93: =E80/H21 -> #REF!
C94: EV / 2017P Revenue | E94: =E80/L21 -> #REF!
A97: x | C97: Sensitivity
B99: x | C99: EV / 2013P EBITDA
E101: WACC
D102: =E89 -> #REF! | E102: 0.0813 | F102: 0.0863 | G102: 0.0913 | H102: 0.0963 | I102: 0.1013
D103: 0.015 | E103: #REF! | F103: #REF! | G103: #REF! | H103: #REF! | I103: #REF!
C104: Perpetuity | D104: 0.0175 | E104: #REF! | F104: #REF! | G104: #REF! | H104: #REF! | I104: #REF!
C105: Growth | D105: 0.02 | E105: #REF! | F105: #REF! | G105: #REF! | H105: #REF! | I105: #REF!
C106: Rate | D106: 0.0225 | E106: #REF! | F106: #REF! | G106: #REF! | H106: #REF! | I106: #REF!
D107: 0.025 | E107: #REF! | F107: #REF! | G107: #REF! | H107: #REF! | I107: #REF!
B110: x | C110: EV / 2013P Revenue
E112: WACC
D113: =E93 -> #REF! | E113: =E102 -> 0.0813 | F113: =F102 -> 0.0863 | G113: =G102 -> 0.0913 | H113: =H102 -> 0.0963 | I113: =I102 -> 0.1013
D114: =D103 -> 0.015 | E114: #REF! | F114: #REF! | G114: #REF! | H114: #REF! | I114: #REF!
C115: Perpetuity | D115: =D104 -> 0.0175 | E115: #REF! | F115: #REF! | G115: #REF! | H115: #REF! | I115: #REF!
C116: Growth | D116: =D105 -> 0.02 | E116: #REF! | F116: #REF! | G116: #REF! | H116: #REF! | I116: #REF!
C117: Rate | D117: =D106 -> 0.0225 | E117: #REF! | F117: #REF! | G117: #REF! | H117: #REF! | I117: #REF!
D118: =D107 -> 0.025 | E118: #REF! | F118: #REF! | G118: #REF! | H118: #REF! | I118: #REF!
A121: x | B121: x

Sheet Binomial Tree
C3: Method 2: Binomial Tree
C5: Input Assumptions | H5: Notes
C6: Ticker | G6: AAPL
C7: Option | G7: European-style vanilla call
C8: Valuation Date | G8: ='[1]Historical Prices'!B4 -> 46101
C9: Stock price at time0 | F9: S0 | G9: ='BSM Model'!E9 -> 247.99 | H9: Bloomberg spot price
C10: Volatility: Choose source | G10: Implied volatility
C11: Implied volatility | G11: ='Option Monitor'!F7/100 -> 0.31072491 | H11: Bloomberg implied volatility
C12: Historical volatility | G12: ='Historical Prices'!F9 -> 0.22560599 | H12: 180-day annualized historical
C13: Active volatility | F13: σ | G13: =IF(G10="Implied volatility", G11, G12) -> 0.31072491
C14: Total lifetime in years | F14: T | G14: ='BSM Model'!E15 -> 0.5
C15: Number of periods | F15: N | G15: 100
C16: Length of periods in years | F16: Δt | G16: =G14/G15 -> 0.005
C17: Up-movement | F17: u | G17: =EXP(G13 * SQRT(G16)) -> 1.0222147
C18: Down-movement | F18: d | G18: =1/G17 -> 0.97826805
C19: Probability | F19: p | G19: =(EXP((G21-G22)*G16) - G18) / (G17 - G18) -> 0.49828927
C20: Strike price | F20: K | G20: ='Option Monitor'!H7 -> 250
C21: Risk-free rate | F21: r | G21: ='Risk-Free Rate'!C2/100 -> 0.037438 | H21: USGG6M INDEX
C22: Dividend yield | F22: q | G22: ='Dividend Yield'!B2 -> 0.0042 | H22: Indicated yield
C25: Call Option Price | G25: =D136 -> 22.635424
C28: Stock Price Tree
D29: 0 | E29: 1 | F29: 2 | G29: 3 | H29: 4 | I29: 5 | J29: 6 | K29: 7 | L29: 8 | M29: 9 | N29: 10 | O29: 11 | P29: 12 | Q29: 13 | R29: 14 | S29: 15 | T29: 16 | U29: 17 | V29: 18 | W29: 19 | X29: 20 | Y29: 21 | Z29: 22 | AA29: 23 | AB29: 24 | AC29: 25 | AD29: 26 | AE29: 27 | AF29: 28 | AG29: 29 | AH29: 30 | AI29: 31 | AJ29: 32 | AK29: 33 | AL29: 34 | AM29: 35 | AN29: 36 | AO29: 37 | AP29: 38 | AQ29: 39 | AR29: 40 | AS29: 41 | AT29: 42 | AU29: 43 | AV29: 44 | AW29: 45 | AX29: 46 | AY29: 47 | AZ29: 48 | BA29: 49 | BB29: 50 | BC29: 51 | BD29: 52 | BE29: 53 | BF29: 54 | BG29: 55 | BH29: 56 | BI29: 57 | BJ29: 58 | BK29: 59 | BL29: 60 | BM29: 61 | BN29: 62 | BO29: 63 | BP29: 64 | BQ29: 65 | BR29: 66 | BS29: 67 | BT29: 68 | BU29: 69 | BV29: 70 | BW29: 71 | BX29: 72 | BY29: 73 | BZ29: 74 | CA29: 75 | CB29: 76 | CC29: 77 | CD29: 78 | CE29: 79 | CF29: 80 | CG29: 81 | CH29: 82 | CI29: 83 | CJ29: 84 | CK29: 85 | CL29: 86 | CM29: 87 | CN29: 88 | CO29: 89 | CP29: 90 | CQ29: 91 | CR29: 92 | CS29: 93 | CT29: 94 | CU29: 95 | CV29: 96 | CW29: 97 | CX29: 98 | CY29: 99 | CZ29: 100
C30: 0 | D30: =IF($C30>D$29, "", $G$9 * ($G$17^(D$29-$C30)) * ($G$18^$C30)) -> 247.99 | E30: =IF($C30>E$29, "", $G$9 * ($G$17^(E$29-$C30)) * ($G$18^$C30)) -> 253.49903 | F30: =IF($C30>F$29, "", $G$9 * ($G$17^(F$29-$C30)) * ($G$18^$C30)) -> 259.13044 | G30: =IF($C30>G$29, "", $G$9 * ($G$17^(G$29-$C30)) * ($G$18^$C30)) -> 264.88695 | H30: =IF($C30>H$29, "", $G$9 * ($G$17^(H$29-$C30)) * ($G$18^$C30)) -> 270.77134 | I30: =IF($C30>I$29, "", $G$9 * ($G$17^(I$29-$C30)) * ($G$18^$C30)) -> 276.78645 | J30: =IF($C30>J$29, "", $G$9 * ($G$17^(J$29-$C30)) * ($G$18^$C30)) -> 282.93518 | K30: =IF($C30>K$29, "", $G$9 * ($G$17^(K$29-$C30)) * ($G$18^$C30)) -> 289.22051 | ... CZ30: =IF($C30>CZ$29, "", $G$9 * ($G$17^(CZ$29-$C30)) * ($G$18^$C30)) -> 2231.7589
C31: 1 | D31: =IF($C31>D$29, "", $G$9 * ($G$17^(D$29-$C31)) * ($G$18^$C31)) | E31: =IF($C31>E$29, "", $G$9 * ($G$17^(E$29-$C31)) * ($G$18^$C31)) -> 242.60069 | F31: =IF($C31>F$29, "", $G$9 * ($G$17^(F$29-$C31)) * ($G$18^$C31)) -> 247.99 | G31: =IF($C31>G$29, "", $G$9 * ($G$17^(G$29-$C31)) * ($G$18^$C31)) -> 253.49903 | H31: =IF($C31>H$29, "", $G$9 * ($G$17^(H$29-$C31)) * ($G$18^$C31)) -> 259.13044 | I31: =IF($C31>I$29, "", $G$9 * ($G$17^(I$29-$C31)) * ($G$18^$C31)) -> 264.88695 | J31: =IF($C31>J$29, "", $G$9 * ($G$17^(J$29-$C31)) * ($G$18^$C31)) -> 270.77134 | K31: =IF($C31>K$29, "", $G$9 * ($G$17^(K$29-$C31)) * ($G$18^$C31)) -> 276.78645 | ... CZ31: =IF($C31>CZ$29, "", $G$9 * ($G$17^(CZ$29-$C31)) * ($G$18^$C31)) -> 2135.812
C32: 2 | D32: =IF($C32>D$29, "", $G$9 * ($G$17^(D$29-$C32)) * ($G$18^$C32)) | E32: =IF($C32>E$29, "", $G$9 * ($G$17^(E$29-$C32)) * ($G$18^$C32)) | F32: =IF($C32>F$29, "", $G$9 * ($G$17^(F$29-$C32)) * ($G$18^$C32)) -> 237.32851 | G32: =IF($C32>G$29, "", $G$9 * ($G$17^(G$29-$C32)) * ($G$18^$C32)) -> 242.60069 | H32: =IF($C32>H$29, "", $G$9 * ($G$17^(H$29-$C32)) * ($G$18^$C32)) -> 247.99 | I32: =IF($C32>I$29, "", $G$9 * ($G$17^(I$29-$C32)) * ($G$18^$C32)) -> 253.49903 | J32: =IF($C32>J$29, "", $G$9 * ($G$17^(J$29-$C32)) * ($G$18^$C32)) -> 259.13044 | K32: =IF($C32>K$29, "", $G$9 * ($G$17^(K$29-$C32)) * ($G$18^$C32)) -> 264.88695 | ... CZ32: =IF($C32>CZ$29, "", $G$9 * ($G$17^(CZ$29-$C32)) * ($G$18^$C32)) -> 2043.99
C33: 3 | D33: =IF($C33>D$29, "", $G$9 * ($G$17^(D$29-$C33)) * ($G$18^$C33)) | E33: =IF($C33>E$29, "", $G$9 * ($G$17^(E$29-$C33)) * ($G$18^$C33)) | F33: =IF($C33>F$29, "", $G$9 * ($G$17^(F$29-$C33)) * ($G$18^$C33)) | G33: =IF($C33>G$29, "", $G$9 * ($G$17^(G$29-$C33)) * ($G$18^$C33)) -> 232.17089 | H33: =IF($C33>H$29, "", $G$9 * ($G$17^(H$29-$C33)) * ($G$18^$C33)) -> 237.32851 | I33: =IF($C33>I$29, "", $G$9 * ($G$17^(I$29-$C33)) * ($G$18^$C33)) -> 242.60069 | J33: =IF($C33>J$29, "", $G$9 * ($G$17^(J$29-$C33)) * ($G$18^$C33)) -> 247.99 | K33: =IF($C33>K$29, "", $G$9 * ($G$17^(K$29-$C33)) * ($G$18^$C33)) -> 253.49903 | ... CZ33: =IF($C33>CZ$29, "", $G$9 * ($G$17^(CZ$29-$C33)) * ($G$18^$C33)) -> 1956.1155
C34: 4 | D34: =IF($C34>D$29, "", $G$9 * ($G$17^(D$29-$C34)) * ($G$18^$C34)) | E34: =IF($C34>E$29, "", $G$9 * ($G$17^(E$29-$C34)) * ($G$18^$C34)) | F34: =IF($C34>F$29, "", $G$9 * ($G$17^(F$29-$C34)) * ($G$18^$C34)) | G34: =IF($C34>G$29, "", $G$9 * ($G$17^(G$29-$C34)) * ($G$18^$C34)) | H34: =IF($C34>H$29, "", $G$9 * ($G$17^(H$29-$C34)) * ($G$18^$C34)) -> 227.12537 | I34: =IF($C34>I$29, "", $G$9 * ($G$17^(I$29-$C34)) * ($G$18^$C34)) -> 232.17089 | J34: =IF($C34>J$29, "", $G$9 * ($G$17^(J$29-$C34)) * ($G$18^$C34)) -> 237.32851 | K34: =IF($C34>K$29, "", $G$9 * ($G$17^(K$29-$C34)) * ($G$18^$C34)) -> 242.60069 | ... CZ34: =IF($C34>CZ$29, "", $G$9 * ($G$17^(CZ$29-$C34)) * ($G$18^$C34)) -> 1872.0189
C35: 5 | D35: =IF($C35>D$29, "", $G$9 * ($G$17^(D$29-$C35)) * ($G$18^$C35)) | E35: =IF($C35>E$29, "", $G$9 * ($G$17^(E$29-$C35)) * ($G$18^$C35)) | F35: =IF($C35>F$29, "", $G$9 * ($G$17^(F$29-$C35)) * ($G$18^$C35)) | G35: =IF($C35>G$29, "", $G$9 * ($G$17^(G$29-$C35)) * ($G$18^$C35)) | H35: =IF($C35>H$29, "", $G$9 * ($G$17^(H$29-$C35)) * ($G$18^$C35)) | I35: =IF($C35>I$29, "", $G$9 * ($G$17^(I$29-$C35)) * ($G$18^$C35)) -> 222.18949 | J35: =IF($C35>J$29, "", $G$9 * ($G$17^(J$29-$C35)) * ($G$18^$C35)) -> 227.12537 | K35: =IF($C35>K$29, "", $G$9 * ($G$17^(K$29-$C35)) * ($G$18^$C35)) -> 232.17089 | ... CZ35: =IF($C35>CZ$29, "", $G$9 * ($G$17^(CZ$29-$C35)) * ($G$18^$C35)) -> 1791.5378
C36: 6 | D36: =IF($C36>D$29, "", $G$9 * ($G$17^(D$29-$C36)) * ($G$18^$C36)) | E36: =IF($C36>E$29, "", $G$9 * ($G$17^(E$29-$C36)) * ($G$18^$C36)) | F36: =IF($C36>F$29, "", $G$9 * ($G$17^(F$29-$C36)) * ($G$18^$C36)) | G36: =IF($C36>G$29, "", $G$9 * ($G$17^(G$29-$C36)) * ($G$18^$C36)) | H36: =IF($C36>H$29, "", $G$9 * ($G$17^(H$29-$C36)) * ($G$18^$C36)) | I36: =IF($C36>I$29, "", $G$9 * ($G$17^(I$29-$C36)) * ($G$18^$C36)) | J36: =IF($C36>J$29, "", $G$9 * ($G$17^(J$29-$C36)) * ($G$18^$C36)) -> 217.36088 | K36: =IF($C36>K$29, "", $G$9 * ($G$17^(K$29-$C36)) * ($G$18^$C36)) -> 222.18949 | ... CZ36: =IF($C36>CZ$29, "", $G$9 * ($G$17^(CZ$29-$C36)) * ($G$18^$C36)) -> 1714.5167
C37: 7 | D37: =IF($C37>D$29, "", $G$9 * ($G$17^(D$29-$C37)) * ($G$18^$C37)) | E37: =IF($C37>E$29, "", $G$9 * ($G$17^(E$29-$C37)) * ($G$18^$C37)) | F37: =IF($C37>F$29, "", $G$9 * ($G$17^(F$29-$C37)) * ($G$18^$C37)) | G37: =IF($C37>G$29, "", $G$9 * ($G$17^(G$29-$C37)) * ($G$18^$C37)) | H37: =IF($C37>H$29, "", $G$9 * ($G$17^(H$29-$C37)) * ($G$18^$C37)) | I37: =IF($C37>I$29, "", $G$9 * ($G$17^(I$29-$C37)) * ($G$18^$C37)) | J37: =IF($C37>J$29, "", $G$9 * ($G$17^(J$29-$C37)) * ($G$18^$C37)) | K37: =IF($C37>K$29, "", $G$9 * ($G$17^(K$29-$C37)) * ($G$18^$C37)) -> 212.6372 | ... CZ37: =IF($C37>CZ$29, "", $G$9 * ($G$17^(CZ$29-$C37)) * ($G$18^$C37)) -> 1640.8068
C38: 8 | D38: =IF($C38>D$29, "", $G$9 * ($G$17^(D$29-$C38)) * ($G$18^$C38)) | E38: =IF($C38>E$29, "", $G$9 * ($G$17^(E$29-$C38)) * ($G$18^$C38)) | F38: =IF($C38>F$29, "", $G$9 * ($G$17^(F$29-$C38)) * ($G$18^$C38)) | G38: =IF($C38>G$29, "", $G$9 * ($G$17^(G$29-$C38)) * ($G$18^$C38)) | H38: =IF($C38>H$29, "", $G$9 * ($G$17^(H$29-$C38)) * ($G$18^$C38)) | I38: =IF($C38>I$29, "", $G$9 * ($G$17^(I$29-$C38)) * ($G$18^$C38)) | J38: =IF($C38>J$29, "", $G$9 * ($G$17^(J$29-$C38)) * ($G$18^$C38)) | K38: =IF($C38>K$29, "", $G$9 * ($G$17^(K$29-$C38)) * ($G$18^$C38)) | ... CZ38: =IF($C38>CZ$29, "", $G$9 * ($G$17^(CZ$29-$C38)) * ($G$18^$C38)) -> 1570.2658
C39: 9 | D39: =IF($C39>D$29, "", $G$9 * ($G$17^(D$29-$C39)) * ($G$18^$C39)) | E39: =IF($C39>E$29, "", $G$9 * ($G$17^(E$29-$C39)) * ($G$18^$C39)) | F39: =IF($C39>F$29, "", $G$9 * ($G$17^(F$29-$C39)) * ($G$18^$C39)) | G39: =IF($C39>G$29, "", $G$9 * ($G$17^(G$29-$C39)) * ($G$18^$C39)) | H39: =IF($C39>H$29, "", $G$9 * ($G$17^(H$29-$C39)) * ($G$18^$C39)) | I39: =IF($C39>I$29, "", $G$9 * ($G$17^(I$29-$C39)) * ($G$18^$C39)) | J39: =IF($C39>J$29, "", $G$9 * ($G$17^(J$29-$C39)) * ($G$18^$C39)) | K39: =IF($C39>K$29, "", $G$9 * ($G$17^(K$29-$C39)) * ($G$18^$C39)) | ... CZ39: =IF($C39>CZ$29, "", $G$9 * ($G$17^(CZ$29-$C39)) * ($G$18^$C39)) -> 1502.7576
C40: 10 | D40: =IF($C40>D$29, "", $G$9 * ($G$17^(D$29-$C40)) * ($G$18^$C40)) | E40: =IF($C40>E$29, "", $G$9 * ($G$17^(E$29-$C40)) * ($G$18^$C40)) | F40: =IF($C40>F$29, "", $G$9 * ($G$17^(F$29-$C40)) * ($G$18^$C40)) | G40: =IF($C40>G$29, "", $G$9 * ($G$17^(G$29-$C40)) * ($G$18^$C40)) | H40: =IF($C40>H$29, "", $G$9 * ($G$17^(H$29-$C40)) * ($G$18^$C40)) | I40: =IF($C40>I$29, "", $G$9 * ($G$17^(I$29-$C40)) * ($G$18^$C40)) | J40: =IF($C40>J$29, "", $G$9 * ($G$17^(J$29-$C40)) * ($G$18^$C40)) | K40: =IF($C40>K$29, "", $G$9 * ($G$17^(K$29-$C40)) * ($G$18^$C40)) | ... CZ40: =IF($C40>CZ$29, "", $G$9 * ($G$17^(CZ$29-$C40)) * ($G$18^$C40)) -> 1438.1516
C41: 11 | D41: =IF($C41>D$29, "", $G$9 * ($G$17^(D$29-$C41)) * ($G$18^$C41)) | E41: =IF($C41>E$29, "", $G$9 * ($G$17^(E$29-$C41)) * ($G$18^$C41)) | F41: =IF($C41>F$29, "", $G$9 * ($G$17^(F$29-$C41)) * ($G$18^$C41)) | G41: =IF($C41>G$29, "", $G$9 * ($G$17^(G$29-$C41)) * ($G$18^$C41)) | H41: =IF($C41>H$29, "", $G$9 * ($G$17^(H$29-$C41)) * ($G$18^$C41)) | I41: =IF($C41>I$29, "", $G$9 * ($G$17^(I$29-$C41)) * ($G$18^$C41)) | J41: =IF($C41>J$29, "", $G$9 * ($G$17^(J$29-$C41)) * ($G$18^$C41)) | K41: =IF($C41>K$29, "", $G$9 * ($G$17^(K$29-$C41)) * ($G$18^$C41)) | ... CZ41: =IF($C41>CZ$29, "", $G$9 * ($G$17^(CZ$29-$C41)) * ($G$18^$C41)) -> 1376.3231
... C130: 100 | D130: =IF($C130>D$29, "", $G$9 * ($G$17^(D$29-$C130)) * ($G$18^$C130)) | E130: =IF($C130>E$29, "", $G$9 * ($G$17^(E$29-$C130)) * ($G$18^$C130)) | F130: =IF($C130>F$29, "", $G$9 * ($G$17^(F$29-$C130)) * ($G$18^$C130)) | G130: =IF($C130>G$29, "", $G$9 * ($G$17^(G$29-$C130)) * ($G$18^$C130)) | H130: =IF($C130>H$29, "", $G$9 * ($G$17^(H$29-$C130)) * ($G$18^$C130)) | I130: =IF($C130>I$29, "", $G$9 * ($G$17^(I$29-$C130)) * ($G$18^$C130)) | J130: =IF($C130>J$29, "", $G$9 * ($G$17^(J$29-$C130)) * ($G$18^$C130)) | K130: =IF($C130>K$29, "", $G$9 * ($G$17^(K$29-$C130)) * ($G$18^$C130)) | ... CZ130: =IF($C130>CZ$29, "", $G$9 * ($G$17^(CZ$29-$C130)) * ($G$18^$C130)) -> 27.55631
C134: European Call Option Price Tree
D135: 0 | E135: 1 | F135: 2 | G135: 3 | H135: 4 | I135: 5 | J135: 6 | K135: 7 | L135: 8 | M135: 9 | N135: 10 | O135: 11 | P135: 12 | Q135: 13 | R135: 14 | S135: 15 | T135: 16 | U135: 17 | V135: 18 | W135: 19 | X135: 20 | Y135: 21 | Z135: 22 | AA135: 23 | AB135: 24 | AC135: 25 | AD135: 26 | AE135: 27 | AF135: 28 | AG135: 29 | AH135: 30 | AI135: 31 | AJ135: 32 | AK135: 33 | AL135: 34 | AM135: 35 | AN135: 36 | AO135: 37 | AP135: 38 | AQ135: 39 | AR135: 40 | AS135: 41 | AT135: 42 | AU135: 43 | AV135: 44 | AW135: 45 | AX135: 46 | AY135: 47 | AZ135: 48 | BA135: 49 | BB135: 50 | BC135: 51 | BD135: 52 | BE135: 53 | BF135: 54 | BG135: 55 | BH135: 56 | BI135: 57 | BJ135: 58 | BK135: 59 | BL135: 60 | BM135: 61 | BN135: 62 | BO135: 63 | BP135: 64 | BQ135: 65 | BR135: 66 | BS135: 67 | BT135: 68 | BU135: 69 | BV135: 70 | BW135: 71 | BX135: 72 | BY135: 73 | BZ135: 74 | CA135: 75 | CB135: 76 | CC135: 77 | CD135: 78 | CE135: 79 | CF135: 80 | CG135: 81 | CH135: 82 | CI135: 83 | CJ135: 84 | CK135: 85 | CL135: 86 | CM135: 87 | CN135: 88 | CO135: 89 | CP135: 90 | CQ135: 91 | CR135: 92 | CS135: 93 | CT135: 94 | CU135: 95 | CV135: 96 | CW135: 97 | CX135: 98 | CY135: 99 | CZ135: 100
C136: 0 | D136: =IF($C136>D$135, "", IF(D$135=$G$15, MAX(D30-$G$20, 0), EXP(-$G$21*$G$16)*($G$19*E136+(1-$G$19)*E137))) -> 22.635424 | E136: =IF($C136>E$135, "", IF(E$135=$G$15, MAX(E30-$G$20, 0), EXP(-$G$21*$G$16)*($G$19*F136+(1-$G$19)*F137))) -> 25.689911 | F136: =IF($C136>F$135, "", IF(F$135=$G$15, MAX(F30-$G$20, 0), EXP(-$G$21*$G$16)*($G$19*G136+(1-$G$19)*G137))) -> 29.029832 | G136: =IF($C136>G$135, "", IF(G$135=$G$15, MAX(G30-$G$20, 0), EXP(-$G$21*$G$16)*($G$19*H136+(1-$G$19)*H137))) -> 32.663172 | H136: =IF($C136>H$135, "", IF(H$135=$G$15, MAX(H30-$G$20, 0), EXP(-$G$21*$G$16)*($G$19*I136+(1-$G$19)*I137))) -> 36.59587 | I136: =IF($C136>I$135, "", IF(I$135=$G$15, MAX(I30-$G$20, 0), EXP(-$G$21*$G$16)*($G$19*J136+(1-$G$19)*J137))) -> 40.831715 | J136: =IF($C136>J$135, "", IF(J$135=$G$15, MAX(J30-$G$20, 0), EXP(-$G$21*$G$16)*($G$19*K136+(1-$G$19)*K137))) -> 45.372324 | K136: =IF($C136>K$135, "", IF(K$135=$G$15, MAX(K30-$G$20, 0), EXP(-$G$21*$G$16)*($G$19*L136+(1-$G$19)*L137))) -> 50.217187 | ... CY136: =IF($C136>CY$135, "", IF(CY$135=$G$15, MAX(CY30-$G$20, 0), EXP(-$G$21*$G$16)*($G$19*CZ136+(1-$G$19)*CZ137))) -> 1933.2594 | CZ136: =IF($C136>CZ$135, "", IF(CZ$135=$G$15, MAX(CZ30-$G$20, 0), EXP(-$G$21*$G$16)*($G$19*#REF!+(1-$G$19)*#REF!))) -> 1981.7589
C137: 1 | D137: =IF($C137>D$135, "", IF(D$135=$G$15, MAX(D31-$G$20, 0), EXP(-$G$21*$G$16)*($G$19*E137+(1-$G$19)*E138))) | E137: =IF($C137>E$135, "", IF(E$135=$G$15, MAX(E31-$G$20, 0), EXP(-$G$21*$G$16)*($G$19*F137+(1-$G$19)*F138))) -> 19.610213 | F137: =IF($C137>F$135, "", IF(F$135=$G$15, MAX(F31-$G$20, 0), EXP(-$G$21*$G$16)*($G$19*G137+(1-$G$19)*G138))) -> 22.382353 | G137: =IF($C137>G$135, "", IF(G$135=$G$15, MAX(G31-$G$20, 0), EXP(-$G$21*$G$16)*($G$19*H137+(1-$G$19)*H138))) -> 25.432101 | H137: =IF($C137>H$135, "", IF(H$135=$G$15, MAX(H31-$G$20, 0), EXP(-$G$21*$G$16)*($G$19*I137+(1-$G$19)*I138))) -> 28.769482 | I137: =IF($C137>I$135, "", IF(I$135=$G$15, MAX(I31-$G$20, 0), EXP(-$G$21*$G$16)*($G$19*J137+(1-$G$19)*J138))) -> 32.402567 | J137: =IF($C137>J$135, "", IF(J$135=$G$15, MAX(J31-$G$20, 0), EXP(-$G$21*$G$16)*($G$19*K137+(1-$G$19)*K138))) -> 36.337306 | K137: =IF($C137>K$135, "", IF(K$135=$G$15, MAX(K31-$G$20, 0), EXP(-$G$21*$G$16)*($G$19*L137+(1-$G$19)*L138))) -> 40.577432 | ... CY137: =IF($C137>CY$135, "", IF(CY$135=$G$15, MAX(CY31-$G$20, 0), EXP(-$G$21*$G$16)*($G$19*CZ137+(1-$G$19)*CZ138))) -> 1839.3995 | CZ137: =IF($C137>CZ$135, "", IF(CZ$135=$G$15, MAX(CZ31-$G$20, 0), EXP(-$G$21*$G$16)*($G$19*#REF!+(1-$G$19)*#REF!))) -> 1885.812
C138: 2 | D138: =IF($C138>D$135, "", IF(D$135=$G$15, MAX(D32-$G$20, 0), EXP(-$G$21*$G$16)*($G$19*E138+(1-$G$19)*E139))) | E138: =IF($C138>E$135, "", IF(E$135=$G$15, MAX(E32-$G$20, 0), EXP(-$G$21*$G$16)*($G$19*F138+(1-$G$19)*F139))) | F138: =IF($C138>F$135, "", IF(F$135=$G$15, MAX(F32-$G$20, 0), EXP(-$G$21*$G$16)*($G$19*G138+(1-$G$19)*G139))) -> 16.864295 | G138: =IF($C138>G$135, "", IF(G$135=$G$15, MAX(G32-$G$20, 0), EXP(-$G$21*$G$16)*($G$19*H138+(1-$G$19)*H139))) -> 19.361755 | H138: =IF($C138>H$135, "", IF(H$135=$G$15, MAX(H32-$G$20, 0), EXP(-$G$21*$G$16)*($G$19*I138+(1-$G$19)*I139))) -> 22.126969 | I138: =IF($C138>I$135, "", IF(I$135=$G$15, MAX(I32-$G$20, 0), EXP(-$G$21*$G$16)*($G$19*J138+(1-$G$19)*J139))) -> 25.171908 | J138: =IF($C138>J$135, "", IF(J$135=$G$15, MAX(J32-$G$20, 0), EXP(-$G$21*$G$16)*($G$19*K138+(1-$G$19)*K139))) -> 28.506752 | K138: =IF($C138>K$135, "", IF(K$135=$G$15, MAX(K32-$G$20, 0), EXP(-$G$21*$G$16)*($G$19*L138+(1-$G$19)*L139))) -> 32.139655 | ... CY138: =IF($C138>CY$135, "", IF(CY$135=$G$15, MAX(CY32-$G$20, 0), EXP(-$G$21*$G$16)*($G$19*CZ138+(1-$G$19)*CZ139))) -> 1749.5749 | CZ138: =IF($C138>CZ$135, "", IF(CZ$135=$G$15, MAX(CZ32-$G$20, 0), EXP(-$G$21*$G$16)*($G$19*#REF!+(1-$G$19)*#REF!))) -> 1793.99
C139: 3 | D139: =IF($C139>D$135, "", IF(D$135=$G$15, MAX(D33-$G$20, 0), EXP(-$G$21*$G$16)*($G$19*E139+(1-$G$19)*E140))) | E139: =IF($C139>E$135, "", IF(E$135=$G$15, MAX(E33-$G$20, 0), EXP(-$G$21*$G$16)*($G$19*F139+(1-$G$19)*F140))) | F139: =IF($C139>F$135, "", IF(F$135=$G$15, MAX(F33-$G$20, 0), EXP(-$G$21*$G$16)*($G$19*G139+(1-$G$19)*G140))) | G139: =IF($C139>G$135, "", IF(G$135=$G$15, MAX(G33-$G$20, 0), EXP(-$G$21*$G$16)*($G$19*H139+(1-$G$19)*H140))) -> 14.390159 | H139: =IF($C139>H$135, "", IF(H$135=$G$15, MAX(H33-$G$20, 0), EXP(-$G$21*$G$16)*($G$19*I139+(1-$G$19)*I140))) -> 16.622624 | I139: =IF($C139>I$135, "", IF(I$135=$G$15, MAX(I33-$G$20, 0), EXP(-$G$21*$G$16)*($G$19*J139+(1-$G$19)*J140))) -> 19.111051 | J139: =IF($C139>J$135, "", IF(J$135=$G$15, MAX(J33-$G$20, 0), EXP(-$G$21*$G$16)*($G$19*K139+(1-$G$19)*K140))) -> 21.8692 | K139: =IF($C139>K$135, "", IF(K$135=$G$15, MAX(K33-$G$20, 0), EXP(-$G$21*$G$16)*($G$19*L139+(1-$G$19)*L140))) -> 24.90926 | ... CY139: =IF($C139>CY$135, "", IF(CY$135=$G$15, MAX(CY33-$G$20, 0), EXP(-$G$21*$G$16)*($G$19*CZ139+(1-$G$19)*CZ140))) -> 1663.6119 | CZ139: =IF($C139>CZ$135, "", IF(CZ$135=$G$15, MAX(CZ33-$G$20, 0), EXP(-$G$21*$G$16)*($G$19*#REF!+(1-$G$19)*#REF!))) -> 1706.1155
C140: 4 | D140: =IF($C140>D$135, "", IF(D$135=$G$15, MAX(D34-$G$20, 0), EXP(-$G$21*$G$16)*($G$19*E140+(1-$G$19)*E141))) | E140: =IF($C140>E$135, "", IF(E$135=$G$15, MAX(E34-$G$20, 0), EXP(-$G$21*$G$16)*($G$19*F140+(1-$G$19)*F141))) | F140: =IF($C140>F$135, "", IF(F$135=$G$15, MAX(F34-$G$20, 0), EXP(-$G$21*$G$16)*($G$19*G140+(1-$G$19)*G141))) | G140: =IF($C140>G$135, "", IF(G$135=$G$15, MAX(G34-$G$20, 0), EXP(-$G$21*$G$16)*($G$19*H140+(1-$G$19)*H141))) | H140: =IF($C140>H$135, "", IF(H$135=$G$15, MAX(H34-$G$20, 0), EXP(-$G$21*$G$16)*($G$19*I140+(1-$G$19)*I141))) -> 12.178289 | I140: =IF($C140>I$135, "", IF(I$135=$G$15, MAX(I34-$G$20, 0), EXP(-$G$21*$G$16)*($G$19*J140+(1-$G$19)*J141))) -> 14.157369 | J140: =IF($C140>J$135, "", IF(J$135=$G$15, MAX(J34-$G$20, 0), EXP(-$G$21*$G$16)*($G$19*K140+(1-$G$19)*K141))) -> 16.378842 | K140: =IF($C140>K$135, "", IF(K$135=$G$15, MAX(K34-$G$20, 0), EXP(-$G$21*$G$16)*($G$19*L140+(1-$G$19)*L141))) -> 18.858032 | ... CY140: =IF($C140>CY$135, "", IF(CY$135=$G$15, MAX(CY34-$G$20, 0), EXP(-$G$21*$G$16)*($G$19*CZ140+(1-$G$19)*CZ141))) -> 1581.3446 | CZ140: =IF($C140>CZ$135, "", IF(CZ$135=$G$15, MAX(CZ34-$G$20, 0), EXP(-$G$21*$G$16)*($G$19*#REF!+(1-$G$19)*#REF!))) -> 1622.0189
C141: 5 | D141: =IF($C141>D$135, "", IF(D$135=$G$15, MAX(D35-$G$20, 0), EXP(-$G$21*$G$16)*($G$19*E141+(1-$G$19)*E142))) | E141: =IF($C141>E$135, "", IF(E$135=$G$15, MAX(E35-$G$20, 0), EXP(-$G$21*$G$16)*($G$19*F141+(1-$G$19)*F142))) | F141: =IF($C141>F$135, "", IF(F$135=$G$15, MAX(F35-$G$20, 0), EXP(-$G$21*$G$16)*($G$19*G141+(1-$G$19)*G142))) | G141: =IF($C141>G$135, "", IF(G$135=$G$15, MAX(G35-$G$20, 0), EXP(-$G$21*$G$16)*($G$19*H141+(1-$G$19)*H142))) | H141: =IF($C141>H$135, "", IF(H$135=$G$15, MAX(H35-$G$20, 0), EXP(-$G$21*$G$16)*($G$19*I141+(1-$G$19)*I142))) | I141: =IF($C141>I$135, "", IF(I$135=$G$15, MAX(I35-$G$20, 0), EXP(-$G$21*$G$16)*($G$19*J141+(1-$G$19)*J142))) -> 10.217249 | J141: =IF($C141>J$135, "", IF(J$135=$G$15, MAX(J35-$G$20, 0), EXP(-$G$21*$G$16)*($G$19*K141+(1-$G$19)*K142))) -> 11.956328 | K141: =IF($C141>K$135, "", IF(K$135=$G$15, MAX(K35-$G$20, 0), EXP(-$G$21*$G$16)*($G$19*L141+(1-$G$19)*L142))) -> 13.922671 | ... CY141: =IF($C141>CY$135, "", IF(CY$135=$G$15, MAX(CY35-$G$20, 0), EXP(-$G$21*$G$16)*($G$19*CZ141+(1-$G$19)*CZ142))) -> 1502.6141 | CZ141: =IF($C141>CZ$135, "", IF(CZ$135=$G$15, MAX(CZ35-$G$20, 0), EXP(-$G$21*$G$16)*($G$19*#REF!+(1-$G$19)*#REF!))) -> 1541.5378
C142: 6 | D142: =IF($C142>D$135, "", IF(D$135=$G$15, MAX(D36-$G$20, 0), EXP(-$G$21*$G$16)*($G$19*E142+(1-$G$19)*E143))) | E142: =IF($C142>E$135, "", IF(E$135=$G$15, MAX(E36-$G$20, 0), EXP(-$G$21*$G$16)*($G$19*F142+(1-$G$19)*F143))) | F142: =IF($C142>F$135, "", IF(F$135=$G$15, MAX(F36-$G$20, 0), EXP(-$G$21*$G$16)*($G$19*G142+(1-$G$19)*G143))) | G142: =IF($C142>G$135, "", IF(G$135=$G$15, MAX(G36-$G$20, 0), EXP(-$G$21*$G$16)*($G$19*H142+(1-$G$19)*H143))) | H142: =IF($C142>H$135, "", IF(H$135=$G$15, MAX(H36-$G$20, 0), EXP(-$G$21*$G$16)*($G$19*I142+(1-$G$19)*I143))) | I142: =IF($C142>I$135, "", IF(I$135=$G$15, MAX(I36-$G$20, 0), EXP(-$G$21*$G$16)*($G$19*J142+(1-$G$19)*J143))) | J142: =IF($C142>J$135, "", IF(J$135=$G$15, MAX(J36-$G$20, 0), EXP(-$G$21*$G$16)*($G$19*K142+(1-$G$19)*K143))) -> 8.4938416 | K142: =IF($C142>K$135, "", IF(K$135=$G$15, MAX(K36-$G$20, 0), EXP(-$G$21*$G$16)*($G$19*L142+(1-$G$19)*L143))) -> 10.007857 | ... CY142: =IF($C142>CY$135, "", IF(CY$135=$G$15, MAX(CY36-$G$20, 0), EXP(-$G$21*$G$16)*($G$19*CZ142+(1-$G$19)*CZ143))) -> 1427.2684 | CZ142: =IF($C142>CZ$135, "", IF(CZ$135=$G$15, MAX(CZ36-$G$20, 0), EXP(-$G$21*$G$16)*($G$19*#REF!+(1-$G$19)*#REF!))) -> 1464.5167
C143: 7 | D143: =IF($C143>D$135, "", IF(D$135=$G$15, MAX(D37-$G$20, 0), EXP(-$G$21*$G$16)*($G$19*E143+(1-$G$19)*E144))) | E143: =IF($C143>E$135, "", IF(E$135=$G$15, MAX(E37-$G$20, 0), EXP(-$G$21*$G$16)*($G$19*F143+(1-$G$19)*F144))) | F143: =IF($C143>F$135, "", IF(F$135=$G$15, MAX(F37-$G$20, 0), EXP(-$G$21*$G$16)*($G$19*G143+(1-$G$19)*G144))) | G143: =IF($C143>G$135, "", IF(G$135=$G$15, MAX(G37-$G$20, 0), EXP(-$G$21*$G$16)*($G$19*H143+(1-$G$19)*H144))) | H143: =IF($C143>H$135, "", IF(H$135=$G$15, MAX(H37-$G$20, 0), EXP(-$G$21*$G$16)*($G$19*I143+(1-$G$19)*I144))) | I143: =IF($C143>I$135, "", IF(I$135=$G$15, MAX(I37-$G$20, 0), EXP(-$G$21*$G$16)*($G$19*J143+(1-$G$19)*J144))) | J143: =IF($C143>J$135, "", IF(J$135=$G$15, MAX(J37-$G$20, 0), EXP(-$G$21*$G$16)*($G$19*K143+(1-$G$19)*K144))) | K143: =IF($C143>K$135, "", IF(K$135=$G$15, MAX(K37-$G$20, 0), EXP(-$G$21*$G$16)*($G$19*L143+(1-$G$19)*L144))) -> 6.9933206 | ... CY143: =IF($C143>CY$135, "", IF(CY$135=$G$15, MAX(CY37-$G$20, 0), EXP(-$G$21*$G$16)*($G$19*CZ143+(1-$G$19)*CZ144))) -> 1355.1619 | CZ143: =IF($C143>CZ$135, "", IF(CZ$135=$G$15, MAX(CZ37-$G$20, 0), EXP(-$G$21*$G$16)*($G$19*#REF!+(1-$G$19)*#REF!))) -> 1390.8068
C144: 8 | D144: =IF($C144>D$135, "", IF(D$135=$G$15, MAX(D38-$G$20, 0), EXP(-$G$21*$G$16)*($G$19*E144+(1-$G$19)*E145))) | E144: =IF($C144>E$135, "", IF(E$135=$G$15, MAX(E38-$G$20, 0), EXP(-$G$21*$G$16)*($G$19*F144+(1-$G$19)*F145))) | F144: =IF($C144>F$135, "", IF(F$135=$G$15, MAX(F38-$G$20, 0), EXP(-$G$21*$G$16)*($G$19*G144+(1-$G$19)*G145))) | G144: =IF($C144>G$135, "", IF(G$135=$G$15, MAX(G38-$G$20, 0), EXP(-$G$21*$G$16)*($G$19*H144+(1-$G$19)*H145))) | H144: =IF($C144>H$135, "", IF(H$135=$G$15, MAX(H38-$G$20, 0), EXP(-$G$21*$G$16)*($G$19*I144+(1-$G$19)*I145))) | I144: =IF($C144>I$135, "", IF(I$135=$G$15, MAX(I38-$G$20, 0), EXP(-$G$21*$G$16)*($G$19*J144+(1-$G$19)*J145))) | J144: =IF($C144>J$135, "", IF(J$135=$G$15, MAX(J38-$G$20, 0), EXP(-$G$21*$G$16)*($G$19*K144+(1-$G$19)*K145))) | K144: =IF($C144>K$135, "", IF(K$135=$G$15, MAX(K38-$G$20, 0), EXP(-$G$21*$G$16)*($G$19*L144+(1-$G$19)*L145))) | ... CY144: =IF($C144>CY$135, "", IF(CY$135=$G$15, MAX(CY38-$G$20, 0), EXP(-$G$21*$G$16)*($G$19*CZ144+(1-$G$19)*CZ145))) -> 1286.1554 | CZ144: =IF($C144>CZ$135, "", IF(CZ$135=$G$15, MAX(CZ38-$G$20, 0), EXP(-$G$21*$G$16)*($G$19*#REF!+(1-$G$19)*#REF!))) -> 1320.2658
C145: 9 | D145: =IF($C145>D$135, "", IF(D$135=$G$15, MAX(D39-$G$20, 0), EXP(-$G$21*$G$16)*($G$19*E145+(1-$G$19)*E146))) | E145: =IF($C145>E$135, "", IF(E$135=$G$15, MAX(E39-$G$20, 0), EXP(-$G$21*$G$16)*($G$19*F145+(1-$G$19)*F146))) | F145: =IF($C145>F$135, "", IF(F$135=$G$15, MAX(F39-$G$20, 0), EXP(-$G$21*$G$16)*($G$19*G145+(1-$G$19)*G146))) | G145: =IF($C145>G$135, "", IF(G$135=$G$15, MAX(G39-$G$20, 0), EXP(-$G$21*$G$16)*($G$19*H145+(1-$G$19)*H146))) | H145: =IF($C145>H$135, "", IF(H$135=$G$15, MAX(H39-$G$20, 0), EXP(-$G$21*$G$16)*($G$19*I145+(1-$G$19)*I146))) | I145: =IF($C145>I$135, "", IF(I$135=$G$15, MAX(I39-$G$20, 0), EXP(-$G$21*$G$16)*($G$19*J145+(1-$G$19)*J146))) | J145: =IF($C145>J$135, "", IF(J$135=$G$15, MAX(J39-$G$20, 0), EXP(-$G$21*$G$16)*($G$19*K145+(1-$G$19)*K146))) | K145: =IF($C145>K$135, "", IF(K$135=$G$15, MAX(K39-$G$20, 0), EXP(-$G$21*$G$16)*($G$19*L145+(1-$G$19)*L146))) | ... CY145: =IF($C145>CY$135, "", IF(CY$135=$G$15, MAX(CY39-$G$20, 0), EXP(-$G$21*$G$16)*($G$19*CZ145+(1-$G$19)*CZ146))) -> 1220.1156 | CZ145: =IF($C145>CZ$135, "", IF(CZ$135=$G$15, MAX(CZ39-$G$20, 0), EXP(-$G$21*$G$16)*($G$19*#REF!+(1-$G$19)*#REF!))) -> 1252.7576
C146: 10 | D146: =IF($C146>D$135, "", IF(D$135=$G$15, MAX(D40-$G$20, 0), EXP(-$G$21*$G$16)*($G$19*E146+(1-$G$19)*E147))) | E146: =IF($C146>E$135, "", IF(E$135=$G$15, MAX(E40-$G$20, 0), EXP(-$G$21*$G$16)*($G$19*F146+(1-$G$19)*F147))) | F146: =IF($C146>F$135, "", IF(F$135=$G$15, MAX(F40-$G$20, 0), EXP(-$G$21*$G$16)*($G$19*G146+(1-$G$19)*G147))) | G146: =IF($C146>G$135, "", IF(G$135=$G$15, MAX(G40-$G$20, 0), EXP(-$G$21*$G$16)*($G$19*H146+(1-$G$19)*H147))) | H146: =IF($C146>H$135, "", IF(H$135=$G$15, MAX(H40-$G$20, 0), EXP(-$G$21*$G$16)*($G$19*I146+(1-$G$19)*I147))) | I146: =IF($C146>I$135, "", IF(I$135=$G$15, MAX(I40-$G$20, 0), EXP(-$G$21*$G$16)*($G$19*J146+(1-$G$19)*J147))) | J146: =IF($C146>J$135, "", IF(J$135=$G$15, MAX(J40-$G$20, 0), EXP(-$G$21*$G$16)*($G$19*K146+(1-$G$19)*K147))) | K146: =IF($C146>K$135, "", IF(K$135=$G$15, MAX(K40-$G$20, 0), EXP(-$G$21*$G$16)*($G$19*L146+(1-$G$19)*L147))) | ... CY146: =IF($C146>CY$135, "", IF(CY$135=$G$15, MAX(CY40-$G$20, 0), EXP(-$G$21*$G$16)*($G$19*CZ146+(1-$G$19)*CZ147))) -> 1156.915 | CZ146: =IF($C146>CZ$135, "", IF(CZ$135=$G$15, MAX(CZ40-$G$20, 0), EXP(-$G$21*$G$16)*($G$19*#REF!+(1-$G$19)*#REF!))) -> 1188.1516
C147: 11 | D147: =IF($C147>D$135, "", IF(D$135=$G$15, MAX(D41-$G$20, 0), EXP(-$G$21*$G$16)*($G$19*E147+(1-$G$19)*E148))) | E147: =IF($C147>E$135, "", IF(E$135=$G$15, MAX(E41-$G$20, 0), EXP(-$G$21*$G$16)*($G$19*F147+(1-$G$19)*F148))) | F147: =IF($C147>F$135, "", IF(F$135=$G$15, MAX(F41-$G$20, 0), EXP(-$G$21*$G$16)*($G$19*G147+(1-$G$19)*G148))) | G147: =IF($C147>G$135, "", IF(G$135=$G$15, MAX(G41-$G$20, 0), EXP(-$G$21*$G$16)*($G$19*H147+(1-$G$19)*H148))) | H147: =IF($C147>H$135, "", IF(H$135=$G$15, MAX(H41-$G$20, 0), EXP(-$G$21*$G$16)*($G$19*I147+(1-$G$19)*I148))) | I147: =IF($C147>I$135, "", IF(I$135=$G$15, MAX(I41-$G$20, 0), EXP(-$G$21*$G$16)*($G$19*J147+(1-$G$19)*J148))) | J147: =IF($C147>J$135, "", IF(J$135=$G$15, MAX(J41-$G$20, 0), EXP(-$G$21*$G$16)*($G$19*K147+(1-$G$19)*K148))) | K147: =IF($C147>K$135, "", IF(K$135=$G$15, MAX(K41-$G$20, 0), EXP(-$G$21*$G$16)*($G$19*L147+(1-$G$19)*L148))) | ... CY147: =IF($C147>CY$135, "", IF(CY$135=$G$15, MAX(CY41-$G$20, 0), EXP(-$G$21*$G$16)*($G$19*CZ147+(1-$G$19)*CZ148))) -> 1096.4314 | CZ147: =IF($C147>CZ$135, "", IF(CZ$135=$G$15, MAX(CZ41-$G$20, 0), EXP(-$G$21*$G$16)*($G$19*#REF!+(1-$G$19)*#REF!))) -> 1126.3231
... C235: 99 | D235: =IF($C235>D$135, "", IF(D$135=$G$15, MAX(D129-$G$20, 0), EXP(-$G$21*$G$16)*($G$19*E235+(1-$G$19)*E236))) | E235: =IF($C235>E$135, "", IF(E$135=$G$15, MAX(E129-$G$20, 0), EXP(-$G$21*$G$16)*($G$19*F235+(1-$G$19)*F236))) | F235: =IF($C235>F$135, "", IF(F$135=$G$15, MAX(F129-$G$20, 0), EXP(-$G$21*$G$16)*($G$19*G235+(1-$G$19)*G236))) | G235: =IF($C235>G$135, "", IF(G$135=$G$15, MAX(G129-$G$20, 0), EXP(-$G$21*$G$16)*($G$19*H235+(1-$G$19)*H236))) | H235: =IF($C235>H$135, "", IF(H$135=$G$15, MAX(H129-$G$20, 0), EXP(-$G$21*$G$16)*($G$19*I235+(1-$G$19)*I236))) | I235: =IF($C235>I$135, "", IF(I$135=$G$15, MAX(I129-$G$20, 0), EXP(-$G$21*$G$16)*($G$19*J235+(1-$G$19)*J236))) | J235: =IF($C235>J$135, "", IF(J$135=$G$15, MAX(J129-$G$20, 0), EXP(-$G$21*$G$16)*($G$19*K235+(1-$G$19)*K236))) | K235: =IF($C235>K$135, "", IF(K$135=$G$15, MAX(K129-$G$20, 0), EXP(-$G$21*$G$16)*($G$19*L235+(1-$G$19)*L236))) | ... CY235: =IF($C235>CY$135, "", IF(CY$135=$G$15, MAX(CY129-$G$20, 0), EXP(-$G$21*$G$16)*($G$19*CZ235+(1-$G$19)*CZ236))) -> 0 | CZ235: =IF($C235>CZ$135, "", IF(CZ$135=$G$15, MAX(CZ129-$G$20, 0), EXP(-$G$21*$G$16)*($G$19*#REF!+(1-$G$19)*#REF!))) -> 0
C236: 100 | D236: =IF($C236>D$135, "", IF(D$135=$G$15, MAX(D130-$G$20, 0), EXP(-$G$21*$G$16)*($G$19*E236+(1-$G$19)*#REF!))) | E236: =IF($C236>E$135, "", IF(E$135=$G$15, MAX(E130-$G$20, 0), EXP(-$G$21*$G$16)*($G$19*F236+(1-$G$19)*N238))) | F236: =IF($C236>F$135, "", IF(F$135=$G$15, MAX(F130-$G$20, 0), EXP(-$G$21*$G$16)*($G$19*G236+(1-$G$19)*O238))) | G236: =IF($C236>G$135, "", IF(G$135=$G$15, MAX(G130-$G$20, 0), EXP(-$G$21*$G$16)*($G$19*H236+(1-$G$19)*P238))) | H236: =IF($C236>H$135, "", IF(H$135=$G$15, MAX(H130-$G$20, 0), EXP(-$G$21*$G$16)*($G$19*I236+(1-$G$19)*Q238))) | I236: =IF($C236>I$135, "", IF(I$135=$G$15, MAX(I130-$G$20, 0), EXP(-$G$21*$G$16)*($G$19*J236+(1-$G$19)*R238))) | J236: =IF($C236>J$135, "", IF(J$135=$G$15, MAX(J130-$G$20, 0), EXP(-$G$21*$G$16)*($G$19*K236+(1-$G$19)*S238))) | K236: =IF($C236>K$135, "", IF(K$135=$G$15, MAX(K130-$G$20, 0), EXP(-$G$21*$G$16)*($G$19*L236+(1-$G$19)*T238))) | L236: =IF($C236>L$135, "", IF(L$135=$G$15, MAX(L130-$G$20, 0), EXP(-$G$21*$G$16)*($G$19*M236+(1-$G$19)*U238))) | ... CY236: =IF($C236>CY$135, "", IF(CY$135=$G$15, MAX(CY130-$G$20, 0), EXP(-$G$21*$G$16)*($G$19*CZ236+(1-$G$19)*DH238))) | CZ236: =IF($C236>CZ$135, "", IF(CZ$135=$G$15, MAX(CZ130-$G$20, 0), EXP(-$G$21*$G$16)*($G$19*#REF!+(1-$G$19)*DI238))) -> 0

Sheet Monte Carlo
C3: Method 3: Monte Carlo
C5: Input Assumptions | J5: Notes
C6: Ticker | H6: AAPL
C7: Option | H7: European-style vanilla call
C8: Valuation Date | H8: ='[1]Historical Prices'!B4 -> 46101
C9: Stock price at time0 | G9: S0 | H9: ='BSM Model'!E9 -> 247.99 | J9: Bloomberg spot price
C10: Volatility: Choose source | H10: Implied volatility
C11: Implied volatility | H11: ='Option Monitor'!F7/100 -> 0.31072491 | J11: Bloomberg implied volatility
C12: Historical volatility | H12: ='Historical Prices'!F9 -> 0.22560599 | J12: 180-day annualized historical
C13: Active volatility | G13: σ | H13: =IF(H10="Implied volatility", H11, H12) -> 0.31072491
C14: Total lifetime in years | G14: T | H14: ='BSM Model'!E15 -> 0.5
C15: Number of trials | G15: N | H15: 10000
C16: Strike price | G16: K | H16: ='Option Monitor'!H7 -> 250
C17: Risk-free rate | G17: r | H17: ='Risk-Free Rate'!C2/100 -> 0.037438 | J17: USGG6M INDEX
C18: Dividend yield | G18: q | H18: ='Dividend Yield'!B2 -> 0.0042 | J18: Indicated yield
C20: Call Option Price | H20: =IF(H10="Implied volatility", K25, K26) -> 22.594179
C23: 10,000-Iteration Simulation Matrix
C24: Trial | D24: Random Shock Z | E24: Simulated ST (Implied Vol) | F24: Simulated ST (Historical Vol) | G24: Payoff (Implied Vol) | H24: Payoff (Historical Vol)
C25: 1 | D25: =_xlfn.NORM.S.INV(RAND()) -> -0.67016765 | E25: =$H$9 * EXP(($H$17 - $H$18 - ($H$11^2)/2)*$H$14 + $H$11*SQRT($H$14)*D25) -> 212.43235 | F25: =$H$9 * EXP(($H$17 - $H$18 - ($H$12^2)/2)*$H$14 + $H$12*SQRT($H$14)*D25) -> 223.71495 | G25: =MAX(E25-$H$16, 0) -> 0 | H25: =MAX(F25-$H$16, 0) -> 0 | J25: Call Option Price (Implied Vol) | K25: =AVERAGE(G25:G10024) * EXP(-H17*H14) -> 22.594179
C26: 2 | D26: =_xlfn.NORM.S.INV(RAND()) -> -0.58563596 | E26: =$H$9 * EXP(($H$17 - $H$18 - ($H$11^2)/2)*$H$14 + $H$11*SQRT($H$14)*D26) -> 216.41471 | F26: =$H$9 * EXP(($H$17 - $H$18 - ($H$12^2)/2)*$H$14 + $H$12*SQRT($H$14)*D26) -> 226.75221 | G26: =MAX(E26-$H$16, 0) -> 0 | H26: =MAX(F26-$H$16, 0) -> 0 | J26: Call Option Price (Historical Vol) | K26: =AVERAGE(H25:H10024) * EXP(-H17*H14) -> 16.711456
C27: 3 | D27: =_xlfn.NORM.S.INV(RAND()) -> -0.43298283 | E27: =$H$9 * EXP(($H$17 - $H$18 - ($H$11^2)/2)*$H$14 + $H$11*SQRT($H$14)*D27) -> 223.79642 | F27: =$H$9 * EXP(($H$17 - $H$18 - ($H$12^2)/2)*$H$14 + $H$12*SQRT($H$14)*D27) -> 232.34195 | G27: =MAX(E27-$H$16, 0) -> 0 | H27: =MAX(F27-$H$16, 0) -> 0
C28: 4 | D28: =_xlfn.NORM.S.INV(RAND()) -> 0.6643077 | E28: =$H$9 * EXP(($H$17 - $H$18 - ($H$11^2)/2)*$H$14 + $H$11*SQRT($H$14)*D28) -> 284.81184 | F28: =$H$9 * EXP(($H$17 - $H$18 - ($H$12^2)/2)*$H$14 + $H$12*SQRT($H$14)*D28) -> 276.78977 | G28: =MAX(E28-$H$16, 0) -> 34.811841 | H28: =MAX(F28-$H$16, 0) -> 26.789772
C29: 5 | D29: =_xlfn.NORM.S.INV(RAND()) -> 1.2571514 | E29: =$H$9 * EXP(($H$17 - $H$18 - ($H$11^2)/2)*$H$14 + $H$11*SQRT($H$14)*D29) -> 324.4352 | F29: =$H$9 * EXP(($H$17 - $H$18 - ($H$12^2)/2)*$H$14 + $H$12*SQRT($H$14)*D29) -> 304.24496 | G29: =MAX(E29-$H$16, 0) -> 74.435195 | H29: =MAX(F29-$H$16, 0) -> 54.244957
C30: 6 | D30: =_xlfn.NORM.S.INV(RAND()) -> 0.96479238 | E30: =$H$9 * EXP(($H$17 - $H$18 - ($H$11^2)/2)*$H$14 + $H$11*SQRT($H$14)*D30) -> 304.25007 | F30: =$H$9 * EXP(($H$17 - $H$18 - ($H$12^2)/2)*$H$14 + $H$12*SQRT($H$14)*D30) -> 290.381 | G30: =MAX(E30-$H$16, 0) -> 54.250067 | H30: =MAX(F30-$H$16, 0) -> 40.380999
C31: 7 | D31: =_xlfn.NORM.S.INV(RAND()) -> 0.0084537535 | E31: =$H$9 * EXP(($H$17 - $H$18 - ($H$11^2)/2)*$H$14 + $H$11*SQRT($H$14)*D31) -> 246.59008 | F31: =$H$9 * EXP(($H$17 - $H$18 - ($H$12^2)/2)*$H$14 + $H$12*SQRT($H$14)*D31) -> 249.29365 | G31: =MAX(E31-$H$16, 0) -> 0 | H31: =MAX(F31-$H$16, 0) -> 0
C32: 8 | D32: =_xlfn.NORM.S.INV(RAND()) -> -0.79629017 | E32: =$H$9 * EXP(($H$17 - $H$18 - ($H$11^2)/2)*$H$14 + $H$11*SQRT($H$14)*D32) -> 206.62643 | F32: =$H$9 * EXP(($H$17 - $H$18 - ($H$12^2)/2)*$H$14 + $H$12*SQRT($H$14)*D32) -> 219.25879 | G32: =MAX(E32-$H$16, 0) -> 0 | H32: =MAX(F32-$H$16, 0) -> 0
C33: 9 | D33: =_xlfn.NORM.S.INV(RAND()) -> -0.1291601 | E33: =$H$9 * EXP(($H$17 - $H$18 - ($H$11^2)/2)*$H$14 + $H$11*SQRT($H$14)*D33) -> 239.24579 | F33: =$H$9 * EXP(($H$17 - $H$18 - ($H$12^2)/2)*$H$14 + $H$12*SQRT($H$14)*D33) -> 243.88049 | G33: =MAX(E33-$H$16, 0) -> 0 | H33: =MAX(F33-$H$16, 0) -> 0
C34: 10 | D34: =_xlfn.NORM.S.INV(RAND()) -> 0.41940644 | E34: =$H$9 * EXP(($H$17 - $H$18 - ($H$11^2)/2)*$H$14 + $H$11*SQRT($H$14)*D34) -> 269.89152 | F34: =$H$9 * EXP(($H$17 - $H$18 - ($H$12^2)/2)*$H$14 + $H$12*SQRT($H$14)*D34) -> 266.18453 | G34: =MAX(E34-$H$16, 0) -> 19.891521 | H34: =MAX(F34-$H$16, 0) -> 16.184527
C35: 11 | D35: =_xlfn.NORM.S.INV(RAND()) -> 0.96087406 | E35: =$H$9 * EXP(($H$17 - $H$18 - ($H$11^2)/2)*$H$14 + $H$11*SQRT($H$14)*D35) -> 303.98825 | F35: =$H$9 * EXP(($H$17 - $H$18 - ($H$12^2)/2)*$H$14 + $H$12*SQRT($H$14)*D35) -> 290.19954 | G35: =MAX(E35-$H$16, 0) -> 53.988246 | H35: =MAX(F35-$H$16, 0) -> 40.199545
C36: 12 | D36: =_xlfn.NORM.S.INV(RAND()) -> -1.7807322 | E36: =$H$9 * EXP(($H$17 - $H$18 - ($H$11^2)/2)*$H$14 + $H$11*SQRT($H$14)*D36) -> 166.43671 | F36: =$H$9 * EXP(($H$17 - $H$18 - ($H$12^2)/2)*$H$14 + $H$12*SQRT($H$14)*D36) -> 187.39283 | G36: =MAX(E36-$H$16, 0) -> 0 | H36: =MAX(F36-$H$16, 0) -> 0
C37: 13 | D37: =_xlfn.NORM.S.INV(RAND()) -> 1.8674018 | E37: =$H$9 * EXP(($H$17 - $H$18 - ($H$11^2)/2)*$H$14 + $H$11*SQRT($H$14)*D37) -> 370.98714 | F37: =$H$9 * EXP(($H$17 - $H$18 - ($H$12^2)/2)*$H$14 + $H$12*SQRT($H$14)*D37) -> 335.3534 | G37: =MAX(E37-$H$16, 0) -> 120.98714 | H37: =MAX(F37-$H$16, 0) -> 85.3534
C38: 14 | D38: =_xlfn.NORM.S.INV(RAND()) -> 0.29151003 | E38: =$H$9 * EXP(($H$17 - $H$18 - ($H$11^2)/2)*$H$14 + $H$11*SQRT($H$14)*D38) -> 262.41291 | F38: =$H$9 * EXP(($H$17 - $H$18 - ($H$12^2)/2)*$H$14 + $H$12*SQRT($H$14)*D38) -> 260.80859 | G38: =MAX(E38-$H$16, 0) -> 12.412911 | H38: =MAX(F38-$H$16, 0) -> 10.808594
... C10024: 10000 | D10024: =_xlfn.NORM.S.INV(RAND()) -> -1.1993042 | E10024: =$H$9 * EXP(($H$17 - $H$18 - ($H$11^2)/2)*$H$14 + $H$11*SQRT($H$14)*D10024) -> 189.11664 | F10024: =$H$9 * EXP(($H$17 - $H$18 - ($H$12^2)/2)*$H$14 + $H$12*SQRT($H$14)*D10024) -> 205.60583 | G10024: =MAX(E10024-$H$16, 0) -> 0 | H10024: =MAX(F10024-$H$16, 0) -> 0

Sheet Sensitivity & Scenario
C3: Sensitivity Analysis
E4: T
D5: ='BSM Model'!J9 -> 22.625253 | E5: ='BSM Model'!K9 -> 0.1 | F5: ='BSM Model'!L9 -> 0.2 | G5: ='BSM Model'!M9 -> 0.3 | H5: ='BSM Model'!N9 -> 0.4 | I5: ='BSM Model'!O9 -> 0.5 | J5: ='BSM Model'!P9 -> 0.6 | K5: ='BSM Model'!Q9 -> 0.7 | ... N5: ='BSM Model'!T9 -> 1
C6: σ | D6: ='BSM Model'!J10 -> 0.1 | E6: ='BSM Model'!K10 -> 2.5798628 | F6: ='BSM Model'!L10 -> 4.249105 | G6: ='BSM Model'!M10 -> 5.6443719 | H6: ='BSM Model'!N10 -> 6.8953425 | I6: ='BSM Model'!O10 -> 8.0535159 | J6: ='BSM Model'!P10 -> 9.1455436 | K6: ='BSM Model'!Q10 -> 10.187314 | ... N6: ='BSM Model'!T10 -> 13.100048
D7: ='BSM Model'!J11 -> 0.15 | E7: ='BSM Model'!K11 -> 4.1351594 | F7: ='BSM Model'!L11 -> 6.459424 | G7: ='BSM Model'!M11 -> 8.3451161 | H7: ='BSM Model'!N11 -> 10.000971 | I7: ='BSM Model'!O11 -> 11.508826 | J7: ='BSM Model'!P11 -> 12.910873 | K7: ='BSM Model'!Q11 -> 14.232255 | ... N7: ='BSM Model'!T11 -> 17.853427
D8: ='BSM Model'!J12 -> 0.2 | E8: ='BSM Model'!K12 -> 5.6960176 | F8: ='BSM Model'!L12 -> 8.6692883 | G8: ='BSM Model'!M12 -> 11.044882 | H8: ='BSM Model'!N12 -> 13.107801 | I8: ='BSM Model'!O12 -> 14.969311 | J8: ='BSM Model'!P12 -> 16.686714 | K8: ='BSM Model'!Q12 -> 18.294145 | ... N8: ='BSM Model'!T12 -> 22.6482
D9: ='BSM Model'!J13 -> 0.25 | E9: ='BSM Model'!K13 -> 7.2588332 | F9: ='BSM Model'!L13 -> 10.878197 | G9: ='BSM Model'!M13 -> 13.742841 | H9: ='BSM Model'!N13 -> 16.212936 | I9: ='BSM Model'!O13 -> 18.428842 | J9: ='BSM Model'!P13 -> 20.462803 | K9: ='BSM Model'!Q13 -> 22.357859 | ... N9: ='BSM Model'!T13 -> 27.451233
D10: ='BSM Model'!J14 -> 0.3 | E10: ='BSM Model'!K14 -> 8.8223351 | F10: ='BSM Model'!L14 -> 13.085801 | G10: ='BSM Model'!M14 -> 16.438379 | H10: ='BSM Model'!N14 -> 19.314898 | I10: ='BSM Model'!O14 -> 21.884653 | J10: ='BSM Model'!P14 -> 24.23477 | K10: ='BSM Model'!Q14 -> 26.417153 | ... N10: ='BSM Model'!T14 -> 32.2494
D11: ='BSM Model'!J15 -> 0.35 | E11: ='BSM Model'!K15 -> 10.385922 | F11: ='BSM Model'!L15 -> 15.291792 | G11: ='BSM Model'!M15 -> 19.130948 | H11: ='BSM Model'!N15 -> 22.412612 | I11: ='BSM Model'!O15 -> 25.334952 | J11: ='BSM Model'!P15 -> 27.999944 | K11: ='BSM Model'!Q15 -> 30.46835 | ... N11: ='BSM Model'!T15 -> 37.035378
D12: ='BSM Model'!J16 -> 0.4 | E12: ='BSM Model'!K16 -> 11.949245 | F12: ='BSM Model'!L16 -> 17.495881 | G12: ='BSM Model'!M16 -> 21.820024 | H12: ='BSM Model'!N16 -> 25.505162 | I12: ='BSM Model'!O16 -> 28.77831 | J12: ='BSM Model'!P16 -> 31.756298 | K12: ='BSM Model'!Q16 -> 34.508746 | ... N12: ='BSM Model'!T16 -> 41.804058
D13: ='BSM Model'!J17 -> 0.45 | E13: ='BSM Model'!K17 -> 13.512066 | F13: ='BSM Model'!L17 -> 19.697784 | G13: ='BSM Model'!M17 -> 24.505095 | H13: ='BSM Model'!N17 -> 28.5917 | I13: ='BSM Model'!O17 -> 32.213469 | J13: ='BSM Model'!P17 -> 35.502098 | K13: ='BSM Model'!Q17 -> 38.53608 | ... N13: ='BSM Model'!T17 -> 46.551341
D14: ='BSM Model'!J18 -> 0.5 | E14: ='BSM Model'!K18 -> 15.074204 | F14: ='BSM Model'!L18 -> 21.897224 | G14: ='BSM Model'!M18 -> 27.185657 | H14: ='BSM Model'!N18 -> 31.671417 | I14: ='BSM Model'!O18 -> 35.639258 | J14: ='BSM Model'!P18 -> 39.235765 | K14: ='BSM Model'!Q18 -> 42.548323 | ... N14: ='BSM Model'!T18 -> 51.273659
C17: Scenario Analysis
C19: Key Assumptions
C21: Assumption | H21: Downside Case | J21: Base Case | M21: Upside Case
C22: Spot price | G22: S0 | H22: 235 | K22: ='BSM Model'!E9 -> 247.99 | M22: 260
C23: Strike | G23: K | H23: ='BSM Model'!E14 -> 250 | K23: ='BSM Model'!E14 -> 250 | M23: ='BSM Model'!E14 -> 250
C24: Time to maturity | G24: T | H24: ='BSM Model'!E15 -> 0.5 | K24: ='BSM Model'!E15 -> 0.5 | M24: ='BSM Model'!E15 -> 0.5
C25: Risk-free rate | G25: r | H25: ='BSM Model'!E16 -> 0.037438 | K25: ='BSM Model'!E16 -> 0.037438 | M25: ='BSM Model'!E16 -> 0.037438
C26: Dividend yield | G26: q | H26: ='BSM Model'!E17 -> 0.0042 | K26: ='BSM Model'!E17 -> 0.0042 | M26: ='BSM Model'!E17 -> 0.0042
C27: Implied volatility | G27: σ | H27: 0.35 | K27: ='BSM Model'!E11 -> 0.31072491 | M27: 0.27
C29: Valuation Results
C31: Output | H31: Downside Case | J31: Base Case | M31: Upside Case
C32: Call option price (BSM) | H32: 18.59 | K32: =Summary!D9 -> 22.63 | M32: 27.05
C33: Delta | G33: Δ | H33: 0.4754 | K33: 0.558 | M33: 0.6496
C34: Vega (per 1% vol change) | G34: ν | H34: 0.6604 | K34: 0.69041802 | M34: 0.6789

Sheet Comps
C3: Editure Limited | Comparable Company Analysis
C5: =Cover!C5 -> 0
A7: x | C7: Overview
B9: x | C9: Key Company Assumptions
C11: Tax Rate | F11: =Tax -> #REF!
A13: x | C13: Comparable Company Analysis
B15: x | C15: Companies and Commentary
D17: Current Market Metrics
C18: Potential Companies | D18: 5-Year Beta | E18: EV / Revenue | F18: EV / EBITDA | H18: Commentary
C19: Coursera | D19: n.a. | E19: 14.36 | F19: n.a. | H19: To the left is a short list of comparable companies that were considered somewhat comparable in today's market. The goal was to identify any company that was in the Education Technology vertical and had a comparable business model to Editure. While there were three possible companies, none of these were public in 2012. As a result, we did not conduct a comparable company analysis due to lack of public information available on the public companies (not being public means we cannot calculate equity value, enterprise value and the necessary multiples). Additionally, today's market, especially due to Covid and the current downturn, is not comparable to the market in 2012.
C20: Learning Technologies Group | D20: 1.33 | E20: 7.53 | F20: 22.07
C21: Udemy | D21: n.a. | E21: 5.2 | F21: n.a.
C22: Average | D22: =AVERAGE(D19:D21) -> 1.33 | E22: =AVERAGE(E19:E21) -> 9.03 | F22: =IFERROR(AVERAGE(F19:F21),"n.a.") -> 22.07
C23: Minimum | E23: =QUARTILE(E$19:E$21,0) -> 5.2 | F23: =IFERROR(QUARTILE(F$19:F$21,0),"n.a.") -> 22.07
C24: Q1 | E24: =QUARTILE(E$19:E$21,1) -> 6.365 | F24: =IFERROR(QUARTILE(F$19:F$21,1),"n.a.") -> 22.07
C25: Q2 | E25: =QUARTILE(E$19:E$21,2) -> 7.53 | F25: =IFERROR(QUARTILE(F$19:F$21,2),"n.a.") -> 22.07
C26: Q3 | E26: =QUARTILE(E$19:E$21,3) -> 10.945 | F26: =IFERROR(QUARTILE(F$19:F$21,3),"n.a.") -> 22.07
C27: Maximum | E27: =QUARTILE(E$19:E$21,4) -> 14.36 | F27: =IFERROR(QUARTILE(F$19:F$21,4),"n.a.") -> 22.07
A29: x | B29: x

Sheet Support>>

Sheet Historical Prices
A1: Bloomberg Evidence – Historical Prices
A2: Security | B2: AAPL US Equity
A3: Start Date | B3: 45737
A4: End Date | B4: 46101
A5: Period | B5: D
A6: Currency | B6: USD
A8: Date | B8: PX_LAST | C8: PX_BID | D8: Daily Return | E8: 180D Volatility | F8: Annualized Volatility
A9: 46101 | B9: 247.99 | C9: 248.16 | D9: =LN(B9/B10) -> -0.0039038182 | E9: =_xlfn.STDEV.S(D9:D188) -> 0.014211842 | F9: =E9*SQRT(252) -> 0.22560599
A10: 46100 | B10: 248.96 | C10: 248.86 | D10: =LN(B10/B11) -> -0.0039286481 | E10: =_xlfn.STDEV.S(D10:D189) -> 0.014294146 | F10: =E10*SQRT(252) -> 0.22691254
A11: 46099 | B11: 249.94 | C11: 249.88 | D11: =LN(B11/B12) -> -0.01701848 | E11: =_xlfn.STDEV.S(D11:D190) -> 0.014316418 | F11: =E11*SQRT(252) -> 0.22726609
A12: 46098 | B12: 254.23 | C12: 254.21 | D12: =LN(B12/B13) -> 0.005561596 | E12: =_xlfn.STDEV.S(D12:D191) -> 0.014321623 | F12: =E12*SQRT(252) -> 0.22734871
A13: 46097 | B13: 252.82 | C13: 252.77 | D13: =LN(B13/B14) -> 0.01073697 | E13: =_xlfn.STDEV.S(D13:D192) -> 0.014318216 | F13: =E13*SQRT(252) -> 0.22729463
A14: 46094 | B14: 250.12 | C14: 250.01 | D14: =LN(B14/B15) -> -0.022298702 | E14: =_xlfn.STDEV.S(D14:D193) -> 0.014303752 | F14: =E14*SQRT(252) -> 0.22706503
A15: 46093 | B15: 255.76 | C15: 255.75 | D15: =LN(B15/B16) -> -0.019552668 | E15: =_xlfn.STDEV.S(D15:D194) -> 0.014199685 | F15: =E15*SQRT(252) -> 0.22541301
A16: 46092 | B16: 260.81 | C16: 260.77 | D16: =LN(B16/B17) -> -7.6681236e-05 | E16: =_xlfn.STDEV.S(D16:D195) -> 0.014123839 | F16: =E16*SQRT(252) -> 0.22420899
A17: 46091 | B17: 260.83 | C17: 260.73 | D17: =LN(B17/B18) -> 0.0036488681 | E17: =_xlfn.STDEV.S(D17:D196) -> 0.014123599 | F17: =E17*SQRT(252) -> 0.22420519
A18: 46090 | B18: 259.88 | C18: 259.89 | D18: =LN(B18/B19) -> 0.0093556178 | E18: =_xlfn.STDEV.S(D18:D197) -> 0.014207478 | F18: =E18*SQRT(252) -> 0.22553672
A19: 46087 | B19: 257.46 | C19: 257.39 | D19: =LN(B19/B20) -> -0.010932026 | E19: =_xlfn.STDEV.S(D19:D198) -> 0.014197542 | F19: =E19*SQRT(252) -> 0.22537899
A20: 46086 | B20: 260.29 | C20: 260.21 | D20: =LN(B20/B21) -> -0.0085308756 | E20: =_xlfn.STDEV.S(D20:D199) -> 0.014215084 | F20: =E20*SQRT(252) -> 0.22565746
... A79: 45999 | B79: 277.89 | C79: 277.95 | D79: =LN(B79/B80) -> -0.0031975884 | E79: =_xlfn.STDEV.S(D79:D258) -> 0.021539705 | F79: =E79*SQRT(252) -> 0.34193221
A80: 45996 | B80: 278.78 | C80: 278.69 | D80: =LN(B80/B81) -> -0.0068635431
A81: 45995 | B81: 280.7 | C81: 280.65 | D81: =LN(B81/B82) -> -0.012215784
A82: 45994 | B82: 284.15 | C82: 284.15 | D82: =LN(B82/B83) -> -0.0071536582
A83: 45993 | B83: 286.19 | C83: 286.23 | D83: =LN(B83/B84) -> 0.010855734
A84: 45992 | B84: 283.1 | C84: 283.24 | D84: =LN(B84/B85) -> 0.015126189
A85: 45989 | B85: 278.85 | C85: 278.85 | D85: =LN(B85/B86) -> 0.0046729057
A86: 45987 | B86: 277.55 | C86: 277.47 | D86: =LN(B86/B87) -> 0.0020919001
A87: 45986 | B87: 276.97 | C87: 276.88 | D87: =LN(B87/B88) -> 0.0037982284
A88: 45985 | B88: 275.92 | C88: 275.8 | D88: =LN(B88/B89) -> 0.016185662
A89: 45982 | B89: 271.49 | C89: 271.42 | D89: =LN(B89/B90) -> 0.019489589
A90: 45981 | B90: 266.25 | C90: 266.26 | D90: =LN(B90/B91) -> -0.0086386356
A91: 45980 | B91: 268.56 | C91: 268.52 | D91: =LN(B91/B92) -> 0.0041791106
... A258: 45740 | B258: 220.73 | C258: 220.37 | D258: =LN(B258/B259) -> 0.011207407
A259: 45737 | B259: 218.27 | C259: 218.2

Sheet Option Monitor
A1: Bloomberg Evidence – Implied Volatility
A2: Calls
A3: Strike | B3: Ticker | C3: Bid | D3: Ask | E3: Last | F3: IVM | G3: Volm | H3: Strike | I3: Ticker | J3: Bid | K3: Ask | L3: Last | M3: IVM | N3: Volm
A4: 18-Sep-26 (181d); CSize 100; R 4.03
A5: 240 | B5: AAPL 9/18/26 C240 | C5: 28 | D5: 28.65 | E5: 28.75 | F5: 32.080051 | G5: 59 | H5: 240 | I5: AAPL 9/18/26 P240 | J5: 16.1 | K5: 16.35 | L5: 17 | M5: 31.75675 | N5: 153
A6: 245 | B6: AAPL 9/18/26 C245 | C6: 24.85 | D6: 25.6 | E6: 24.700001 | F6: 31.309641 | G6: 19 | H6: 245 | I6: AAPL 9/18/26 P245 | J6: 18 | K6: 18.299999 | L6: 19 | M6: 31.086559 | N6: 331
A7: 250 | B7: AAPL 9/18/26 C250 | C7: 22.450001 | D7: 22.85 | E7: 22.549999 | F7: 31.072491 | G7: 644 | H7: 250 | I7: AAPL 9/18/26 P250 | J7: 19.85 | K7: 20.4 | L7: 20.379999 | M7: 30.238171 | N7: 222
A8: 255 | B8: AAPL 9/18/26 C255 | C8: 19.75 | D8: 20.15 | E8: 19.75 | F8: 30.40659 | G8: 237 | H8: 255 | I8: AAPL 9/18/26 P255 | J8: 22.4 | K8: 22.700001 | L8: 23.1 | M8: 29.781891 | N8: 315
A9: 260 | B9: AAPL 9/18/26 C260 | C9: 17.299999 | D9: 17.549999 | E9: 17.299999 | F9: 29.74234 | G9: 185 | H9: 260 | I9: AAPL 9/18/26 P260 | J9: 24.75 | K9: 25.25 | L9: 25.200001 | M9: 29.071951 | N9: 64
A10: 16-Oct-26 (209d); CSize 100; R 4.04
A11: 240 | B11: AAPL 10/16/26 C240 | C11: 28.65 | D11: 30.6 | E11: 30.75 | F11: 30.444059 | G11: 3 | H11: 240 | I11: AAPL 10/16/26 P240 | J11: 16.9 | K11: 17.450001 | L11: 17.450001 | M11: 30.755739 | N11: 11
A12: 245 | B12: AAPL 10/16/26 C245 | C12: 27.049999 | D12: 28.049999 | E12: 27 | F12: 31.128981 | G12: 32 | H12: 245 | I12: AAPL 10/16/26 P245 | J12: 18.700001 | K12: 19.4 | L12: 20.1 | M12: 30.067249 | N12: 15
A13: 250 | B13: AAPL 10/16/26 C250 | C13: 24.25 | D13: 25.1 | E13: 24.15 | F13: 30.495899 | G13: 21 | H13: 250 | I13: AAPL 10/16/26 P250 | J13: 21.299999 | K13: 21.549999 | L13: 21.4 | M13: 29.831881 | N13: 6
A14: 255 | B14: AAPL 10/16/26 C255 | C14: 21.6 | D14: 22.35 | E14: 21.5 | F14: 29.89362 | G14: 29 | H14: 255 | I14: AAPL 10/16/26 P255 | J14: 23.15 | K14: 24.6 | L14: 23.549999 | M14: 29.463511 | N14: 9
A15: 260 | B15: AAPL 10/16/26 C260 | C15: 19.1 | D15: 19.450001 | E15: 19.08 | F15: 29.08544 | G15: 63 | H15: 260 | I15: AAPL 10/16/26 P260 | J15: 25.25 | K15: 26.4 | L15: 26.15 | M15: 28.184299 | N15: 1
A16: 20-Nov-26 (244d); CSize 100; R 4.05
A17: 240 | B17: AAPL 11/20/26 C240 | C17: 31 | D17: 33.5 | E17: 32.419998 | F17: 30.976179 | G17: 42 | H17: 240 | I17: AAPL 11/20/26 P240 | J17: 18.799999 | K17: 19 | L17: 18.549999 | M17: 31.112419 | N17: 35
A18: 245 | B18: AAPL 11/20/26 C245 | C18: 28.1 | D18: 30.549999 | E18: 29.5 | F18: 30.492741 | G18: 86 | H18: 245 | I18: AAPL 11/20/26 P245 | J18: 20.75 | K18: 21 | L18: 20.700001 | M18: 30.568199 | N18: 53
A19: 250 | B19: AAPL 11/20/26 C250 | C19: 26.6 | D19: 26.799999 | E19: 26.73 | F19: 30.20961 | G19: 51 | H19: 250 | I19: AAPL 11/20/26 P250 | J19: 22.450001 | K19: 23.200001 | L19: 23.33 | M19: 29.808701 | N19: 425
A20: 255 | B20: AAPL 11/20/26 C255 | C20: 24 | D20: 24.950001 | E20: 24.299999 | F20: 30.234131 | G20: 27 | H20: 255 | I20: AAPL 11/20/26 P255 | J20: 24.75 | K20: 25.549999 | L20: 25.459999 | M20: 29.31222 | N20: 13
A21: 260 | B21: AAPL 11/20/26 C260 | C21: 21.5 | D21: 22.1 | E21: 21.450001 | F21: 29.5299 | G21: 90 | H21: 260 | I21: AAPL 11/20/26 P260 | J21: 27.299999 | K21: 28.700001 | L21: 27.799999 | M21: 29.273081 | N21: 2
A22: 18-Dec-26 (272d); CSize 100; R 4.05
A23: 240 | B23: AAPL 12/18/26 C240 | C23: 33.599998 | D23: 34.25 | E23: 33.580002 | F23: 30.947901 | G23: 13 | H23: 240 | I23: AAPL 12/18/26 P240 | J23: 19.700001 | K23: 19.9 | L23: 20.15 | M23: 30.889891 | N23: 65
A24: 245 | B24: AAPL 12/18/26 C245 | C24: 30.4 | D24: 31.6 | E24: 31 | F24: 30.466789 | G24: 62 | H24: 245 | I24: AAPL 12/18/26 P245 | J24: 21.700001 | K24: 21.950001 | L24: 21.65 | M24: 30.4235 | N24: 25
A25: 250 | B25: AAPL 12/18/26 C250 | C25: 28.25 | D25: 28.450001 | E25: 28.299999 | F25: 30.15535 | G25: 204 | H25: 250 | I25: AAPL 12/18/26 P250 | J25: 23.9 | K25: 24.1 | L25: 24.85 | M25: 29.965891 | N25: 209
A26: 255 | B26: AAPL 12/18/26 C255 | C26: 25.6 | D26: 25.799999 | E26: 25.700001 | F26: 29.685711 | G26: 33 | H26: 255 | I26: AAPL 12/18/26 P255 | J26: 25.85 | K26: 26.5 | L26: 26.049999 | M26: 29.33502 | N26: 44
A27: 260 | B27: AAPL 12/18/26 C260 | C27: 23.1 | D27: 23.6 | E27: 23.450001 | F27: 29.404449 | G27: 157 | H27: 260 | I27: AAPL 12/18/26 P260 | J27: 28.450001 | K27: 29 | L27: 28.83 | M27: 28.95129 | N27: 10
A28: 15-Jan-27 (300d); CSize 100; R 4.05
A29: 230 | B29: AAPL 1/15/27 C230 | C29: 41.25 | D29: 42.5 | E29: 40.900002 | F29: 32.056629 | G29: 206 | H29: 230 | I29: AAPL 1/15/27 P230 | J29: 16.950001 | K29: 17.15 | L29: 17.18 | M29: 31.69038 | N29: 890
A30: 240 | B30: AAPL 1/15/27 C240 | C30: 35.349998 | D30: 36.549999 | E30: 35.57 | F30: 31.416821 | G30: 27 | H30: 240 | I30: AAPL 1/15/27 P240 | J30: 20.35 | K30: 20.799999 | L30: 20.76 | M30: 30.62125 | N30: 313
A31: 250 | B31: AAPL 1/15/27 C250 | C31: 29.85 | D31: 30.15 | E31: 29.790001 | F31: 30.18906 | G31: 526 | H31: 250 | I31: AAPL 1/15/27 P250 | J31: 24.75 | K31: 25 | L31: 25.5 | M31: 29.84721 | N31: 496
A32: 260 | B32: AAPL 1/15/27 C260 | C32: 24.75 | D32: 25.200001 | E32: 24.15 | F32: 29.447241 | G32: 282 | H32: 260 | I32: AAPL 1/15/27 P260 | J32: 29.35 | K32: 29.85 | L32: 30.5 | M32: 28.897791 | N32: 207
A33: 270 | B33: AAPL 1/15/27 C270 | C33: 20.200001 | D33: 20.6 | E33: 20.24 | F33: 28.622061 | G33: 332 | H33: 270 | I33: AAPL 1/15/27 P270 | J33: 34.799999 | K33: 35.349998 | L33: 35.73 | M33: 28.110941 | N33: 13
A34: 19-Mar-27 (363d); CSize 100; R 4.06
A35: 230 | B35: AAPL 3/19/27 C230 | C35: 42.900002 | D35: 45.599998 | E35: 44.900002 | F35: 30.88468 | G35: 1 | H35: 230 | I35: AAPL 3/19/27 P230 | J35: 18.75 | K35: 19.700001 | L35: 18.889999 | M35: 31.8367 | N35: 13
A36: 240 | B36: AAPL 3/19/27 C240 | C36: 36.700001 | D36: 40.25 | E36: 38.869999 | F36: 30.40517 | G36: 11 | H36: 240 | I36: AAPL 3/19/27 P240 | J36: 22.5 | K36: 23.5 | L36: 22.799999 | M36: 31.03853 | N36: 42
A37: 250 | B37: AAPL 3/19/27 C250 | C37: 33.349998 | D37: 34.299999 | E37: 33.360001 | F37: 30.594851 | G37: 45 | H37: 250 | I37: AAPL 3/19/27 P250 | J37: 26.799999 | K37: 27.9 | L37: 27.299999 | M37: 30.34025 | N37: 82
A38: 260 | B38: AAPL 3/19/27 C260 | C38: 28.299999 | D38: 29.15 | E38: 28.32 | F38: 29.83107 | G38: 164 | H38: 260 | I38: AAPL 3/19/27 P260 | J38: 30.9 | K38: 32.900002 | L38: 31.549999 | M38: 29.31743 | N38: 23
A39: 270 | B39: AAPL 3/19/27 C270 | C39: 23.75 | D39: 24.5 | E39: 23.639999 | F39: 29.10586 | G39: 60 | H39: 270 | I39: AAPL 3/19/27 P270 | J39: 37 | K39: 37.450001 | L39: 36.700001 | M39: 28.53727 | N39: 16
A40: 17-Jun-27 (453d); CSize 100; R 4.04
A41: 230 | B41: AAPL 6/17/27 C230 | C41: 49.25 | D41: 49.700001 | E41: 49.349998 | F41: 31.795811 | G41: 8 | H41: 230 | I41: AAPL 6/17/27 P230 | J41: 21.299999 | K41: 21.549999 | L41: 21.6 | M41: 31.44865 | N41: 3
A42: 240 | B42: AAPL 6/17/27 C240 | C42: 43.400002 | D42: 43.849998 | E42: 43.419998 | F42: 31.108521 | G42: 235 | H42: 240 | I42: AAPL 6/17/27 P240 | J42: 25.1 | K42: 25.35 | L42: 25.360001 | M42: 30.69215 | N42: 44
A43: 250 | B43: AAPL 6/17/27 C250 | C43: 37.950001 | D43: 38.400002 | E43: 38.040001 | F43: 30.44289 | G43: 155 | H43: 250 | I43: AAPL 6/17/27 P250 | J43: 29 | K43: 29.75 | L43: 29.65 | M43: 29.863091 | N43: 25
A44: 260 | B44: AAPL 6/17/27 C260 | C44: 32.950001 | D44: 33.349998 | E44: 33.32 | F44: 29.807831 | G44: 325 | H44: 260 | I44: AAPL 6/17/27 P260 | J44: 34.25 | K44: 34.599998 | L44: 35.049999 | M44: 29.424549 | N44: 7
A45: 270 | B45: AAPL 6/17/27 C270 | C45: 28.4 | D45: 29.1 | E45: 28.049999 | F45: 29.37273 | G45: 376 | H45: 270 | I45: AAPL 6/17/27 P270 | J45: 39.549999 | K45: 39.950001 | L45: 38.849998 | M45: 28.803499 | N45: 0
A46: 17-Dec-27 (636d); CSize 100; R 4.00
A47: 240 | B47: AAPL 12/17/27 C240 | C47: 50.299999 | D47: 52.25 | E47: 51.209999 | F47: 30.8025 | G47: 2 | H47: 240 | I47: AAPL 12/17/27 P240 | J47: 28.9 | K47: 29.35 | L47: 28.15 | M47: 30.384291 | N47: 0
A48: 245 | B48: AAPL 12/17/27 C245 | C48: 46.700001 | D48: 49.650002 | E48: 48.029999 | F48: 30.18605 | G48: 4 | H48: 245 | I48: AAPL 12/17/27 P245 | J48: 31.15 | K48: 31.5 | L48: 30.799999 | M48: 30.1402 | N48: 0
A49: 250 | B49: AAPL 12/17/27 C250 | C49: 44.599998 | D49: 46.349998 | E49: 45 | F49: 29.85034 | G49: 13 | H49: 250 | I49: AAPL 12/17/27 P250 | J49: 33.349998 | K49: 33.799999 | L49: 33.529999 | M49: 29.873341 | N49: 0
A50: 255 | B50: AAPL 12/17/27 C255 | C50: 43.25 | D50: 43.950001 | E50: 43.400002 | F50: 30.0895 | G50: 3 | H50: 255 | I50: AAPL 12/17/27 P255 | J50: 35.75 | K50: 36.150002 | L50: 34.700001 | M50: 29.616631 | N50: 0
A51: 260 | B51: AAPL 12/17/27 C260 | C51: 40.950001 | D51: 41.299999 | E51: 40.700001 | F51: 29.79567 | G51: 19 | H51: 260 | I51: AAPL 12/17/27 P260 | J51: 38.200001 | K51: 38.650002 | L51: 37.919998 | M51: 29.366699 | N51: 1
A52: 21-Jan-28 (671d); CSize 100; R 4.00
A53: 230 | B53: AAPL 1/21/28 C230 | C53: 57.099998 | D53: 58.650002 | E53: 58.279999 | F53: 31.02846 | G53: 2 | H53: 230 | I53: AAPL 1/21/28 P230 | J53: 25.6 | K53: 26 | L53: 25.940001 | M53: 30.904831 | N53: 5
A54: 240 | B54: AAPL 1/21/28 C240 | C54: 52.5 | D54: 53 | E54: 52.860001 | F54: 30.87241 | G54: 70 | H54: 240 | I54: AAPL 1/21/28 P240 | J54: 29.700001 | K54: 30 | L54: 30.17 | M54: 30.386061 | N54: 18
A55: 250 | B55: AAPL 1/21/28 C250 | C55: 47.299999 | D55: 47.75 | E55: 47.150002 | F55: 30.3599 | G55: 117 | H55: 250 | I55: AAPL 1/21/28 P250 | J55: 34 | K55: 34.5 | L55: 34.5 | M55: 29.847549 | N55: 43
A56: 260 | B56: AAPL 1/21/28 C260 | C56: 42.450001 | D56: 43.700001 | E56: 42.549999 | F56: 30.208549 | G56: 11 | H56: 260 | I56: AAPL 1/21/28 P260 | J56: 38.950001 | K56: 39.349998 | L56: 38.950001 | M56: 29.40023 | N56: 61
A57: 270 | B57: AAPL 1/21/28 C270 | C57: 37.900002 | D57: 38.299999 | E57: 38.200001 | F57: 29.425079 | G57: 9 | H57: 270 | I57: AAPL 1/21/28 P270 | J57: 44.200001 | K57: 44.700001 | L57: 40.669998 | M57: 28.95097 | N57: 0
A58: 17-Mar-28 (727d); CSize 100; R 3.98
A59: 230 | B59: AAPL 3/17/28 C230 | C59: 57.5 | D59: 61.400002 | E59: 60.150002 | F59: 30.58153 | G59: 2 | H59: 230 | I59: AAPL 3/17/28 P230 | J59: 26.4 | K59: 26.85 | L59: 26.65 | M59: 30.68767 | N59: 10
A60: 240 | B60: AAPL 3/17/28 C240 | C60: 53.400002 | D60: 55.150002 | E60: 53.459999 | F60: 30.37785 | G60: 91 | H60: 240 | I60: AAPL 3/17/28 P240 | J60: 30.450001 | K60: 30.950001 | L60: 30.75 | M60: 30.20178 | N60: 41
A61: 250 | B61: AAPL 3/17/28 C250 | C61: 47 | D61: 51.299999 | E61: 49.459999 | F61: 29.94636 | G61: 4 | H61: 250 | I61: AAPL 3/17/28 P250 | J61: 34.900002 | K61: 35.450001 | L61: 34.950001 | M61: 29.73115 | N61: 22
A62: 260 | B62: AAPL 3/17/28 C260 | C62: 42.299999 | D62: 46.299999 | E62: 43.959999 | F62: 29.50078 | G62: 11 | H62: 260 | I62: AAPL 3/17/28 P260 | J62: 39.75 | K62: 40.349998 | L62: 38.549999 | M62: 29.28821 | N62: 0
A63: 270 | B63: AAPL 3/17/28 C270 | C63: 40 | D63: 40.450001 | E63: 40.200001 | F63: 29.39572 | G63: 2 | H63: 270 | I63: AAPL 3/17/28 P270 | J63: 45.099998 | K63: 45.700001 | L63: 44.650002 | M63: 28.907061 | N63: 0
A64: 15-Dec-28 (1000d); CSize 100; R 3.93
A65: 230 | B65: AAPL 12/15/28 C230 | C65: 66.050003 | D65: 69.949997 | E65: 68.330002 | F65: 30.00242 | G65: 3 | H65: 230 | I65: AAPL 12/15/28 P230 | J65: 29.950001 | K65: 30.6 | L65: 30.33 | M65: 30.106871 | N65: 0
A66: 240 | B66: AAPL 12/15/28 C240 | C66: 61.049999 | D66: 64.699997 | E66: 61.509998 | F66: 29.734369 | G66: 16 | H66: 240 | I66: AAPL 12/15/28 P240 | J66: 34.099998 | K66: 34.75 | L66: 34.509998 | M66: 29.675529 | N66: 0
A67: 250 | B67: AAPL 12/15/28 C250 | C67: 57.349998 | D67: 59.400002 | E67: 58.580002 | F67: 29.686081 | G67: 8 | H67: 250 | I67: AAPL 12/15/28 P250 | J67: 38.549999 | K67: 39.299999 | L67: 38.959999 | M67: 29.28681 | N67: 1
A68: 260 | B68: AAPL 12/15/28 C260 | C68: 52.049999 | D68: 55.349998 | E68: 53.790001 | F68: 29.33145 | G68: 106 | H68: 260 | I68: AAPL 12/15/28 P260 | J68: 43.5 | K68: 44.200001 | L68: 43.919998 | M68: 28.94286 | N68: 1
A69: 270 | B69: AAPL 12/15/28 C270 | C69: 48.799999 | D69: 50.049999 | E69: 49.349998 | F69: 29.08733 | G69: 54 | H69: 270 | I69: AAPL 12/15/28 P270 | J69: 48.700001 | K69: 49.450001 | L69: 49.029999 | M69: 28.58885 | N69: 2
A70: 17-Apr-26 (27d); CSize 100; R 3.99
A71: 242.5 | B71: AAPL 4/17/26 C242.5 | C71: 0 | D71: 0 | E71: 0 | G71: 0 | H71: 242.5 | I71: AAPL 4/17/26 P242.5 | J71: 0 | K71: 0 | L71: 0 | N71: 0
A72: 245 | B72: AAPL 4/17/26 C245 | C72: 9.75 | D72: 10.2 | E72: 9.6999998 | F72: 29.67083 | G72: 1039 | H72: 245 | I72: AAPL 4/17/26 P245 | J72: 5.9000001 | K72: 6.0500002 | L72: 6.1500001 | M72: 28.42597 | N72: 935
A73: 247.5 | B73: AAPL 4/17/26 C247.5 | C73: 0 | D73: 0 | E73: 0 | G73: 0 | H73: 247.5 | I73: AAPL 4/17/26 P247.5 | J73: 0 | K73: 0 | L73: 0 | N73: 0
A74: 250 | B74: AAPL 4/17/26 C250 | C74: 6.75 | D74: 6.9000001 | E74: 6.6999998 | F74: 27.38777 | G74: 3439 | H74: 250 | I74: AAPL 4/17/26 P250 | J74: 7.9000001 | K74: 8.1000004 | L74: 8.0699997 | M74: 26.79759 | N74: 1538
A75: 252.5 | B75: AAPL 4/17/26 C252.5 | C75: 0 | D75: 0 | E75: 0 | G75: 0 | H75: 252.5 | I75: AAPL 4/17/26 P252.5 | J75: 0 | K75: 0 | L75: 0 | N75: 0
A76: 15-May-26 (55d); CSize 100; R 3.99
A77: 240 | B77: AAPL 5/15/26 C240 | C77: 17.35 | D77: 17.950001 | E77: 17.35 | F77: 32.652988 | G77: 182 | H77: 240 | I77: AAPL 5/15/26 P240 | J77: 8.0500002 | K77: 8.25 | L77: 8.2600002 | M77: 31.95706 | N77: 969
A78: 245 | B78: AAPL 5/15/26 C245 | C78: 14.1 | D78: 14.7 | E78: 14.1 | F78: 31.583639 | G78: 260 | H78: 245 | I78: AAPL 5/15/26 P245 | J78: 9.6000004 | K78: 9.9499998 | L78: 10.35 | M78: 30.520809 | N78: 719
A79: 250 | B79: AAPL 5/15/26 C250 | C79: 11.2 | D79: 11.6 | E79: 11.25 | F79: 30.23769 | G79: 1149 | H79: 250 | I79: AAPL 5/15/26 P250 | J79: 11.55 | K79: 12 | L79: 12.05 | M79: 29.31003 | N79: 459
A80: 255 | B80: AAPL 5/15/26 C255 | C80: 8.6000004 | D80: 8.75 | E80: 8.6800003 | F80: 28.755171 | G80: 1201 | H80: 255 | I80: AAPL 5/15/26 P255 | J80: 13.75 | K80: 14.5 | L80: 14.7 | M80: 28.09453 | N80: 87
A81: 260 | B81: AAPL 5/15/26 C260 | C81: 6.4000001 | D81: 6.75 | E81: 6.5 | F81: 27.989361 | G81: 2953 | H81: 260 | I81: AAPL 5/15/26 P260 | J81: 16.5 | K81: 17.299999 | L81: 17.450001 | M81: 26.78863 | N81: 203
A82: 18-Jun-26 (89d); CSize 100; R 3.99
A83: 240 | B83: AAPL 6/18/26 C240 | C83: 20.799999 | D83: 21.6 | E83: 20.77 | F83: 32.611198 | G83: 85 | H83: 240 | I83: AAPL 6/18/26 P240 | J83: 10.5 | K83: 10.85 | L83: 11.05 | M83: 31.39341 | N83: 338
A84: 245 | B84: AAPL 6/18/26 C245 | C84: 17.65 | D84: 18.299999 | E84: 17.58 | F84: 31.510111 | G84: 362 | H84: 245 | I84: AAPL 6/18/26 P245 | J84: 12.25 | K84: 12.65 | L84: 12.71 | M84: 30.451509 | N84: 478
A85: 250 | B85: AAPL 6/18/26 C250 | C85: 14.7 | D85: 15.25 | E85: 14.85 | F85: 30.40118 | G85: 555 | H85: 250 | I85: AAPL 6/18/26 P250 | J85: 14.4 | K85: 14.7 | L85: 14.98 | M85: 29.767401 | N85: 231
A86: 255 | B86: AAPL 6/18/26 C255 | C86: 12.05 | D86: 12.35 | E86: 11.95 | F86: 29.242149 | G86: 327 | H86: 255 | I86: AAPL 6/18/26 P255 | J86: 16.549999 | K86: 17.1 | L86: 17.4 | M86: 28.800659 | N86: 87
A87: 260 | B87: AAPL 6/18/26 C260 | C87: 9.6999998 | D87: 9.8999996 | E87: 9.6700001 | F87: 28.36195 | G87: 1429 | H87: 260 | I87: AAPL 6/18/26 P260 | J87: 18.85 | K87: 19.75 | L87: 20.1 | M87: 27.40523 | N87: 715
A88: 17-Jul-26 (118d); CSize 100; R 4.00
A89: 240 | B89: AAPL 7/17/26 C240 | C89: 22.75 | D89: 23.35 | E89: 23 | F89: 31.261971 | G89: 7 | H89: 240 | I89: AAPL 7/17/26 P240 | J89: 12.15 | K89: 12.5 | L89: 12.34 | M89: 31.05443 | N89: 184
A90: 245 | B90: AAPL 7/17/26 C245 | C90: 20 | D90: 20.65 | E90: 20.049999 | F90: 31.1679 | G90: 310 | H90: 245 | I90: AAPL 7/17/26 P245 | J90: 13.95 | K90: 14.35 | L90: 15.01 | M90: 30.1786 | N90: 768
A91: 250 | B91: AAPL 7/17/26 C250 | C91: 17.049999 | D91: 17.700001 | E91: 17.049999 | F91: 30.2677 | G91: 369 | H91: 250 | I91: AAPL 7/17/26 P250 | J91: 16.1 | K91: 16.450001 | L91: 16.700001 | M91: 29.45573 | N91: 149
A92: 255 | B92: AAPL 7/17/26 C255 | C92: 14.4 | D92: 14.65 | E92: 14.35 | F92: 29.1602 | G92: 94 | H92: 255 | I92: AAPL 7/17/26 P255 | J92: 18.1 | K92: 18.799999 | L92: 19.049999 | M92: 28.464649 | N92: 17
A93: 260 | B93: AAPL 7/17/26 C260 | C93: 12 | D93: 12.2 | E93: 11.96 | F93: 28.467331 | G93: 11540 | H93: 260 | I93: AAPL 7/17/26 P260 | J93: 20.85 | K93: 21.4 | L93: 21.65 | M93: 27.83897 | N93: 29

Sheet Risk-Free Rate
A1: Bloomberg Evidence – Risk-Free Rate
A2: USGG6M INDEX | C2: 3.7438 | D2: +0.0394

Sheet Dividend Yield
A1: Bloomberg Evidence – Indicated Dividend Yield
A2: Indicated Yield | B2: 0.0042
A3: Source Date | B3: 46101
